Workbook

Sheet FNOMO_CURRENT_PROGRESS
A1: FNOMO CURRENT PROGRESS
A2: Live snapshot from FNOMO_MASTER_PIPELINE after WhatsApp lead separation
A4: Metric | B4: Value | C4: Operator Meaning | D4: Next Control
A5: Total pipeline leads | B5: 185 | C5: Live pipeline health signal | D5: Keep next action current
A6: Contacted leads | B6: 99 | C6: Live pipeline health signal | D6: Keep next action current
A7: New leads | B7: 86 | C7: Live pipeline health signal | D7: Keep next action current
A8: Tier A total | B8: 49 | C8: Live pipeline health signal | D8: Keep next action current
A9: Tier A contacted | B9: 28 | C9: Live pipeline health signal | D9: Keep next action current
A10: Tier A still new | B10: 21 | C10: Highest priority drift risk | D10: Clear before Tier B work
A11: Active leads | B11: 120 | C11: Live pipeline health signal | D11: Keep next action current
A12: Waiting leads | B12: 65 | C12: Live pipeline health signal | D12: Keep next action current
A13: Contacted today | B13: 47 | C13: Live pipeline health signal | D13: Keep next action current
A14: Follow-ups due 2026-05-03 | B14: 111 | C14: Follow-up queue pressure | D14: Prepare WhatsApp/email follow-up blocks
A15: Follow-ups due 2026-05-04 | B15: 53 | C15: Follow-up queue pressure | D15: Prepare WhatsApp/email follow-up blocks
A16: WhatsApp batch rows | B16: 20 | C16: Separate raw lead batch mirrored into pipeline | D16: Use WHATSAPP_CA_LEADS for source details
A18: Stage | B18: Count
A19: Contacted | B19: 99
A20: New | B20: 86
A22: Tier | B22: Count
A23: A | B23: 49
A24: B | B24: 135
A25: C | B25: 1
A27: Immediate Operator Note
A28: Dashboard was stale because it was connected to GTM_Schedule/Outreach_Database. This sheet now shows live FNOMO_MASTER_PIPELINE progress. Tier A still-new count is 21.

Sheet Outreach_Database
A1: ID | B1: Status | C1: Outreach Date | D1: Members Joined | E1: Group Name | F1: Focus Area | G1: Outreach Script | H1: Link | I1: Platform | J1: Question Asked | K1: Your Response | L1: User Reaction | M1: Follow-up | N1: Decision Quality | O1: Admin Handle (@) | P1: Decision Proximity (1-10) | Q1: The Hook (Entry Angle) | R1: Influence Score (1-5)
A2: 1 | B2: ⚪ New | D2: 0 | E2: r/IndiaInvestments | F2: Core Wealth Validation | G2: Your group is discussing trades daily. We've built a decision layer to help members validate actions... | H2: https://www.reddit.com/r/IndiaInvestments/ | I2: Reddit
A3: 2 | B3: ⚪ New | D3: 0 | E3: r/IndianStreetBets | F3: Speculative Trade Validation | G3: Your group is discussing trades daily. We've built a decision layer to help members validate actions... | H3: https://www.reddit.com/r/IndianStreetBets/ | I3: Reddit
A4: 3 | B4: ⚪ New | D4: 0 | E4: r/PersonalFinanceIndia | F4: Long-term Planning | G4: Your group is discussing trades daily. We've built a decision layer to help members validate actions... | H4: https://www.reddit.com/r/personalfinanceindia/ | I4: Reddit
A5: 4 | B5: ⚪ New | D5: 0 | E5: r/Indiantradingbets | F5: Trade Setup Confirmation | G5: Your group is discussing trades daily. We've built a decision layer to help members validate actions... | H5: https://www.reddit.com/r/Indiantradingbets/ | I5: Reddit
A6: 5 | B6: ⚪ New | D6: 0 | E6: r/dalalstreetbets | F6: Speculative Discussions | G6: Your group is discussing trades daily. We've built a decision layer to help members validate actions... | H6: https://www.reddit.com/r/dalalstreetbets/ | I6: Reddit
A7: 6 | B7: ⚪ New | D7: 0 | E7: r/StockMarketIndia | F7: General Stock Validation | G7: Your group is discussing trades daily. We've built a decision layer to help members validate actions... | H7: https://www.reddit.com/r/StockMarketIndia/ | I7: Reddit
A8: 7 | B8: ⚪ New | D8: 0 | E8: r/FIREIndia | F8: Early Retirement Logic | G8: Your group is discussing trades daily. We've built a decision layer to help members validate actions... | H8: https://www.reddit.com/r/FIREIndia/ | I8: Reddit
A9: 8 | B9: ⚪ New | D9: 0 | E9: r/IndiaTax | F9: High-Impact Tax Decisions | G9: Your group is discussing trades daily. We've built a decision layer to help members validate actions... | H9: https://www.reddit.com/r/IndiaTax/ | I9: Reddit
A10: 9 | B10: ⚪ New | D10: 0 | E10: r/IndiaCreditCards | F10: Reward/Purchase Decisions | G10: Your group is discussing trades daily. We've built a decision layer to help members validate actions... | H10: https://www.google.com/search?q=https://www.reddit.com/r/IndiaCreditCards/ | I10: Reddit
A11: 10 | B11: ⚪ New | D11: 0 | E11: r/StartupIndia | F11: Founders' Financial Planning | G11: Your group is discussing trades daily. We've built a decision layer to help members validate actions... | H11: https://www.reddit.com/r/StartupIndia/ | I11: Reddit
A12: 11 | B12: ⚪ New | D12: 0 | E12: r/MutualFundsIndia | F12: Product Comparison | G12: Your group is discussing trades daily. We've built a decision layer to help members validate actions... | H12: https://www.reddit.com/r/MutualFundsIndia/ | I12: Reddit
A13: 12 | B13: ⚪ New | D13: 0 | E13: r/IndiaMarket | F13: Macro Market Analysis | G13: Your group is discussing trades daily. We've built a decision layer to help members validate actions... | H13: https://www.google.com/search?q=https://www.reddit.com/r/IndiaMarket/ | I13: Reddit
... A101: 100 | B101: ⚪ New | D101: 0 | E101: Stock Market Daily Analysis | F101: Pre-Market Routine Wedge | G101: Your group is discussing trades daily. We've built a decision layer to help members validate actions... | H101: https://www.google.com/search?q=https://t.me/dailyanalysisindia | I101: Telegram
A102: 101 | B102: ⚪ New | D102: 0 | E102: Sample Telegram Group | F102: Sample Focus | I102: Telegram | J102: Should I buy HDFC? | K102: Structured (Score, Risk, Reason, Alternative) | L102: Asked More | N102: 7
A103: 102 | B103: 🔥 Priority 1 | E103: The Safe Trader Academy | O103: @AnkitThakur / 9297506666 | P103: 10 | Q103: Leveraging Fnomo...
A104: 103 | B104: ? New | E104: Dr. Skand Kumar Trivedi | F104: Doctors | I104: Doctors | J104: Last wrong investment/financial decision? What was the decision process? | Q104: Decision validation before investment action
A105: 104 | B105: ? New | E105: Dr. Rajnees h Kachha ra | F105: Doctors | I105: Doctors | J105: Last wrong investment/financial decision? What was the decision process? | Q105: Decision validation before investment action
A106: 105 | B106: ? New | E106: Dr. Vinit Pandey | F106: Doctors | I106: Doctors | J106: Last wrong investment/financial decision? What was the decision process? | Q106: Decision validation before investment action
A107: 106 | B107: ? New | E107: Dr. Aaditya Sirohi | F107: Doctors | I107: Doctors | J107: Last wrong investment/financial decision? What was the decision process? | Q107: Decision validation before investment action
A108: 107 | B108: ? New | E108: Dr. Gopal Batni | F108: Doctors | I108: Doctors | J108: Last wrong investment/financial decision? What was the decision process? | Q108: Decision validation before investment action
A109: 108 | B109: ? New | E109: Dr. Neeraj Jain | F109: Doctors | I109: Doctors | J109: Last wrong investment/financial decision? What was the decision process? | Q109: Decision validation before investment action
A110: 109 | B110: ? New | E110: Dr. Amit Joshi | F110: Doctors | I110: Doctors | J110: Last wrong investment/financial decision? What was the decision process? | Q110: Decision validation before investment action
A111: 110 | B111: ? New | E111: Dr. Seetha Lekshm i B | F111: Doctors | I111: Doctors | J111: Last wrong investment/financial decision? What was the decision process? | Q111: Decision validation before investment action
A112: 111 | B112: ? New | E112: Dr. Rohit Joshi | F112: Doctors | I112: Doctors | J112: Last wrong investment/financial decision? What was the decision process? | Q112: Decision validation before investment action
A113: 112 | B113: ? New | E113: Dr. Vikram Balwani | F113: Doctors | I113: Doctors | J113: Last wrong investment/financial decision? What was the decision process? | Q113: Decision validation before investment action
A114: 113 | B114: ? New | E114: Dr. Santos h Choudh ary | F114: Doctors | I114: Doctors | J114: Last wrong investment/financial decision? What was the decision process? | Q114: Decision validation before investment action
A115: 114 | B115: ? New | E115: Dr. Arpit Tiwari | F115: Doctors | I115: Doctors | J115: Last wrong investment/financial decision? What was the decision process? | Q115: Decision validation before investment action
... A163: 162 | B163: ? New | E163: Shri Ram Global School | F163: Schools | I163: Schools | J163: Do students act on confidence before validating judgment? | Q163: Decision validation as a student/parent capability

Sheet GTM_Schedule
B2: FNOMO TODO EXECUTION CONTROL SHEET
B3: Update Task Status and Owner only. Dashboard refreshes automatically for Kush and Indu.
B4: Day | C4: Phase | D4: Quest Title | E4: Primary Objective | F4: Success Metric | G4: Task Status | H4: Owner | I4: Priority | J4: Progress
B5: Day 1 | C5: Phase 1 | Association and high-value lead buildout | D5: Contact Doctor Associations | E5: Outreach to doctor associations | F5: Priority contacts identified, first outreach sent, next follow-up date logged | G5: Not Started | H5: Kush | I5: Medium | J5: =IF(G5="Done",1,IF(G5="In Progress",0.6,IF(G5="Waiting",0.35,IF(G5="Blocked",0.15,0))))
B6: Day 2 | C6: Phase 1 | Association and high-value lead buildout | D6: Contact Business Associations | E6: Outreach to business associations | F6: Priority contacts identified, first outreach sent, next follow-up date logged | G6: Not Started | H6: Kush | I6: Medium | J6: =IF(G6="Done",1,IF(G6="In Progress",0.6,IF(G6="Waiting",0.35,IF(G6="Blocked",0.15,0))))
B7: Day 3 | C7: Phase 1 | Association and high-value lead buildout | D7: Contact CA Associations | E7: Outreach to CA associations | F7: Priority contacts identified, first outreach sent, next follow-up date logged | G7: In Progress | H7: Kush | I7: Medium | J7: =IF(G7="Done",1,IF(G7="In Progress",0.6,IF(G7="Waiting",0.35,IF(G7="Blocked",0.15,0))))
B8: Day 4 | C8: Phase 1 | Association and high-value lead buildout | D8: Identify Business Owners >2Cr | E8: Find and reach high value business owners | F8: Qualified target list built with owners, contacts, and next actions | G8: Not Started | H8: Kush | I8: High | J8: =IF(G8="Done",1,IF(G8="In Progress",0.6,IF(G8="Waiting",0.35,IF(G8="Blocked",0.15,0))))
B9: Day 5 | C9: Phase 2 | Platform and channel partnerships | D9: Reach out Practo | E9: Platform partnership outreach | F9: Decision-maker identified, personalized outreach sent, reply tracked | G9: In Progress | H9: Kush | I9: High | J9: =IF(G9="Done",1,IF(G9="In Progress",0.6,IF(G9="Waiting",0.35,IF(G9="Blocked",0.15,0))))
B10: Day 6 | C10: Phase 2 | Platform and channel partnerships | D10: Reach out Blinkit | E10: Platform partnership outreach | F10: Decision-maker identified, personalized outreach sent, reply tracked | G10: In Progress | H10: Kush | I10: High | J10: =IF(G10="Done",1,IF(G10="In Progress",0.6,IF(G10="Waiting",0.35,IF(G10="Blocked",0.15,0))))
B11: Day 7 | C11: Phase 2 | Platform and channel partnerships | D11: Reach out Zomato | E11: Platform partnership outreach | F11: Decision-maker identified, personalized outreach sent, reply tracked | G11: In Progress | H11: Kush | I11: High | J11: =IF(G11="Done",1,IF(G11="In Progress",0.6,IF(G11="Waiting",0.35,IF(G11="Blocked",0.15,0))))
B12: Day 8 | C12: Phase 2 | Platform and channel partnerships | D12: Reach out Swiggy | E12: Platform partnership outreach | F12: Decision-maker identified, personalized outreach sent, reply tracked | G12: In Progress | H12: Kush | I12: High | J12: =IF(G12="Done",1,IF(G12="In Progress",0.6,IF(G12="Waiting",0.35,IF(G12="Blocked",0.15,0))))
B13: Day 9 | C13: Phase 2 | Platform and channel partnerships | D13: Reach out MyGate | E13: Platform partnership outreach | F13: Decision-maker identified, personalized outreach sent, reply tracked | G13: In Progress | H13: Kush | I13: Medium | J13: =IF(G13="Done",1,IF(G13="In Progress",0.6,IF(G13="Waiting",0.35,IF(G13="Blocked",0.15,0))))
B14: Day 10 | C14: Phase 2 | Platform and channel partnerships | D14: Explore National Platforms | E14: Find expansion platforms | F14: New target set shortlisted and first 5 next moves defined | G14: In Progress | H14: Kush | I14: Low | J14: =IF(G14="Done",1,IF(G14="In Progress",0.6,IF(G14="Waiting",0.35,IF(G14="Blocked",0.15,0))))
B15: Day 11 | C15: Phase 2 | Platform and channel partnerships | D15: Explore Event Platforms | E15: Find event-based growth channels | F15: New target set shortlisted and first 5 next moves defined | G15: Not Started | H15: Kush | I15: Low | J15: =IF(G15="Done",1,IF(G15="In Progress",0.6,IF(G15="Waiting",0.35,IF(G15="Blocked",0.15,0))))
B16: Day 12 | C16: Phase 2 | Platform and channel partnerships | D16: Restaurant Partnerships | E16: Tie up with restaurants | F16: Clear deliverable completed and next step logged | G16: Not Started | H16: Kush | I16: Medium | J16: =IF(G16="Done",1,IF(G16="In Progress",0.6,IF(G16="Waiting",0.35,IF(G16="Blocked",0.15,0))))
... B40: Day 36 | C40: Phase 6 | Demand generation and trust building | D40: Free Investing Sessions | E40: General sessions | F40: Campaign plan finalized with target audience, owner, and first launch date | G40: Not Started | H40: Kush | I40: Medium | J40: =IF(G40="Done",1,IF(G40="In Progress",0.6,IF(G40="Waiting",0.35,IF(G40="Blocked",0.15,0))))

Sheet Calc_Engine
B2: Calculation Engine
B4: KPI | C4: Value | D4: Status | E4: Count | G4: Date | H4: Volume | I4: Conversions
B5: Total Outreach Volume | C5: =COUNTA(OutreachData[ID]) | D5: New | E5: =COUNTIF(OutreachData[Status], D5) | G5: =IFERROR(__xludf.DUMMYFUNCTION("SORT(UNIQUE(FILTER(OutreachData[Outreach Date], OutreachData[Outreach Date]<>"""")))"),"#N/A") | H5: {=IF(G5:G1003="", "", COUNTIFS(OutreachData[Outreach Date], G5:G1003))} | I5: {=IF(G5:G1003="", "", COUNTIFS(OutreachData[Outreach Date], G5:G1003, OutreachData[Status], "Done"))}
B6: Pending Responses | C6: =COUNTIF(OutreachData[Status], "Follow-up") + COUNTIF(OutreachData[Status], "Pitching") | D6: Pitching | E6: =COUNTIF(OutreachData[Status], D6)
B7: Total Members Joined | C7: =SUM(OutreachData[Members Joined]) | D7: Follow-up | E7: =COUNTIF(OutreachData[Status], D7)
B8: Conversion Rate | C8: =COUNTIF(OutreachData[Status], "Done") / C5 | D8: Done | E8: =COUNTIF(OutreachData[Status], D8)

Sheet Dashboard
X1: Status Options | Y1: Owner Options | Z1: Priority Options
B2: FNOMO LIVE PIPELINE DASHBOARD | X2: Not Started | Y2: Kush | Z2: High
B3: Connected to FNOMO_MASTER_PIPELINE + WHATSAPP_CA_LEADS. Current progress refreshed by Codex on 2026-05-02. | X3: In Progress | Y3: Indu | Z3: Medium
B4: Total Leads | F4: Contacted | J4: Tier A Pending | N4: Follow-ups Due May 4 | X4: Waiting | Y4: Codex | Z4: Low
B5: 185 | F5: 99 | J5: 21 | N5: 53 | X5: Blocked | Y5: Shared
X6: Done
B9: New | F9: Active | J9: Waiting | N9: Contacted Today
B10: 86 | F10: 120 | J10: 65 | N10: 47
B14: Status Overview | H14: Phase Performance | N14: Owner Accountability
B15: Status | C15: Count | D15: Share | E15: Target Signal | F15: Health | H15: Phase | I15: Open | J15: Done | K15: Completion % | L15: Reading | N15: Owner | O15: Open | P15: Done | Q15: Share of Open | R15: Reading
B16: Not Started | C16: =COUNTIF(GTM_Schedule!$G$5:$G$40,B16) | D16: =IFERROR(C16/COUNTA(GTM_Schedule!$D$5:$D$40),0) | E16: Watch | F16: =REPT("|",ROUND(D16*20,0)) | H16: Phase 1 | I16: =COUNTIF(GTM_Schedule!$C$5:$C$40,"Phase 1*")-COUNTIFS(GTM_Schedule!$C$5:$C$40,"Phase 1*",GTM_Schedule!$G$5:$G$40,"Done") | J16: =COUNTIFS(GTM_Schedule!$C$5:$C$40,"Phase 1*",GTM_Schedule!$G$5:$G$40,"Done") | K16: =IFERROR(J16/(I16+J16),0) | L16: =IF(K16>=0.75,"Strong",IF(K16>=0.4,"Moving","Early")) | N16: Kush | O16: =COUNTIF(GTM_Schedule!$H$5:$H$40,N16)-COUNTIFS(GTM_Schedule!$H$5:$H$40,N16,GTM_Schedule!$G$5:$G$40,"Done") | P16: =COUNTIFS(GTM_Schedule!$H$5:$H$40,N16,GTM_Schedule!$G$5:$G$40,"Done") | Q16: =IFERROR(O16/SUM($O$16:$O$19),0) | R16: =IF(O16=0,"Clear",IF(O16<=3,"Controlled","Loaded"))
B17: In Progress | C17: =COUNTIF(GTM_Schedule!$G$5:$G$40,B17) | D17: =IFERROR(C17/COUNTA(GTM_Schedule!$D$5:$D$40),0) | E17: Stable | F17: =REPT("|",ROUND(D17*20,0)) | H17: Phase 2 | I17: =COUNTIF(GTM_Schedule!$C$5:$C$40,"Phase 2*")-COUNTIFS(GTM_Schedule!$C$5:$C$40,"Phase 2*",GTM_Schedule!$G$5:$G$40,"Done") | J17: =COUNTIFS(GTM_Schedule!$C$5:$C$40,"Phase 2*",GTM_Schedule!$G$5:$G$40,"Done") | K17: =IFERROR(J17/(I17+J17),0) | L17: =IF(K17>=0.75,"Strong",IF(K17>=0.4,"Moving","Early")) | N17: Indu | O17: =COUNTIF(GTM_Schedule!$H$5:$H$40,N17)-COUNTIFS(GTM_Schedule!$H$5:$H$40,N17,GTM_Schedule!$G$5:$G$40,"Done") | P17: =COUNTIFS(GTM_Schedule!$H$5:$H$40,N17,GTM_Schedule!$G$5:$G$40,"Done") | Q17: =IFERROR(O17/SUM($O$16:$O$19),0) | R17: =IF(O17=0,"Clear",IF(O17<=3,"Controlled","Loaded"))
B18: Waiting | C18: =COUNTIF(GTM_Schedule!$G$5:$G$40,B18) | D18: =IFERROR(C18/COUNTA(GTM_Schedule!$D$5:$D$40),0) | E18: Attention | F18: =REPT("|",ROUND(D18*20,0)) | H18: Phase 3 | I18: =COUNTIF(GTM_Schedule!$C$5:$C$40,"Phase 3*")-COUNTIFS(GTM_Schedule!$C$5:$C$40,"Phase 3*",GTM_Schedule!$G$5:$G$40,"Done") | J18: =COUNTIFS(GTM_Schedule!$C$5:$C$40,"Phase 3*",GTM_Schedule!$G$5:$G$40,"Done") | K18: =IFERROR(J18/(I18+J18),0) | L18: =IF(K18>=0.75,"Strong",IF(K18>=0.4,"Moving","Early")) | N18: Codex | O18: =COUNTIF(GTM_Schedule!$H$5:$H$40,N18)-COUNTIFS(GTM_Schedule!$H$5:$H$40,N18,GTM_Schedule!$G$5:$G$40,"Done") | P18: =COUNTIFS(GTM_Schedule!$H$5:$H$40,N18,GTM_Schedule!$G$5:$G$40,"Done") | Q18: =IFERROR(O18/SUM($O$16:$O$19),0) | R18: =IF(O18=0,"Clear",IF(O18<=3,"Controlled","Loaded"))
B19: Blocked | C19: =COUNTIF(GTM_Schedule!$G$5:$G$40,B19) | D19: =IFERROR(C19/COUNTA(GTM_Schedule!$D$5:$D$40),0) | E19: Attention | F19: =REPT("|",ROUND(D19*20,0)) | H19: Phase 4 | I19: =COUNTIF(GTM_Schedule!$C$5:$C$40,"Phase 4*")-COUNTIFS(GTM_Schedule!$C$5:$C$40,"Phase 4*",GTM_Schedule!$G$5:$G$40,"Done") | J19: =COUNTIFS(GTM_Schedule!$C$5:$C$40,"Phase 4*",GTM_Schedule!$G$5:$G$40,"Done") | K19: =IFERROR(J19/(I19+J19),0) | L19: =IF(K19>=0.75,"Strong",IF(K19>=0.4,"Moving","Early")) | N19: Shared | O19: =COUNTIF(GTM_Schedule!$H$5:$H$40,N19)-COUNTIFS(GTM_Schedule!$H$5:$H$40,N19,GTM_Schedule!$G$5:$G$40,"Done") | P19: =COUNTIFS(GTM_Schedule!$H$5:$H$40,N19,GTM_Schedule!$G$5:$G$40,"Done") | Q19: =IFERROR(O19/SUM($O$16:$O$19),0) | R19: =IF(O19=0,"Clear",IF(O19<=3,"Controlled","Loaded"))
B20: Done | C20: =COUNTIF(GTM_Schedule!$G$5:$G$40,B20) | D20: =IFERROR(C20/COUNTA(GTM_Schedule!$D$5:$D$40),0) | E20: Stable | F20: =REPT("|",ROUND(D20*20,0)) | H20: Phase 5 | I20: =COUNTIF(GTM_Schedule!$C$5:$C$40,"Phase 5*")-COUNTIFS(GTM_Schedule!$C$5:$C$40,"Phase 5*",GTM_Schedule!$G$5:$G$40,"Done") | J20: =COUNTIFS(GTM_Schedule!$C$5:$C$40,"Phase 5*",GTM_Schedule!$G$5:$G$40,"Done") | K20: =IFERROR(J20/(I20+J20),0) | L20: =IF(K20>=0.75,"Strong",IF(K20>=0.4,"Moving","Early"))
H21: Phase 6 | I21: =COUNTIF(GTM_Schedule!$C$5:$C$40,"Phase 6*")-COUNTIFS(GTM_Schedule!$C$5:$C$40,"Phase 6*",GTM_Schedule!$G$5:$G$40,"Done") | J21: =COUNTIFS(GTM_Schedule!$C$5:$C$40,"Phase 6*",GTM_Schedule!$G$5:$G$40,"Done") | K21: =IFERROR(J21/(I21+J21),0) | L21: =IF(K21>=0.75,"Strong",IF(K21>=0.4,"Moving","Early"))
B24: Priority Focus Board | K24: Blocked / Waiting Watchlist
B25: Task | E25: Priority | K25: Task | N25: Priority
B26: =IFERROR(INDEX(GTM_Schedule!$D$5:$D$40,AGGREGATE(15,6,(ROW(GTM_Schedule!$D$5:$D$40)-ROW(GTM_Schedule!$D$5)+1)/((GTM_Schedule!$I$5:$I$40="High")*(GTM_Schedule!$G$5:$G$40<>"Done")),ROW(A26)-25)),"") | E26: =IF(B26="","",IFERROR(INDEX(GTM_Schedule!$C$5:$C$40,AGGREGATE(15,6,(ROW(GTM_Schedule!$C$5:$C$40)-ROW(GTM_Schedule!$C$5)+1)/((GTM_Schedule!$I$5:$I$40="High")*(GTM_Schedule!$G$5:$G$40<>"Done")),ROW(A26)-25)),"")) | G26: =IF(B26="","",IFERROR(INDEX(GTM_Schedule!$H$5:$H$40,AGGREGATE(15,6,(ROW(GTM_Schedule!$H$5:$H$40)-ROW(GTM_Schedule!$H$5)+1)/((GTM_Schedule!$I$5:$I$40="High")*(GTM_Schedule!$G$5:$G$40<>"Done")),ROW(A26)-25)),"")) | I26: =IF(B26="","",IFERROR(INDEX(GTM_Schedule!$I$5:$I$40,AGGREGATE(15,6,(ROW(GTM_Schedule!$I$5:$I$40)-ROW(GTM_Schedule!$I$5)+1)/((GTM_Schedule!$I$5:$I$40="High")*(GTM_Schedule!$G$5:$G$40<>"Done")),ROW(A26)-25)),"")) | K26: =IFERROR(INDEX(GTM_Schedule!$D$5:$D$40,AGGREGATE(15,6,(ROW(GTM_Schedule!$D$5:$D$40)-ROW(GTM_Schedule!$D$5)+1)/((GTM_Schedule!$G$5:$G$40="Blocked")+(GTM_Schedule!$G$5:$G$40="Waiting")),ROW(A26)-25)),"") | N26: =IF(K26="","",IFERROR(INDEX(GTM_Schedule!$G$5:$G$40,AGGREGATE(15,6,(ROW(GTM_Schedule!$G$5:$G$40)-ROW(GTM_Schedule!$G$5)+1)/((GTM_Schedule!$G$5:$G$40="Blocked")+(GTM_Schedule!$G$5:$G$40="Waiting")),ROW(A26)-25)),"")) | P26: =IF(K26="","",IFERROR(INDEX(GTM_Schedule!$H$5:$H$40,AGGREGATE(15,6,(ROW(GTM_Schedule!$H$5:$H$40)-ROW(GTM_Schedule!$H$5)+1)/((GTM_Schedule!$G$5:$G$40="Blocked")+(GTM_Schedule!$G$5:$G$40="Waiting")),ROW(A26)-25)),"")) | R26: =IF(K26="","",IFERROR(INDEX(GTM_Schedule!$I$5:$I$40,AGGREGATE(15,6,(ROW(GTM_Schedule!$I$5:$I$40)-ROW(GTM_Schedule!$I$5)+1)/((GTM_Schedule!$G$5:$G$40="Blocked")+(GTM_Schedule!$G$5:$G$40="Waiting")),ROW(A26)-25)),""))
B27: =IFERROR(INDEX(GTM_Schedule!$D$5:$D$40,AGGREGATE(15,6,(ROW(GTM_Schedule!$D$5:$D$40)-ROW(GTM_Schedule!$D$5)+1)/((GTM_Schedule!$I$5:$I$40="High")*(GTM_Schedule!$G$5:$G$40<>"Done")),ROW(A27)-25)),"") | E27: =IF(B27="","",IFERROR(INDEX(GTM_Schedule!$C$5:$C$40,AGGREGATE(15,6,(ROW(GTM_Schedule!$C$5:$C$40)-ROW(GTM_Schedule!$C$5)+1)/((GTM_Schedule!$I$5:$I$40="High")*(GTM_Schedule!$G$5:$G$40<>"Done")),ROW(A27)-25)),"")) | G27: =IF(B27="","",IFERROR(INDEX(GTM_Schedule!$H$5:$H$40,AGGREGATE(15,6,(ROW(GTM_Schedule!$H$5:$H$40)-ROW(GTM_Schedule!$H$5)+1)/((GTM_Schedule!$I$5:$I$40="High")*(GTM_Schedule!$G$5:$G$40<>"Done")),ROW(A27)-25)),"")) | I27: =IF(B27="","",IFERROR(INDEX(GTM_Schedule!$I$5:$I$40,AGGREGATE(15,6,(ROW(GTM_Schedule!$I$5:$I$40)-ROW(GTM_Schedule!$I$5)+1)/((GTM_Schedule!$I$5:$I$40="High")*(GTM_Schedule!$G$5:$G$40<>"Done")),ROW(A27)-25)),"")) | K27: =IFERROR(INDEX(GTM_Schedule!$D$5:$D$40,AGGREGATE(15,6,(ROW(GTM_Schedule!$D$5:$D$40)-ROW(GTM_Schedule!$D$5)+1)/((GTM_Schedule!$G$5:$G$40="Blocked")+(GTM_Schedule!$G$5:$G$40="Waiting")),ROW(A27)-25)),"") | N27: =IF(K27="","",IFERROR(INDEX(GTM_Schedule!$G$5:$G$40,AGGREGATE(15,6,(ROW(GTM_Schedule!$G$5:$G$40)-ROW(GTM_Schedule!$G$5)+1)/((GTM_Schedule!$G$5:$G$40="Blocked")+(GTM_Schedule!$G$5:$G$40="Waiting")),ROW(A27)-25)),"")) | P27: =IF(K27="","",IFERROR(INDEX(GTM_Schedule!$H$5:$H$40,AGGREGATE(15,6,(ROW(GTM_Schedule!$H$5:$H$40)-ROW(GTM_Schedule!$H$5)+1)/((GTM_Schedule!$G$5:$G$40="Blocked")+(GTM_Schedule!$G$5:$G$40="Waiting")),ROW(A27)-25)),"")) | R27: =IF(K27="","",IFERROR(INDEX(GTM_Schedule!$I$5:$I$40,AGGREGATE(15,6,(ROW(GTM_Schedule!$I$5:$I$40)-ROW(GTM_Schedule!$I$5)+1)/((GTM_Schedule!$G$5:$G$40="Blocked")+(GTM_Schedule!$G$5:$G$40="Waiting")),ROW(A27)-25)),""))
B28: =IFERROR(INDEX(GTM_Schedule!$D$5:$D$40,AGGREGATE(15,6,(ROW(GTM_Schedule!$D$5:$D$40)-ROW(GTM_Schedule!$D$5)+1)/((GTM_Schedule!$I$5:$I$40="High")*(GTM_Schedule!$G$5:$G$40<>"Done")),ROW(A28)-25)),"") | E28: =IF(B28="","",IFERROR(INDEX(GTM_Schedule!$C$5:$C$40,AGGREGATE(15,6,(ROW(GTM_Schedule!$C$5:$C$40)-ROW(GTM_Schedule!$C$5)+1)/((GTM_Schedule!$I$5:$I$40="High")*(GTM_Schedule!$G$5:$G$40<>"Done")),ROW(A28)-25)),"")) | G28: =IF(B28="","",IFERROR(INDEX(GTM_Schedule!$H$5:$H$40,AGGREGATE(15,6,(ROW(GTM_Schedule!$H$5:$H$40)-ROW(GTM_Schedule!$H$5)+1)/((GTM_Schedule!$I$5:$I$40="High")*(GTM_Schedule!$G$5:$G$40<>"Done")),ROW(A28)-25)),"")) | I28: =IF(B28="","",IFERROR(INDEX(GTM_Schedule!$I$5:$I$40,AGGREGATE(15,6,(ROW(GTM_Schedule!$I$5:$I$40)-ROW(GTM_Schedule!$I$5)+1)/((GTM_Schedule!$I$5:$I$40="High")*(GTM_Schedule!$G$5:$G$40<>"Done")),ROW(A28)-25)),"")) | K28: =IFERROR(INDEX(GTM_Schedule!$D$5:$D$40,AGGREGATE(15,6,(ROW(GTM_Schedule!$D$5:$D$40)-ROW(GTM_Schedule!$D$5)+1)/((GTM_Schedule!$G$5:$G$40="Blocked")+(GTM_Schedule!$G$5:$G$40="Waiting")),ROW(A28)-25)),"") | N28: =IF(K28="","",IFERROR(INDEX(GTM_Schedule!$G$5:$G$40,AGGREGATE(15,6,(ROW(GTM_Schedule!$G$5:$G$40)-ROW(GTM_Schedule!$G$5)+1)/((GTM_Schedule!$G$5:$G$40="Blocked")+(GTM_Schedule!$G$5:$G$40="Waiting")),ROW(A28)-25)),"")) | P28: =IF(K28="","",IFERROR(INDEX(GTM_Schedule!$H$5:$H$40,AGGREGATE(15,6,(ROW(GTM_Schedule!$H$5:$H$40)-ROW(GTM_Schedule!$H$5)+1)/((GTM_Schedule!$G$5:$G$40="Blocked")+(GTM_Schedule!$G$5:$G$40="Waiting")),ROW(A28)-25)),"")) | R28: =IF(K28="","",IFERROR(INDEX(GTM_Schedule!$I$5:$I$40,AGGREGATE(15,6,(ROW(GTM_Schedule!$I$5:$I$40)-ROW(GTM_Schedule!$I$5)+1)/((GTM_Schedule!$G$5:$G$40="Blocked")+(GTM_Schedule!$G$5:$G$40="Waiting")),ROW(A28)-25)),""))
B29: =IFERROR(INDEX(GTM_Schedule!$D$5:$D$40,AGGREGATE(15,6,(ROW(GTM_Schedule!$D$5:$D$40)-ROW(GTM_Schedule!$D$5)+1)/((GTM_Schedule!$I$5:$I$40="High")*(GTM_Schedule!$G$5:$G$40<>"Done")),ROW(A29)-25)),"") | E29: =IF(B29="","",IFERROR(INDEX(GTM_Schedule!$C$5:$C$40,AGGREGATE(15,6,(ROW(GTM_Schedule!$C$5:$C$40)-ROW(GTM_Schedule!$C$5)+1)/((GTM_Schedule!$I$5:$I$40="High")*(GTM_Schedule!$G$5:$G$40<>"Done")),ROW(A29)-25)),"")) | G29: =IF(B29="","",IFERROR(INDEX(GTM_Schedule!$H$5:$H$40,AGGREGATE(15,6,(ROW(GTM_Schedule!$H$5:$H$40)-ROW(GTM_Schedule!$H$5)+1)/((GTM_Schedule!$I$5:$I$40="High")*(GTM_Schedule!$G$5:$G$40<>"Done")),ROW(A29)-25)),"")) | I29: =IF(B29="","",IFERROR(INDEX(GTM_Schedule!$I$5:$I$40,AGGREGATE(15,6,(ROW(GTM_Schedule!$I$5:$I$40)-ROW(GTM_Schedule!$I$5)+1)/((GTM_Schedule!$I$5:$I$40="High")*(GTM_Schedule!$G$5:$G$40<>"Done")),ROW(A29)-25)),"")) | K29: =IFERROR(INDEX(GTM_Schedule!$D$5:$D$40,AGGREGATE(15,6,(ROW(GTM_Schedule!$D$5:$D$40)-ROW(GTM_Schedule!$D$5)+1)/((GTM_Schedule!$G$5:$G$40="Blocked")+(GTM_Schedule!$G$5:$G$40="Waiting")),ROW(A29)-25)),"") | N29: =IF(K29="","",IFERROR(INDEX(GTM_Schedule!$G$5:$G$40,AGGREGATE(15,6,(ROW(GTM_Schedule!$G$5:$G$40)-ROW(GTM_Schedule!$G$5)+1)/((GTM_Schedule!$G$5:$G$40="Blocked")+(GTM_Schedule!$G$5:$G$40="Waiting")),ROW(A29)-25)),"")) | P29: =IF(K29="","",IFERROR(INDEX(GTM_Schedule!$H$5:$H$40,AGGREGATE(15,6,(ROW(GTM_Schedule!$H$5:$H$40)-ROW(GTM_Schedule!$H$5)+1)/((GTM_Schedule!$G$5:$G$40="Blocked")+(GTM_Schedule!$G$5:$G$40="Waiting")),ROW(A29)-25)),"")) | R29: =IF(K29="","",IFERROR(INDEX(GTM_Schedule!$I$5:$I$40,AGGREGATE(15,6,(ROW(GTM_Schedule!$I$5:$I$40)-ROW(GTM_Schedule!$I$5)+1)/((GTM_Schedule!$G$5:$G$40="Blocked")+(GTM_Schedule!$G$5:$G$40="Waiting")),ROW(A29)-25)),""))
B30: =IFERROR(INDEX(GTM_Schedule!$D$5:$D$40,AGGREGATE(15,6,(ROW(GTM_Schedule!$D$5:$D$40)-ROW(GTM_Schedule!$D$5)+1)/((GTM_Schedule!$I$5:$I$40="High")*(GTM_Schedule!$G$5:$G$40<>"Done")),ROW(A30)-25)),"") | E30: =IF(B30="","",IFERROR(INDEX(GTM_Schedule!$C$5:$C$40,AGGREGATE(15,6,(ROW(GTM_Schedule!$C$5:$C$40)-ROW(GTM_Schedule!$C$5)+1)/((GTM_Schedule!$I$5:$I$40="High")*(GTM_Schedule!$G$5:$G$40<>"Done")),ROW(A30)-25)),"")) | G30: =IF(B30="","",IFERROR(INDEX(GTM_Schedule!$H$5:$H$40,AGGREGATE(15,6,(ROW(GTM_Schedule!$H$5:$H$40)-ROW(GTM_Schedule!$H$5)+1)/((GTM_Schedule!$I$5:$I$40="High")*(GTM_Schedule!$G$5:$G$40<>"Done")),ROW(A30)-25)),"")) | I30: =IF(B30="","",IFERROR(INDEX(GTM_Schedule!$I$5:$I$40,AGGREGATE(15,6,(ROW(GTM_Schedule!$I$5:$I$40)-ROW(GTM_Schedule!$I$5)+1)/((GTM_Schedule!$I$5:$I$40="High")*(GTM_Schedule!$G$5:$G$40<>"Done")),ROW(A30)-25)),"")) | K30: =IFERROR(INDEX(GTM_Schedule!$D$5:$D$40,AGGREGATE(15,6,(ROW(GTM_Schedule!$D$5:$D$40)-ROW(GTM_Schedule!$D$5)+1)/((GTM_Schedule!$G$5:$G$40="Blocked")+(GTM_Schedule!$G$5:$G$40="Waiting")),ROW(A30)-25)),"") | N30: =IF(K30="","",IFERROR(INDEX(GTM_Schedule!$G$5:$G$40,AGGREGATE(15,6,(ROW(GTM_Schedule!$G$5:$G$40)-ROW(GTM_Schedule!$G$5)+1)/((GTM_Schedule!$G$5:$G$40="Blocked")+(GTM_Schedule!$G$5:$G$40="Waiting")),ROW(A30)-25)),"")) | P30: =IF(K30="","",IFERROR(INDEX(GTM_Schedule!$H$5:$H$40,AGGREGATE(15,6,(ROW(GTM_Schedule!$H$5:$H$40)-ROW(GTM_Schedule!$H$5)+1)/((GTM_Schedule!$G$5:$G$40="Blocked")+(GTM_Schedule!$G$5:$G$40="Waiting")),ROW(A30)-25)),"")) | R30: =IF(K30="","",IFERROR(INDEX(GTM_Schedule!$I$5:$I$40,AGGREGATE(15,6,(ROW(GTM_Schedule!$I$5:$I$40)-ROW(GTM_Schedule!$I$5)+1)/((GTM_Schedule!$G$5:$G$40="Blocked")+(GTM_Schedule!$G$5:$G$40="Waiting")),ROW(A30)-25)),""))
B31: =IFERROR(INDEX(GTM_Schedule!$D$5:$D$40,AGGREGATE(15,6,(ROW(GTM_Schedule!$D$5:$D$40)-ROW(GTM_Schedule!$D$5)+1)/((GTM_Schedule!$I$5:$I$40="High")*(GTM_Schedule!$G$5:$G$40<>"Done")),ROW(A31)-25)),"") | E31: =IF(B31="","",IFERROR(INDEX(GTM_Schedule!$C$5:$C$40,AGGREGATE(15,6,(ROW(GTM_Schedule!$C$5:$C$40)-ROW(GTM_Schedule!$C$5)+1)/((GTM_Schedule!$I$5:$I$40="High")*(GTM_Schedule!$G$5:$G$40<>"Done")),ROW(A31)-25)),"")) | G31: =IF(B31="","",IFERROR(INDEX(GTM_Schedule!$H$5:$H$40,AGGREGATE(15,6,(ROW(GTM_Schedule!$H$5:$H$40)-ROW(GTM_Schedule!$H$5)+1)/((GTM_Schedule!$I$5:$I$40="High")*(GTM_Schedule!$G$5:$G$40<>"Done")),ROW(A31)-25)),"")) | I31: =IF(B31="","",IFERROR(INDEX(GTM_Schedule!$I$5:$I$40,AGGREGATE(15,6,(ROW(GTM_Schedule!$I$5:$I$40)-ROW(GTM_Schedule!$I$5)+1)/((GTM_Schedule!$I$5:$I$40="High")*(GTM_Schedule!$G$5:$G$40<>"Done")),ROW(A31)-25)),"")) | K31: =IFERROR(INDEX(GTM_Schedule!$D$5:$D$40,AGGREGATE(15,6,(ROW(GTM_Schedule!$D$5:$D$40)-ROW(GTM_Schedule!$D$5)+1)/((GTM_Schedule!$G$5:$G$40="Blocked")+(GTM_Schedule!$G$5:$G$40="Waiting")),ROW(A31)-25)),"") | N31: =IF(K31="","",IFERROR(INDEX(GTM_Schedule!$G$5:$G$40,AGGREGATE(15,6,(ROW(GTM_Schedule!$G$5:$G$40)-ROW(GTM_Schedule!$G$5)+1)/((GTM_Schedule!$G$5:$G$40="Blocked")+(GTM_Schedule!$G$5:$G$40="Waiting")),ROW(A31)-25)),"")) | P31: =IF(K31="","",IFERROR(INDEX(GTM_Schedule!$H$5:$H$40,AGGREGATE(15,6,(ROW(GTM_Schedule!$H$5:$H$40)-ROW(GTM_Schedule!$H$5)+1)/((GTM_Schedule!$G$5:$G$40="Blocked")+(GTM_Schedule!$G$5:$G$40="Waiting")),ROW(A31)-25)),"")) | R31: =IF(K31="","",IFERROR(INDEX(GTM_Schedule!$I$5:$I$40,AGGREGATE(15,6,(ROW(GTM_Schedule!$I$5:$I$40)-ROW(GTM_Schedule!$I$5)+1)/((GTM_Schedule!$G$5:$G$40="Blocked")+(GTM_Schedule!$G$5:$G$40="Waiting")),ROW(A31)-25)),""))
B32: =IFERROR(INDEX(GTM_Schedule!$D$5:$D$40,AGGREGATE(15,6,(ROW(GTM_Schedule!$D$5:$D$40)-ROW(GTM_Schedule!$D$5)+1)/((GTM_Schedule!$I$5:$I$40="High")*(GTM_Schedule!$G$5:$G$40<>"Done")),ROW(A32)-25)),"") | E32: =IF(B32="","",IFERROR(INDEX(GTM_Schedule!$C$5:$C$40,AGGREGATE(15,6,(ROW(GTM_Schedule!$C$5:$C$40)-ROW(GTM_Schedule!$C$5)+1)/((GTM_Schedule!$I$5:$I$40="High")*(GTM_Schedule!$G$5:$G$40<>"Done")),ROW(A32)-25)),"")) | G32: =IF(B32="","",IFERROR(INDEX(GTM_Schedule!$H$5:$H$40,AGGREGATE(15,6,(ROW(GTM_Schedule!$H$5:$H$40)-ROW(GTM_Schedule!$H$5)+1)/((GTM_Schedule!$I$5:$I$40="High")*(GTM_Schedule!$G$5:$G$40<>"Done")),ROW(A32)-25)),"")) | I32: =IF(B32="","",IFERROR(INDEX(GTM_Schedule!$I$5:$I$40,AGGREGATE(15,6,(ROW(GTM_Schedule!$I$5:$I$40)-ROW(GTM_Schedule!$I$5)+1)/((GTM_Schedule!$I$5:$I$40="High")*(GTM_Schedule!$G$5:$G$40<>"Done")),ROW(A32)-25)),"")) | K32: =IFERROR(INDEX(GTM_Schedule!$D$5:$D$40,AGGREGATE(15,6,(ROW(GTM_Schedule!$D$5:$D$40)-ROW(GTM_Schedule!$D$5)+1)/((GTM_Schedule!$G$5:$G$40="Blocked")+(GTM_Schedule!$G$5:$G$40="Waiting")),ROW(A32)-25)),"") | N32: =IF(K32="","",IFERROR(INDEX(GTM_Schedule!$G$5:$G$40,AGGREGATE(15,6,(ROW(GTM_Schedule!$G$5:$G$40)-ROW(GTM_Schedule!$G$5)+1)/((GTM_Schedule!$G$5:$G$40="Blocked")+(GTM_Schedule!$G$5:$G$40="Waiting")),ROW(A32)-25)),"")) | P32: =IF(K32="","",IFERROR(INDEX(GTM_Schedule!$H$5:$H$40,AGGREGATE(15,6,(ROW(GTM_Schedule!$H$5:$H$40)-ROW(GTM_Schedule!$H$5)+1)/((GTM_Schedule!$G$5:$G$40="Blocked")+(GTM_Schedule!$G$5:$G$40="Waiting")),ROW(A32)-25)),"")) | R32: =IF(K32="","",IFERROR(INDEX(GTM_Schedule!$I$5:$I$40,AGGREGATE(15,6,(ROW(GTM_Schedule!$I$5:$I$40)-ROW(GTM_Schedule!$I$5)+1)/((GTM_Schedule!$G$5:$G$40="Blocked")+(GTM_Schedule!$G$5:$G$40="Waiting")),ROW(A32)-25)),""))
B33: =IFERROR(INDEX(GTM_Schedule!$D$5:$D$40,AGGREGATE(15,6,(ROW(GTM_Schedule!$D$5:$D$40)-ROW(GTM_Schedule!$D$5)+1)/((GTM_Schedule!$I$5:$I$40="High")*(GTM_Schedule!$G$5:$G$40<>"Done")),ROW(A33)-25)),"") | E33: =IF(B33="","",IFERROR(INDEX(GTM_Schedule!$C$5:$C$40,AGGREGATE(15,6,(ROW(GTM_Schedule!$C$5:$C$40)-ROW(GTM_Schedule!$C$5)+1)/((GTM_Schedule!$I$5:$I$40="High")*(GTM_Schedule!$G$5:$G$40<>"Done")),ROW(A33)-25)),"")) | G33: =IF(B33="","",IFERROR(INDEX(GTM_Schedule!$H$5:$H$40,AGGREGATE(15,6,(ROW(GTM_Schedule!$H$5:$H$40)-ROW(GTM_Schedule!$H$5)+1)/((GTM_Schedule!$I$5:$I$40="High")*(GTM_Schedule!$G$5:$G$40<>"Done")),ROW(A33)-25)),"")) | I33: =IF(B33="","",IFERROR(INDEX(GTM_Schedule!$I$5:$I$40,AGGREGATE(15,6,(ROW(GTM_Schedule!$I$5:$I$40)-ROW(GTM_Schedule!$I$5)+1)/((GTM_Schedule!$I$5:$I$40="High")*(GTM_Schedule!$G$5:$G$40<>"Done")),ROW(A33)-25)),"")) | K33: =IFERROR(INDEX(GTM_Schedule!$D$5:$D$40,AGGREGATE(15,6,(ROW(GTM_Schedule!$D$5:$D$40)-ROW(GTM_Schedule!$D$5)+1)/((GTM_Schedule!$G$5:$G$40="Blocked")+(GTM_Schedule!$G$5:$G$40="Waiting")),ROW(A33)-25)),"") | N33: =IF(K33="","",IFERROR(INDEX(GTM_Schedule!$G$5:$G$40,AGGREGATE(15,6,(ROW(GTM_Schedule!$G$5:$G$40)-ROW(GTM_Schedule!$G$5)+1)/((GTM_Schedule!$G$5:$G$40="Blocked")+(GTM_Schedule!$G$5:$G$40="Waiting")),ROW(A33)-25)),"")) | P33: =IF(K33="","",IFERROR(INDEX(GTM_Schedule!$H$5:$H$40,AGGREGATE(15,6,(ROW(GTM_Schedule!$H$5:$H$40)-ROW(GTM_Schedule!$H$5)+1)/((GTM_Schedule!$G$5:$G$40="Blocked")+(GTM_Schedule!$G$5:$G$40="Waiting")),ROW(A33)-25)),"")) | R33: =IF(K33="","",IFERROR(INDEX(GTM_Schedule!$I$5:$I$40,AGGREGATE(15,6,(ROW(GTM_Schedule!$I$5:$I$40)-ROW(GTM_Schedule!$I$5)+1)/((GTM_Schedule!$G$5:$G$40="Blocked")+(GTM_Schedule!$G$5:$G$40="Waiting")),ROW(A33)-25)),""))

Sheet Influencer Hit List
A1: Name | B1: Channel Link | C1: Subscriber Count | D1: Business Email | E1: Niche | F1: Last Upload Topic | G1: Engagement Rate | H1: Status
A2: Arnab Nayak | B2: =IFERROR(__xludf.DUMMYFUNCTION("AI(""Fill an appropriate value for this cell based on the table context"")"),"https://www.youtube.com/@StartupGyaan") | C2: 85000 | D2: arnab@example.com | E2: Startups | F2: Startup Launch Guide | G2: 0.045 | H2: ⚪ New
A3: Ali Solanki | B3: =IFERROR(__xludf.DUMMYFUNCTION("AI(""Fill an appropriate value for this cell based on the table context"")"),"https://www.youtube.com/@StartupGyaan") | C3: 95000 | D3: ali@example.com | E3: Crypto/Tech | F3: Web3 Finance | G3: 0.055 | H3: ⚪ New
A4: Sushant Jain | B4: =IFERROR(__xludf.DUMMYFUNCTION("AI(""Fill an appropriate value for this cell based on the table context"")"),"https://www.youtube.com/@AliSolanki") | C4: 90000 | D4: sushant@example.com | E4: Stock Market | F4: Nifty Analysis | G4: 0.035 | H4: ⚪ New
A5: Riya Yadav | B5: =IFERROR(__xludf.DUMMYFUNCTION("AI(""Fill an appropriate value for this cell based on the table context"")"),"https://www.youtube.com/@AliSolanki") | C5: 75000 | D5: riya@example.com | E5: Crypto | F5: Bitcoin Halving | G5: 0.048 | H5: ⚪ New
A6: Yash Gupta | B6: =IFERROR(__xludf.DUMMYFUNCTION("AI(""Fill an appropriate value for this cell based on the table context"")"),"https://www.youtube.com/@riyayadav") | C6: 60000 | D6: yash@example.com | E6: Money Management | F6: Top 5 SIPs | G6: 0.038 | H6: ⚪ New
A7: Kiran | B7: =IFERROR(__xludf.DUMMYFUNCTION("AI(""Fill an appropriate value for this cell based on the table context"")"),"I do not have enough information to provide the specific YouTube channel link for the Yash Gupta mentioned in your spreadsheet. While there are several creators with this name, none of the available search results match a channel with 60,000 subscribers s"&"pecializing in Money Management and SIPs. To help me find the correct link, please provide the specific YouTube handle or a unique identifier for this creator.") | C7: 50000 | D7: kiran@example.com | E7: Financial Independence | F7: FIRE Movement | G7: 0.04 | H7: ⚪ New
A8: Brahmi Kapasi | B8: =IFERROR(__xludf.DUMMYFUNCTION("AI(""Fill an appropriate value for this cell based on the table context"")"),"https://www.youtube.com/@kiranroy") | C8: 45000 | D8: brahmi@example.com | E8: Personal Finance | F8: Budgeting 101 | G8: 0.052 | H8: ⚪ New
A9: Shivam Chhuneja | B9: =IFERROR(__xludf.DUMMYFUNCTION("AI(""Fill an appropriate value for this cell based on the table context"")"),"https://www.youtube.com/@TravelwithBrahmi") | C9: 40000 | D9: shivam@example.com | E9: Crypto Education | F9: Avoiding Scams | G9: 0.033 | H9: ⚪ New
A10: Ishaan Arora | B10: =IFERROR(__xludf.DUMMYFUNCTION("AI(""Fill an appropriate value for this cell based on the table context"")"),"https://www.youtube.com/@shivamchhuneja") | C10: 30000 | D10: ishaan@example.com | E10: Trading | F10: Options Hedging | G10: 0.061 | H10: ⚪ New
A11: Aashutosh Singla | B11: =IFERROR(__xludf.DUMMYFUNCTION("AI(""Fill an appropriate value for this cell based on the table context"")"),"https://www.youtube.com/@ishaanarora.official") | C11: 25000 | D11: aashutosh@example.com | E11: Finance Guide | F11: Investing for Beginners | G11: 0.059 | H11: ⚪ New
A12: Ujjwal Pahwa | B12: =IFERROR(__xludf.DUMMYFUNCTION("AI(""Fill an appropriate value for this cell based on the table context"")"),"https://www.youtube.com/@AashutoshSingla") | C12: 82000 | D12: ujjwal@example.com | E12: Finance/Careers | F12: Best Credit Cards | G12: 0.042 | H12: =IFERROR(__xludf.DUMMYFUNCTION("AI(""Fill an appropriate value for this cell based on the table context"")"),"⚪ New")
A13: Chhavi Agarwal | B13: =IFERROR(__xludf.DUMMYFUNCTION("AI(""Fill an appropriate value for this cell based on the table context"")"),"https://www.youtube.com/@AashutoshSingla") | C13: 48000 | D13: chhavi@example.com | E13: Stock Market | F13: IPO Reviews | G13: 0.051 | H13: =IFERROR(__xludf.DUMMYFUNCTION("AI(""Fill an appropriate value for this cell based on the table context"")"),"⚪ New")
A14: Vanshree Bajaj | B14: =IFERROR(__xludf.DUMMYFUNCTION("AI(""Fill an appropriate value for this cell based on the table context"")"),"https://www.youtube.com/@chhavibsht") | C14: 35000 | D14: vanshree@example.com | E14: Taxation/Investing | F14: Tax Saving Hacks | G14: 0.039 | H14: =IFERROR(__xludf.DUMMYFUNCTION("AI(""Fill an appropriate value for this cell based on the table context"")"),"⚪ New")
A15: Gauri Punjabi | B15: =IFERROR(__xludf.DUMMYFUNCTION("AI(""Fill an appropriate value for this cell based on the table context"")"),"https://www.youtube.com/@vanshreebajaj") | C15: 22000 | D15: gauri@example.com | E15: Personal Finance | F15: Budgeting for Gen Z | G15: 0.047 | H15: =IFERROR(__xludf.DUMMYFUNCTION("AI(""Fill an appropriate value for this cell based on the table context"")"),"⚪ New")
A16: Esha Choudhary | B16: =IFERROR(__xludf.DUMMYFUNCTION("AI(""Fill an appropriate value for this cell based on the table context"")"),"https://www.youtube.com/@gauripunjabi") | C16: 65000 | D16: esha@example.com | E16: Investing | F16: Mutual Fund Analysis | G16: 0.043 | H16: =IFERROR(__xludf.DUMMYFUNCTION("AI(""Fill an appropriate value for this cell based on the table context"")"),"⚪ New")
A17: Tarun Jagdish | B17: =IFERROR(__xludf.DUMMYFUNCTION("AI(""Fill an appropriate value for this cell based on the table context"")"),"https://www.youtube.com/@eshachoudhary") | C17: 15000 | D17: tarun@example.com | E17: Day Trading | F17: Candlestick Patterns | G17: 0.065 | H17: =IFERROR(__xludf.DUMMYFUNCTION("AI(""Fill an appropriate value for this cell based on the table context"")"),"⚪ New")
A18: Finance with Aarati | B18: =IFERROR(__xludf.DUMMYFUNCTION("AI(""Fill an appropriate value for this cell based on the table context"")"),"https://www.youtube.com/@CATARUNJAGDISH") | C18: 28000 | D18: aarati@example.com | E18: Savings | F18: Gold vs Stocks | G18: 0.04 | H18: =IFERROR(__xludf.DUMMYFUNCTION("AI(""Fill an appropriate value for this cell based on the table context"")"),"⚪ New")
A19: Anamika | B19: =IFERROR(__xludf.DUMMYFUNCTION("AI(""Fill an appropriate value for this cell based on the table context"")"),"https://www.youtube.com/@BusinessLine") | C19: 12000 | D19: anamika@example.com | E19: Beginner Finance | F19: Opening Demat Account | G19: 0.055 | H19: =IFERROR(__xludf.DUMMYFUNCTION("AI(""Fill an appropriate value for this cell based on the table context"")"),"⚪ New")
A20: Kushal Lodha | B20: =IFERROR(__xludf.DUMMYFUNCTION("AI(""Fill an appropriate value for this cell based on the table context"")"),"https://www.youtube.com/@Anamika_18") | C20: 98000 | D20: kushal@example.com | E20: Career/Finance | F20: Salary Negotiations | G20: 0.032 | H20: =IFERROR(__xludf.DUMMYFUNCTION("AI(""Fill an appropriate value for this cell based on the table context"")"),"⚪ New")
A21: Aditya Saini | B21: =IFERROR(__xludf.DUMMYFUNCTION("AI(""Fill an appropriate value for this cell based on the table context"")"),"https://www.youtube.com/@KushalLodha548") | C21: 75000 | D21: aditya@example.com | E21: Trading News | F21: Market Wrap-up | G21: 0.038 | H21: =IFERROR(__xludf.DUMMYFUNCTION("AI(""Fill an appropriate value for this cell based on the table context"")"),"⚪ New")

Sheet Referral & Revenue Tracker
A1: Partner Name | B1: Custom Slug | C1: Total Clicks | D1: Signups | E1: Activations | F1: Commission Earned
A2: Arnab Nayak | B2: fnomo-arnab | C2: 1500 | D2: 300 | E2: 50 | F2: =E2*200
A3: Brahmi Kapasi | B3: fnomo-brahmi | C3: 800 | D3: 150 | E3: 20 | F3: =E3*200
A4: Yash Gupta | B4: fnomo-yash | C4: 1200 | D4: 200 | E4: 35 | F4: =E4*200

Sheet Social Proof Repository
A1: User ID | B1: Decision Moment | C1: Fnomo Score | D1: Risk Level | E1: The Outcome | F1: Narrative Story
A2: U-101 | B2: Paytm IPO | C2: 3 | D2: High | E2: Avoided buying at listing | F2: I was caught up in the hype and almost bought Paytm on listing day. Fnomo's low score made me wait, saving me from a massive 30% drop.
A3: U-102 | B3: HDFC Bank Dip | C3: 8 | D3: Low | E3: Bought the dip | F3: HDFC Bank was falling and I was panicking to sell. Fnomo highlighted the strong fundamentals and low risk, giving me the confidence to buy more instead.
A4: U-103 | B4: Random Crypto Coin | C4: 2 | D4: Very High | E4: Cancelled order | F4: A friend recommended a new crypto coin that was trending on Twitter. Fnomo flagged it as a high-risk speculative asset, so I cancelled my buy order and avoided a rug pull.

Sheet Corporate Pilot Outreach
B2: CORPORATE PILOT: LEADERSHIP SESSIONS
B3: Setup (Green) | Outreach (Purple) | Meeting (Yellow) | Closed (Orange)
B5: Lead ID | C5: Status | D5: Company Name | E5: HR/Leadership Contact | F5: Decision Proximity (1-10) | G5: Sent Date | H5: Email/LinkedIn | I5: Feedback/Notes
B6: 1 | C6: ⚪ New | D6: Tata | I6: Leadership Investing Session
B7: 2 | C7: ⚪ New | D7: Infosys | I7: Leadership Investing Session
B8: 3 | C8: ⚪ New | D8: Reliance | I8: Leadership Investing Session

Sheet Telegram_War_Room
B2: TELEGRAM: ADMIN & COMMUNITY OUTREACH
B3: Setup (Green) | Outreach (Purple) | Meeting (Yellow) | Closed (Orange)
B5: Lead ID | C5: Status | D5: Group Name | E5: Admin Handle (@) | F5: Decision Proximity (1-10) | G5: Influence Score | H5: The Hook | I5: Next Action
B6: =IFERROR(__xludf.DUMMYFUNCTION("IFERROR(CHOOSECOLS(FILTER(Outreach_Database!A2:R1000, Outreach_Database!I2:I1000=""Telegram""), 1, 2, 5, 15, 16, 18, 17, 13), ""No data found"")"),51) | C6: =IFERROR(__xludf.DUMMYFUNCTION("""COMPUTED_VALUE"""),"⚪ New") | D6: =IFERROR(__xludf.DUMMYFUNCTION("""COMPUTED_VALUE"""),"Nifty Stock Trades")
B7: =IFERROR(__xludf.DUMMYFUNCTION("""COMPUTED_VALUE"""),52) | C7: =IFERROR(__xludf.DUMMYFUNCTION("""COMPUTED_VALUE"""),"⚪ New") | D7: =IFERROR(__xludf.DUMMYFUNCTION("""COMPUTED_VALUE"""),"Esha Analysis")
B8: =IFERROR(__xludf.DUMMYFUNCTION("""COMPUTED_VALUE"""),53) | C8: =IFERROR(__xludf.DUMMYFUNCTION("""COMPUTED_VALUE"""),"⚪ New") | D8: =IFERROR(__xludf.DUMMYFUNCTION("""COMPUTED_VALUE"""),"Vijay Wealth Advisor")
B9: =IFERROR(__xludf.DUMMYFUNCTION("""COMPUTED_VALUE"""),54) | C9: =IFERROR(__xludf.DUMMYFUNCTION("""COMPUTED_VALUE"""),"⚪ New") | D9: =IFERROR(__xludf.DUMMYFUNCTION("""COMPUTED_VALUE"""),"Trading Saint Official")
B10: =IFERROR(__xludf.DUMMYFUNCTION("""COMPUTED_VALUE"""),55) | C10: =IFERROR(__xludf.DUMMYFUNCTION("""COMPUTED_VALUE"""),"⚪ New") | D10: =IFERROR(__xludf.DUMMYFUNCTION("""COMPUTED_VALUE"""),"Share Stock Market Calls")
B11: =IFERROR(__xludf.DUMMYFUNCTION("""COMPUTED_VALUE"""),56) | C11: =IFERROR(__xludf.DUMMYFUNCTION("""COMPUTED_VALUE"""),"⚪ New") | D11: =IFERROR(__xludf.DUMMYFUNCTION("""COMPUTED_VALUE"""),"Trade Watcher")
B12: =IFERROR(__xludf.DUMMYFUNCTION("""COMPUTED_VALUE"""),57) | C12: =IFERROR(__xludf.DUMMYFUNCTION("""COMPUTED_VALUE"""),"⚪ New") | D12: =IFERROR(__xludf.DUMMYFUNCTION("""COMPUTED_VALUE"""),"Daily Option Profit")
B13: =IFERROR(__xludf.DUMMYFUNCTION("""COMPUTED_VALUE"""),58) | C13: =IFERROR(__xludf.DUMMYFUNCTION("""COMPUTED_VALUE"""),"⚪ New") | D13: =IFERROR(__xludf.DUMMYFUNCTION("""COMPUTED_VALUE"""),"Chawla Stock Market")
B14: =IFERROR(__xludf.DUMMYFUNCTION("""COMPUTED_VALUE"""),59) | C14: =IFERROR(__xludf.DUMMYFUNCTION("""COMPUTED_VALUE"""),"⚪ New") | D14: =IFERROR(__xludf.DUMMYFUNCTION("""COMPUTED_VALUE"""),"ASHA Stock Market")
B15: =IFERROR(__xludf.DUMMYFUNCTION("""COMPUTED_VALUE"""),60) | C15: =IFERROR(__xludf.DUMMYFUNCTION("""COMPUTED_VALUE"""),"⚪ New") | D15: =IFERROR(__xludf.DUMMYFUNCTION("""COMPUTED_VALUE"""),"IPO Ji ™️")
B16: =IFERROR(__xludf.DUMMYFUNCTION("""COMPUTED_VALUE"""),61) | C16: =IFERROR(__xludf.DUMMYFUNCTION("""COMPUTED_VALUE"""),"⚪ New") | D16: =IFERROR(__xludf.DUMMYFUNCTION("""COMPUTED_VALUE"""),"Trading with CA Abhay")
B17: =IFERROR(__xludf.DUMMYFUNCTION("""COMPUTED_VALUE"""),62) | C17: =IFERROR(__xludf.DUMMYFUNCTION("""COMPUTED_VALUE"""),"⚪ New") | D17: =IFERROR(__xludf.DUMMYFUNCTION("""COMPUTED_VALUE"""),"Index Trading (Nitin Murarka)")
B18: =IFERROR(__xludf.DUMMYFUNCTION("""COMPUTED_VALUE"""),63) | C18: =IFERROR(__xludf.DUMMYFUNCTION("""COMPUTED_VALUE"""),"⚪ New") | D18: =IFERROR(__xludf.DUMMYFUNCTION("""COMPUTED_VALUE"""),"Whale Alert")
B19: =IFERROR(__xludf.DUMMYFUNCTION("""COMPUTED_VALUE"""),64) | C19: =IFERROR(__xludf.DUMMYFUNCTION("""COMPUTED_VALUE"""),"⚪ New") | D19: =IFERROR(__xludf.DUMMYFUNCTION("""COMPUTED_VALUE"""),"CoinCodex")
B20: =IFERROR(__xludf.DUMMYFUNCTION("""COMPUTED_VALUE"""),65) | C20: =IFERROR(__xludf.DUMMYFUNCTION("""COMPUTED_VALUE"""),"⚪ New") | D20: =IFERROR(__xludf.DUMMYFUNCTION("""COMPUTED_VALUE"""),"The Block News")
B21: =IFERROR(__xludf.DUMMYFUNCTION("""COMPUTED_VALUE"""),66) | C21: =IFERROR(__xludf.DUMMYFUNCTION("""COMPUTED_VALUE"""),"⚪ New") | D21: =IFERROR(__xludf.DUMMYFUNCTION("""COMPUTED_VALUE"""),"Binance Killers")
B22: =IFERROR(__xludf.DUMMYFUNCTION("""COMPUTED_VALUE"""),67) | C22: =IFERROR(__xludf.DUMMYFUNCTION("""COMPUTED_VALUE"""),"⚪ New") | D22: =IFERROR(__xludf.DUMMYFUNCTION("""COMPUTED_VALUE"""),"Wolf of Trading")
B23: =IFERROR(__xludf.DUMMYFUNCTION("""COMPUTED_VALUE"""),68) | C23: =IFERROR(__xludf.DUMMYFUNCTION("""COMPUTED_VALUE"""),"⚪ New") | D23: =IFERROR(__xludf.DUMMYFUNCTION("""COMPUTED_VALUE"""),"Crypto Inner Circle")
B24: =IFERROR(__xludf.DUMMYFUNCTION("""COMPUTED_VALUE"""),69) | C24: =IFERROR(__xludf.DUMMYFUNCTION("""COMPUTED_VALUE"""),"⚪ New") | D24: =IFERROR(__xludf.DUMMYFUNCTION("""COMPUTED_VALUE"""),"Bitcoin Bullets")
B25: =IFERROR(__xludf.DUMMYFUNCTION("""COMPUTED_VALUE"""),70) | C25: =IFERROR(__xludf.DUMMYFUNCTION("""COMPUTED_VALUE"""),"⚪ New") | D25: =IFERROR(__xludf.DUMMYFUNCTION("""COMPUTED_VALUE"""),"Wall Street Queen")
B26: =IFERROR(__xludf.DUMMYFUNCTION("""COMPUTED_VALUE"""),71) | C26: =IFERROR(__xludf.DUMMYFUNCTION("""COMPUTED_VALUE"""),"⚪ New") | D26: =IFERROR(__xludf.DUMMYFUNCTION("""COMPUTED_VALUE"""),"Stock Market Adda")
B27: =IFERROR(__xludf.DUMMYFUNCTION("""COMPUTED_VALUE"""),72) | C27: =IFERROR(__xludf.DUMMYFUNCTION("""COMPUTED_VALUE"""),"⚪ New") | D27: =IFERROR(__xludf.DUMMYFUNCTION("""COMPUTED_VALUE"""),"Dark Horse of Stock Market")
B28: =IFERROR(__xludf.DUMMYFUNCTION("""COMPUTED_VALUE"""),73) | C28: =IFERROR(__xludf.DUMMYFUNCTION("""COMPUTED_VALUE"""),"⚪ New") | D28: =IFERROR(__xludf.DUMMYFUNCTION("""COMPUTED_VALUE"""),"Mr Scalper Official")
B29: =IFERROR(__xludf.DUMMYFUNCTION("""COMPUTED_VALUE"""),74) | C29: =IFERROR(__xludf.DUMMYFUNCTION("""COMPUTED_VALUE"""),"⚪ New") | D29: =IFERROR(__xludf.DUMMYFUNCTION("""COMPUTED_VALUE"""),"20PAISA.COM")
B30: =IFERROR(__xludf.DUMMYFUNCTION("""COMPUTED_VALUE"""),75) | C30: =IFERROR(__xludf.DUMMYFUNCTION("""COMPUTED_VALUE"""),"⚪ New") | D30: =IFERROR(__xludf.DUMMYFUNCTION("""COMPUTED_VALUE"""),"Bharath's Market Research")
B31: =IFERROR(__xludf.DUMMYFUNCTION("""COMPUTED_VALUE"""),76) | C31: =IFERROR(__xludf.DUMMYFUNCTION("""COMPUTED_VALUE"""),"⚪ New") | D31: =IFERROR(__xludf.DUMMYFUNCTION("""COMPUTED_VALUE"""),"Stockizen Research")
B32: =IFERROR(__xludf.DUMMYFUNCTION("""COMPUTED_VALUE"""),77) | C32: =IFERROR(__xludf.DUMMYFUNCTION("""COMPUTED_VALUE"""),"⚪ New") | D32: =IFERROR(__xludf.DUMMYFUNCTION("""COMPUTED_VALUE"""),"Eqwires Research")
B33: =IFERROR(__xludf.DUMMYFUNCTION("""COMPUTED_VALUE"""),78) | C33: =IFERROR(__xludf.DUMMYFUNCTION("""COMPUTED_VALUE"""),"⚪ New") | D33: =IFERROR(__xludf.DUMMYFUNCTION("""COMPUTED_VALUE"""),"StockYaari Premium")
B34: =IFERROR(__xludf.DUMMYFUNCTION("""COMPUTED_VALUE"""),79) | C34: =IFERROR(__xludf.DUMMYFUNCTION("""COMPUTED_VALUE"""),"⚪ New") | D34: =IFERROR(__xludf.DUMMYFUNCTION("""COMPUTED_VALUE"""),"Flying Calls")
B35: =IFERROR(__xludf.DUMMYFUNCTION("""COMPUTED_VALUE"""),80) | C35: =IFERROR(__xludf.DUMMYFUNCTION("""COMPUTED_VALUE"""),"⚪ New") | D35: =IFERROR(__xludf.DUMMYFUNCTION("""COMPUTED_VALUE"""),"Rakesh Bansal Ventures")
B36: =IFERROR(__xludf.DUMMYFUNCTION("""COMPUTED_VALUE"""),81) | C36: =IFERROR(__xludf.DUMMYFUNCTION("""COMPUTED_VALUE"""),"⚪ New") | D36: =IFERROR(__xludf.DUMMYFUNCTION("""COMPUTED_VALUE"""),"IPO GMP Updates")
B37: =IFERROR(__xludf.DUMMYFUNCTION("""COMPUTED_VALUE"""),82) | C37: =IFERROR(__xludf.DUMMYFUNCTION("""COMPUTED_VALUE"""),"⚪ New") | D37: =IFERROR(__xludf.DUMMYFUNCTION("""COMPUTED_VALUE"""),"Mutual Fund Guides India")
B38: =IFERROR(__xludf.DUMMYFUNCTION("""COMPUTED_VALUE"""),83) | C38: =IFERROR(__xludf.DUMMYFUNCTION("""COMPUTED_VALUE"""),"⚪ New") | D38: =IFERROR(__xludf.DUMMYFUNCTION("""COMPUTED_VALUE"""),"Zerodha Traders Hub")
B39: =IFERROR(__xludf.DUMMYFUNCTION("""COMPUTED_VALUE"""),84) | C39: =IFERROR(__xludf.DUMMYFUNCTION("""COMPUTED_VALUE"""),"⚪ New") | D39: =IFERROR(__xludf.DUMMYFUNCTION("""COMPUTED_VALUE"""),"Upstox Power Traders")
B40: =IFERROR(__xludf.DUMMYFUNCTION("""COMPUTED_VALUE"""),85) | C40: =IFERROR(__xludf.DUMMYFUNCTION("""COMPUTED_VALUE"""),"⚪ New") | D40: =IFERROR(__xludf.DUMMYFUNCTION("""COMPUTED_VALUE"""),"Groww Investors Club")
B41: =IFERROR(__xludf.DUMMYFUNCTION("""COMPUTED_VALUE"""),86) | C41: =IFERROR(__xludf.DUMMYFUNCTION("""COMPUTED_VALUE"""),"⚪ New") | D41: =IFERROR(__xludf.DUMMYFUNCTION("""COMPUTED_VALUE"""),"Nifty Options Pro")
B42: =IFERROR(__xludf.DUMMYFUNCTION("""COMPUTED_VALUE"""),87) | C42: =IFERROR(__xludf.DUMMYFUNCTION("""COMPUTED_VALUE"""),"⚪ New") | D42: =IFERROR(__xludf.DUMMYFUNCTION("""COMPUTED_VALUE"""),"Bank Nifty Specialists")
B43: =IFERROR(__xludf.DUMMYFUNCTION("""COMPUTED_VALUE"""),88) | C43: =IFERROR(__xludf.DUMMYFUNCTION("""COMPUTED_VALUE"""),"⚪ New") | D43: =IFERROR(__xludf.DUMMYFUNCTION("""COMPUTED_VALUE"""),"Intraday Jackpot India")
B44: =IFERROR(__xludf.DUMMYFUNCTION("""COMPUTED_VALUE"""),89) | C44: =IFERROR(__xludf.DUMMYFUNCTION("""COMPUTED_VALUE"""),"⚪ New") | D44: =IFERROR(__xludf.DUMMYFUNCTION("""COMPUTED_VALUE"""),"Penny Stock Gems India")
B45: =IFERROR(__xludf.DUMMYFUNCTION("""COMPUTED_VALUE"""),90) | C45: =IFERROR(__xludf.DUMMYFUNCTION("""COMPUTED_VALUE"""),"⚪ New") | D45: =IFERROR(__xludf.DUMMYFUNCTION("""COMPUTED_VALUE"""),"Financial Literacy India")
B46: =IFERROR(__xludf.DUMMYFUNCTION("""COMPUTED_VALUE"""),91) | C46: =IFERROR(__xludf.DUMMYFUNCTION("""COMPUTED_VALUE"""),"⚪ New") | D46: =IFERROR(__xludf.DUMMYFUNCTION("""COMPUTED_VALUE"""),"Stock Market Tips SEBI")
B47: =IFERROR(__xludf.DUMMYFUNCTION("""COMPUTED_VALUE"""),92) | C47: =IFERROR(__xludf.DUMMYFUNCTION("""COMPUTED_VALUE"""),"⚪ New") | D47: =IFERROR(__xludf.DUMMYFUNCTION("""COMPUTED_VALUE"""),"Indian Share Market News")
B48: =IFERROR(__xludf.DUMMYFUNCTION("""COMPUTED_VALUE"""),93) | C48: =IFERROR(__xludf.DUMMYFUNCTION("""COMPUTED_VALUE"""),"⚪ New") | D48: =IFERROR(__xludf.DUMMYFUNCTION("""COMPUTED_VALUE"""),"Tax Planning India")
B49: =IFERROR(__xludf.DUMMYFUNCTION("""COMPUTED_VALUE"""),94) | C49: =IFERROR(__xludf.DUMMYFUNCTION("""COMPUTED_VALUE"""),"⚪ New") | D49: =IFERROR(__xludf.DUMMYFUNCTION("""COMPUTED_VALUE"""),"DeFi Million Official")
B50: =IFERROR(__xludf.DUMMYFUNCTION("""COMPUTED_VALUE"""),95) | C50: =IFERROR(__xludf.DUMMYFUNCTION("""COMPUTED_VALUE"""),"⚪ New") | D50: =IFERROR(__xludf.DUMMYFUNCTION("""COMPUTED_VALUE"""),"NFT Evening")
B51: =IFERROR(__xludf.DUMMYFUNCTION("""COMPUTED_VALUE"""),96) | C51: =IFERROR(__xludf.DUMMYFUNCTION("""COMPUTED_VALUE"""),"⚪ New") | D51: =IFERROR(__xludf.DUMMYFUNCTION("""COMPUTED_VALUE"""),"Crypto Inner Circle Official")
B52: =IFERROR(__xludf.DUMMYFUNCTION("""COMPUTED_VALUE"""),97) | C52: =IFERROR(__xludf.DUMMYFUNCTION("""COMPUTED_VALUE"""),"⚪ New") | D52: =IFERROR(__xludf.DUMMYFUNCTION("""COMPUTED_VALUE"""),"Glassnode On-Chain")
B53: =IFERROR(__xludf.DUMMYFUNCTION("""COMPUTED_VALUE"""),98) | C53: =IFERROR(__xludf.DUMMYFUNCTION("""COMPUTED_VALUE"""),"⚪ New") | D53: =IFERROR(__xludf.DUMMYFUNCTION("""COMPUTED_VALUE"""),"Evening Trader Spot/Futures")
B54: =IFERROR(__xludf.DUMMYFUNCTION("""COMPUTED_VALUE"""),99) | C54: =IFERROR(__xludf.DUMMYFUNCTION("""COMPUTED_VALUE"""),"⚪ New") | D54: =IFERROR(__xludf.DUMMYFUNCTION("""COMPUTED_VALUE"""),"Angel One Alerts Pro")
B55: =IFERROR(__xludf.DUMMYFUNCTION("""COMPUTED_VALUE"""),100) | C55: =IFERROR(__xludf.DUMMYFUNCTION("""COMPUTED_VALUE"""),"⚪ New") | D55: =IFERROR(__xludf.DUMMYFUNCTION("""COMPUTED_VALUE"""),"Stock Market Daily Analysis")
B56: =IFERROR(__xludf.DUMMYFUNCTION("""COMPUTED_VALUE"""),101) | C56: =IFERROR(__xludf.DUMMYFUNCTION("""COMPUTED_VALUE"""),"⚪ New") | D56: =IFERROR(__xludf.DUMMYFUNCTION("""COMPUTED_VALUE"""),"Sample Telegram Group")

Sheet Reddit_War_Room
B2: REDDIT: SUBREDDIT & ADVICE THREADS
B3: Setup (Green) | Outreach (Purple) | Meeting (Yellow) | Closed (Orange)
B5: Lead ID | C5: Status | D5: Subreddit | E5: Moderator/Target | F5: Decision Proximity | G5: Karma/Influence | H5: The Hook | I5: Post/Comment Link
B6: =IFERROR(__xludf.DUMMYFUNCTION("IFERROR(CHOOSECOLS(FILTER(Outreach_Database!A2:R1000, Outreach_Database!I2:I1000=""Reddit""), 1, 2, 5, 15, 16, 18, 17, 8), ""No data found"")"),1) | C6: =IFERROR(__xludf.DUMMYFUNCTION("""COMPUTED_VALUE"""),"⚪ New") | D6: =IFERROR(__xludf.DUMMYFUNCTION("""COMPUTED_VALUE"""),"r/IndiaInvestments") | I6: =IFERROR(__xludf.DUMMYFUNCTION("""COMPUTED_VALUE"""),"https://www.reddit.com/r/IndiaInvestments/")
B7: =IFERROR(__xludf.DUMMYFUNCTION("""COMPUTED_VALUE"""),2) | C7: =IFERROR(__xludf.DUMMYFUNCTION("""COMPUTED_VALUE"""),"⚪ New") | D7: =IFERROR(__xludf.DUMMYFUNCTION("""COMPUTED_VALUE"""),"r/IndianStreetBets") | I7: =IFERROR(__xludf.DUMMYFUNCTION("""COMPUTED_VALUE"""),"https://www.reddit.com/r/IndianStreetBets/")
B8: =IFERROR(__xludf.DUMMYFUNCTION("""COMPUTED_VALUE"""),3) | C8: =IFERROR(__xludf.DUMMYFUNCTION("""COMPUTED_VALUE"""),"⚪ New") | D8: =IFERROR(__xludf.DUMMYFUNCTION("""COMPUTED_VALUE"""),"r/PersonalFinanceIndia") | I8: =IFERROR(__xludf.DUMMYFUNCTION("""COMPUTED_VALUE"""),"https://www.reddit.com/r/personalfinanceindia/")
B9: =IFERROR(__xludf.DUMMYFUNCTION("""COMPUTED_VALUE"""),4) | C9: =IFERROR(__xludf.DUMMYFUNCTION("""COMPUTED_VALUE"""),"⚪ New") | D9: =IFERROR(__xludf.DUMMYFUNCTION("""COMPUTED_VALUE"""),"r/Indiantradingbets") | I9: =IFERROR(__xludf.DUMMYFUNCTION("""COMPUTED_VALUE"""),"https://www.reddit.com/r/Indiantradingbets/")
B10: =IFERROR(__xludf.DUMMYFUNCTION("""COMPUTED_VALUE"""),5) | C10: =IFERROR(__xludf.DUMMYFUNCTION("""COMPUTED_VALUE"""),"⚪ New") | D10: =IFERROR(__xludf.DUMMYFUNCTION("""COMPUTED_VALUE"""),"r/dalalstreetbets") | I10: =IFERROR(__xludf.DUMMYFUNCTION("""COMPUTED_VALUE"""),"https://www.reddit.com/r/dalalstreetbets/")
B11: =IFERROR(__xludf.DUMMYFUNCTION("""COMPUTED_VALUE"""),6) | C11: =IFERROR(__xludf.DUMMYFUNCTION("""COMPUTED_VALUE"""),"⚪ New") | D11: =IFERROR(__xludf.DUMMYFUNCTION("""COMPUTED_VALUE"""),"r/StockMarketIndia") | I11: =IFERROR(__xludf.DUMMYFUNCTION("""COMPUTED_VALUE"""),"https://www.reddit.com/r/StockMarketIndia/")
B12: =IFERROR(__xludf.DUMMYFUNCTION("""COMPUTED_VALUE"""),7) | C12: =IFERROR(__xludf.DUMMYFUNCTION("""COMPUTED_VALUE"""),"⚪ New") | D12: =IFERROR(__xludf.DUMMYFUNCTION("""COMPUTED_VALUE"""),"r/FIREIndia") | I12: =IFERROR(__xludf.DUMMYFUNCTION("""COMPUTED_VALUE"""),"https://www.reddit.com/r/FIREIndia/")
B13: =IFERROR(__xludf.DUMMYFUNCTION("""COMPUTED_VALUE"""),8) | C13: =IFERROR(__xludf.DUMMYFUNCTION("""COMPUTED_VALUE"""),"⚪ New") | D13: =IFERROR(__xludf.DUMMYFUNCTION("""COMPUTED_VALUE"""),"r/IndiaTax") | I13: =IFERROR(__xludf.DUMMYFUNCTION("""COMPUTED_VALUE"""),"https://www.reddit.com/r/IndiaTax/")
B14: =IFERROR(__xludf.DUMMYFUNCTION("""COMPUTED_VALUE"""),9) | C14: =IFERROR(__xludf.DUMMYFUNCTION("""COMPUTED_VALUE"""),"⚪ New") | D14: =IFERROR(__xludf.DUMMYFUNCTION("""COMPUTED_VALUE"""),"r/IndiaCreditCards") | I14: =IFERROR(__xludf.DUMMYFUNCTION("""COMPUTED_VALUE"""),"https://www.google.com/search?q=https://www.reddit.com/r/IndiaCreditCards/")
B15: =IFERROR(__xludf.DUMMYFUNCTION("""COMPUTED_VALUE"""),10) | C15: =IFERROR(__xludf.DUMMYFUNCTION("""COMPUTED_VALUE"""),"⚪ New") | D15: =IFERROR(__xludf.DUMMYFUNCTION("""COMPUTED_VALUE"""),"r/StartupIndia") | I15: =IFERROR(__xludf.DUMMYFUNCTION("""COMPUTED_VALUE"""),"https://www.reddit.com/r/StartupIndia/")
B16: =IFERROR(__xludf.DUMMYFUNCTION("""COMPUTED_VALUE"""),11) | C16: =IFERROR(__xludf.DUMMYFUNCTION("""COMPUTED_VALUE"""),"⚪ New") | D16: =IFERROR(__xludf.DUMMYFUNCTION("""COMPUTED_VALUE"""),"r/MutualFundsIndia") | I16: =IFERROR(__xludf.DUMMYFUNCTION("""COMPUTED_VALUE"""),"https://www.reddit.com/r/MutualFundsIndia/")
B17: =IFERROR(__xludf.DUMMYFUNCTION("""COMPUTED_VALUE"""),12) | C17: =IFERROR(__xludf.DUMMYFUNCTION("""COMPUTED_VALUE"""),"⚪ New") | D17: =IFERROR(__xludf.DUMMYFUNCTION("""COMPUTED_VALUE"""),"r/IndiaMarket") | I17: =IFERROR(__xludf.DUMMYFUNCTION("""COMPUTED_VALUE"""),"https://www.google.com/search?q=https://www.reddit.com/r/IndiaMarket/")
B18: =IFERROR(__xludf.DUMMYFUNCTION("""COMPUTED_VALUE"""),13) | C18: =IFERROR(__xludf.DUMMYFUNCTION("""COMPUTED_VALUE"""),"⚪ New") | D18: =IFERROR(__xludf.DUMMYFUNCTION("""COMPUTED_VALUE"""),"r/BusinessIndia") | I18: =IFERROR(__xludf.DUMMYFUNCTION("""COMPUTED_VALUE"""),"https://www.google.com/search?q=https://www.reddit.com/r/BusinessIndia/")
B19: =IFERROR(__xludf.DUMMYFUNCTION("""COMPUTED_VALUE"""),14) | C19: =IFERROR(__xludf.DUMMYFUNCTION("""COMPUTED_VALUE"""),"⚪ New") | D19: =IFERROR(__xludf.DUMMYFUNCTION("""COMPUTED_VALUE"""),"r/Nifty50") | I19: =IFERROR(__xludf.DUMMYFUNCTION("""COMPUTED_VALUE"""),"https://www.google.com/search?q=https://www.reddit.com/r/Nifty50/")
B20: =IFERROR(__xludf.DUMMYFUNCTION("""COMPUTED_VALUE"""),15) | C20: =IFERROR(__xludf.DUMMYFUNCTION("""COMPUTED_VALUE"""),"⚪ New") | D20: =IFERROR(__xludf.DUMMYFUNCTION("""COMPUTED_VALUE"""),"r/IndiaProperty") | I20: =IFERROR(__xludf.DUMMYFUNCTION("""COMPUTED_VALUE"""),"https://www.google.com/search?q=https://www.reddit.com/r/IndiaProperty/")
B21: =IFERROR(__xludf.DUMMYFUNCTION("""COMPUTED_VALUE"""),16) | C21: =IFERROR(__xludf.DUMMYFUNCTION("""COMPUTED_VALUE"""),"⚪ New") | D21: =IFERROR(__xludf.DUMMYFUNCTION("""COMPUTED_VALUE"""),"r/IndiaRealEstate") | I21: =IFERROR(__xludf.DUMMYFUNCTION("""COMPUTED_VALUE"""),"https://www.google.com/search?q=https://www.reddit.com/r/IndiaRealEstate/")
B22: =IFERROR(__xludf.DUMMYFUNCTION("""COMPUTED_VALUE"""),17) | C22: =IFERROR(__xludf.DUMMYFUNCTION("""COMPUTED_VALUE"""),"⚪ New") | D22: =IFERROR(__xludf.DUMMYFUNCTION("""COMPUTED_VALUE"""),"r/PassiveIncomeIndia") | I22: =IFERROR(__xludf.DUMMYFUNCTION("""COMPUTED_VALUE"""),"https://www.google.com/search?q=https://www.reddit.com/r/PassiveIncomeIndia/")
B23: =IFERROR(__xludf.DUMMYFUNCTION("""COMPUTED_VALUE"""),18) | C23: =IFERROR(__xludf.DUMMYFUNCTION("""COMPUTED_VALUE"""),"⚪ New") | D23: =IFERROR(__xludf.DUMMYFUNCTION("""COMPUTED_VALUE"""),"r/Finance") | I23: =IFERROR(__xludf.DUMMYFUNCTION("""COMPUTED_VALUE"""),"https://www.reddit.com/r/Finance/")
B24: =IFERROR(__xludf.DUMMYFUNCTION("""COMPUTED_VALUE"""),19) | C24: =IFERROR(__xludf.DUMMYFUNCTION("""COMPUTED_VALUE"""),"⚪ New") | D24: =IFERROR(__xludf.DUMMYFUNCTION("""COMPUTED_VALUE"""),"r/FinancialPlanning") | I24: =IFERROR(__xludf.DUMMYFUNCTION("""COMPUTED_VALUE"""),"https://www.reddit.com/r/FinancialPlanning/")
B25: =IFERROR(__xludf.DUMMYFUNCTION("""COMPUTED_VALUE"""),20) | C25: =IFERROR(__xludf.DUMMYFUNCTION("""COMPUTED_VALUE"""),"⚪ New") | D25: =IFERROR(__xludf.DUMMYFUNCTION("""COMPUTED_VALUE"""),"r/Investing") | I25: =IFERROR(__xludf.DUMMYFUNCTION("""COMPUTED_VALUE"""),"https://www.reddit.com/r/Investing/")
B26: =IFERROR(__xludf.DUMMYFUNCTION("""COMPUTED_VALUE"""),21) | C26: =IFERROR(__xludf.DUMMYFUNCTION("""COMPUTED_VALUE"""),"⚪ New") | D26: =IFERROR(__xludf.DUMMYFUNCTION("""COMPUTED_VALUE"""),"r/Retirement") | I26: =IFERROR(__xludf.DUMMYFUNCTION("""COMPUTED_VALUE"""),"https://www.reddit.com/r/Retirement/")
B27: =IFERROR(__xludf.DUMMYFUNCTION("""COMPUTED_VALUE"""),22) | C27: =IFERROR(__xludf.DUMMYFUNCTION("""COMPUTED_VALUE"""),"⚪ New") | D27: =IFERROR(__xludf.DUMMYFUNCTION("""COMPUTED_VALUE"""),"r/CreditCards") | I27: =IFERROR(__xludf.DUMMYFUNCTION("""COMPUTED_VALUE"""),"https://www.reddit.com/r/CreditCards/")
B28: =IFERROR(__xludf.DUMMYFUNCTION("""COMPUTED_VALUE"""),23) | C28: =IFERROR(__xludf.DUMMYFUNCTION("""COMPUTED_VALUE"""),"⚪ New") | D28: =IFERROR(__xludf.DUMMYFUNCTION("""COMPUTED_VALUE"""),"r/Tax") | I28: =IFERROR(__xludf.DUMMYFUNCTION("""COMPUTED_VALUE"""),"https://www.reddit.com/r/Tax/")
B29: =IFERROR(__xludf.DUMMYFUNCTION("""COMPUTED_VALUE"""),24) | C29: =IFERROR(__xludf.DUMMYFUNCTION("""COMPUTED_VALUE"""),"⚪ New") | D29: =IFERROR(__xludf.DUMMYFUNCTION("""COMPUTED_VALUE"""),"r/Economics") | I29: =IFERROR(__xludf.DUMMYFUNCTION("""COMPUTED_VALUE"""),"https://www.reddit.com/r/Economics/")
B30: =IFERROR(__xludf.DUMMYFUNCTION("""COMPUTED_VALUE"""),25) | C30: =IFERROR(__xludf.DUMMYFUNCTION("""COMPUTED_VALUE"""),"⚪ New") | D30: =IFERROR(__xludf.DUMMYFUNCTION("""COMPUTED_VALUE"""),"r/CryptoCurrency") | I30: =IFERROR(__xludf.DUMMYFUNCTION("""COMPUTED_VALUE"""),"https://www.reddit.com/r/CryptoCurrency/")
B31: =IFERROR(__xludf.DUMMYFUNCTION("""COMPUTED_VALUE"""),26) | C31: =IFERROR(__xludf.DUMMYFUNCTION("""COMPUTED_VALUE"""),"⚪ New") | D31: =IFERROR(__xludf.DUMMYFUNCTION("""COMPUTED_VALUE"""),"r/SecurityAnalysis") | I31: =IFERROR(__xludf.DUMMYFUNCTION("""COMPUTED_VALUE"""),"https://www.reddit.com/r/SecurityAnalysis/")
B32: =IFERROR(__xludf.DUMMYFUNCTION("""COMPUTED_VALUE"""),27) | C32: =IFERROR(__xludf.DUMMYFUNCTION("""COMPUTED_VALUE"""),"⚪ New") | D32: =IFERROR(__xludf.DUMMYFUNCTION("""COMPUTED_VALUE"""),"r/PovertyFinance") | I32: =IFERROR(__xludf.DUMMYFUNCTION("""COMPUTED_VALUE"""),"https://www.reddit.com/r/PovertyFinance/")
B33: =IFERROR(__xludf.DUMMYFUNCTION("""COMPUTED_VALUE"""),28) | C33: =IFERROR(__xludf.DUMMYFUNCTION("""COMPUTED_VALUE"""),"⚪ New") | D33: =IFERROR(__xludf.DUMMYFUNCTION("""COMPUTED_VALUE"""),"r/Frugal") | I33: =IFERROR(__xludf.DUMMYFUNCTION("""COMPUTED_VALUE"""),"https://www.reddit.com/r/Frugal/")
B34: =IFERROR(__xludf.DUMMYFUNCTION("""COMPUTED_VALUE"""),29) | C34: =IFERROR(__xludf.DUMMYFUNCTION("""COMPUTED_VALUE"""),"⚪ New") | D34: =IFERROR(__xludf.DUMMYFUNCTION("""COMPUTED_VALUE"""),"r/SaaS") | I34: =IFERROR(__xludf.DUMMYFUNCTION("""COMPUTED_VALUE"""),"https://www.reddit.com/r/SaaS/")
B35: =IFERROR(__xludf.DUMMYFUNCTION("""COMPUTED_VALUE"""),30) | C35: =IFERROR(__xludf.DUMMYFUNCTION("""COMPUTED_VALUE"""),"⚪ New") | D35: =IFERROR(__xludf.DUMMYFUNCTION("""COMPUTED_VALUE"""),"r/Entrepreneur") | I35: =IFERROR(__xludf.DUMMYFUNCTION("""COMPUTED_VALUE"""),"https://www.reddit.com/r/Entrepreneur/")
B36: =IFERROR(__xludf.DUMMYFUNCTION("""COMPUTED_VALUE"""),31) | C36: =IFERROR(__xludf.DUMMYFUNCTION("""COMPUTED_VALUE"""),"⚪ New") | D36: =IFERROR(__xludf.DUMMYFUNCTION("""COMPUTED_VALUE"""),"r/Dividends") | I36: =IFERROR(__xludf.DUMMYFUNCTION("""COMPUTED_VALUE"""),"https://www.reddit.com/r/Dividends/")
B37: =IFERROR(__xludf.DUMMYFUNCTION("""COMPUTED_VALUE"""),32) | C37: =IFERROR(__xludf.DUMMYFUNCTION("""COMPUTED_VALUE"""),"⚪ New") | D37: =IFERROR(__xludf.DUMMYFUNCTION("""COMPUTED_VALUE"""),"r/DayTrading") | I37: =IFERROR(__xludf.DUMMYFUNCTION("""COMPUTED_VALUE"""),"https://www.reddit.com/r/DayTrading/")
B38: =IFERROR(__xludf.DUMMYFUNCTION("""COMPUTED_VALUE"""),33) | C38: =IFERROR(__xludf.DUMMYFUNCTION("""COMPUTED_VALUE"""),"⚪ New") | D38: =IFERROR(__xludf.DUMMYFUNCTION("""COMPUTED_VALUE"""),"r/TechnicalAnalysis") | I38: =IFERROR(__xludf.DUMMYFUNCTION("""COMPUTED_VALUE"""),"https://www.reddit.com/r/TechnicalAnalysis/")
B39: =IFERROR(__xludf.DUMMYFUNCTION("""COMPUTED_VALUE"""),34) | C39: =IFERROR(__xludf.DUMMYFUNCTION("""COMPUTED_VALUE"""),"⚪ New") | D39: =IFERROR(__xludf.DUMMYFUNCTION("""COMPUTED_VALUE"""),"r/AlgoTrading") | I39: =IFERROR(__xludf.DUMMYFUNCTION("""COMPUTED_VALUE"""),"https://www.reddit.com/r/AlgoTrading/")
B40: =IFERROR(__xludf.DUMMYFUNCTION("""COMPUTED_VALUE"""),35) | C40: =IFERROR(__xludf.DUMMYFUNCTION("""COMPUTED_VALUE"""),"⚪ New") | D40: =IFERROR(__xludf.DUMMYFUNCTION("""COMPUTED_VALUE"""),"r/IndiaSpeaks (Finance)") | I40: =IFERROR(__xludf.DUMMYFUNCTION("""COMPUTED_VALUE"""),"https://www.reddit.com/r/IndiaSpeaks/")
B41: =IFERROR(__xludf.DUMMYFUNCTION("""COMPUTED_VALUE"""),36) | C41: =IFERROR(__xludf.DUMMYFUNCTION("""COMPUTED_VALUE"""),"⚪ New") | D41: =IFERROR(__xludf.DUMMYFUNCTION("""COMPUTED_VALUE"""),"r/India (Economy)") | I41: =IFERROR(__xludf.DUMMYFUNCTION("""COMPUTED_VALUE"""),"https://www.reddit.com/r/india/")
B42: =IFERROR(__xludf.DUMMYFUNCTION("""COMPUTED_VALUE"""),37) | C42: =IFERROR(__xludf.DUMMYFUNCTION("""COMPUTED_VALUE"""),"⚪ New") | D42: =IFERROR(__xludf.DUMMYFUNCTION("""COMPUTED_VALUE"""),"r/BombayStockExchange") | I42: =IFERROR(__xludf.DUMMYFUNCTION("""COMPUTED_VALUE"""),"https://www.google.com/search?q=https://www.reddit.com/r/BombayStockExchange/")
B43: =IFERROR(__xludf.DUMMYFUNCTION("""COMPUTED_VALUE"""),38) | C43: =IFERROR(__xludf.DUMMYFUNCTION("""COMPUTED_VALUE"""),"⚪ New") | D43: =IFERROR(__xludf.DUMMYFUNCTION("""COMPUTED_VALUE"""),"r/NSEIndia") | I43: =IFERROR(__xludf.DUMMYFUNCTION("""COMPUTED_VALUE"""),"https://www.google.com/search?q=https://www.reddit.com/r/NSEIndia/")
B44: =IFERROR(__xludf.DUMMYFUNCTION("""COMPUTED_VALUE"""),39) | C44: =IFERROR(__xludf.DUMMYFUNCTION("""COMPUTED_VALUE"""),"⚪ New") | D44: =IFERROR(__xludf.DUMMYFUNCTION("""COMPUTED_VALUE"""),"r/WallStreetBets") | I44: =IFERROR(__xludf.DUMMYFUNCTION("""COMPUTED_VALUE"""),"https://www.reddit.com/r/wallstreetbets/")
B45: =IFERROR(__xludf.DUMMYFUNCTION("""COMPUTED_VALUE"""),40) | C45: =IFERROR(__xludf.DUMMYFUNCTION("""COMPUTED_VALUE"""),"⚪ New") | D45: =IFERROR(__xludf.DUMMYFUNCTION("""COMPUTED_VALUE"""),"r/OptionsTrading") | I45: =IFERROR(__xludf.DUMMYFUNCTION("""COMPUTED_VALUE"""),"https://www.reddit.com/r/optionstrading/")
B46: =IFERROR(__xludf.DUMMYFUNCTION("""COMPUTED_VALUE"""),41) | C46: =IFERROR(__xludf.DUMMYFUNCTION("""COMPUTED_VALUE"""),"⚪ New") | D46: =IFERROR(__xludf.DUMMYFUNCTION("""COMPUTED_VALUE"""),"r/PennyStocks") | I46: =IFERROR(__xludf.DUMMYFUNCTION("""COMPUTED_VALUE"""),"https://www.reddit.com/r/pennystocks/")
B47: =IFERROR(__xludf.DUMMYFUNCTION("""COMPUTED_VALUE"""),42) | C47: =IFERROR(__xludf.DUMMYFUNCTION("""COMPUTED_VALUE"""),"⚪ New") | D47: =IFERROR(__xludf.DUMMYFUNCTION("""COMPUTED_VALUE"""),"r/Bitcoin") | I47: =IFERROR(__xludf.DUMMYFUNCTION("""COMPUTED_VALUE"""),"https://www.reddit.com/r/Bitcoin/")
B48: =IFERROR(__xludf.DUMMYFUNCTION("""COMPUTED_VALUE"""),43) | C48: =IFERROR(__xludf.DUMMYFUNCTION("""COMPUTED_VALUE"""),"⚪ New") | D48: =IFERROR(__xludf.DUMMYFUNCTION("""COMPUTED_VALUE"""),"r/Ethereum") | I48: =IFERROR(__xludf.DUMMYFUNCTION("""COMPUTED_VALUE"""),"https://www.reddit.com/r/ethereum/")
B49: =IFERROR(__xludf.DUMMYFUNCTION("""COMPUTED_VALUE"""),44) | C49: =IFERROR(__xludf.DUMMYFUNCTION("""COMPUTED_VALUE"""),"⚪ New") | D49: =IFERROR(__xludf.DUMMYFUNCTION("""COMPUTED_VALUE"""),"r/NFT") | I49: =IFERROR(__xludf.DUMMYFUNCTION("""COMPUTED_VALUE"""),"https://www.reddit.com/r/NFT/")
B50: =IFERROR(__xludf.DUMMYFUNCTION("""COMPUTED_VALUE"""),45) | C50: =IFERROR(__xludf.DUMMYFUNCTION("""COMPUTED_VALUE"""),"⚪ New") | D50: =IFERROR(__xludf.DUMMYFUNCTION("""COMPUTED_VALUE"""),"r/StockMarket") | I50: =IFERROR(__xludf.DUMMYFUNCTION("""COMPUTED_VALUE"""),"https://www.reddit.com/r/StockMarket/")
B51: =IFERROR(__xludf.DUMMYFUNCTION("""COMPUTED_VALUE"""),46) | C51: =IFERROR(__xludf.DUMMYFUNCTION("""COMPUTED_VALUE"""),"⚪ New") | D51: =IFERROR(__xludf.DUMMYFUNCTION("""COMPUTED_VALUE"""),"r/SmallCaps") | I51: =IFERROR(__xludf.DUMMYFUNCTION("""COMPUTED_VALUE"""),"https://www.reddit.com/r/smallcaps/")
B52: =IFERROR(__xludf.DUMMYFUNCTION("""COMPUTED_VALUE"""),47) | C52: =IFERROR(__xludf.DUMMYFUNCTION("""COMPUTED_VALUE"""),"⚪ New") | D52: =IFERROR(__xludf.DUMMYFUNCTION("""COMPUTED_VALUE"""),"r/ValueInvesting") | I52: =IFERROR(__xludf.DUMMYFUNCTION("""COMPUTED_VALUE"""),"https://www.reddit.com/r/ValueInvesting/")
B53: =IFERROR(__xludf.DUMMYFUNCTION("""COMPUTED_VALUE"""),48) | C53: =IFERROR(__xludf.DUMMYFUNCTION("""COMPUTED_VALUE"""),"⚪ New") | D53: =IFERROR(__xludf.DUMMYFUNCTION("""COMPUTED_VALUE"""),"r/FinancialCareers") | I53: =IFERROR(__xludf.DUMMYFUNCTION("""COMPUTED_VALUE"""),"https://www.reddit.com/r/FinancialCareers/")
B54: =IFERROR(__xludf.DUMMYFUNCTION("""COMPUTED_VALUE"""),49) | C54: =IFERROR(__xludf.DUMMYFUNCTION("""COMPUTED_VALUE"""),"⚪ New") | D54: =IFERROR(__xludf.DUMMYFUNCTION("""COMPUTED_VALUE"""),"r/StudentLoans") | I54: =IFERROR(__xludf.DUMMYFUNCTION("""COMPUTED_VALUE"""),"https://www.reddit.com/r/StudentLoans/")
B55: =IFERROR(__xludf.DUMMYFUNCTION("""COMPUTED_VALUE"""),50) | C55: =IFERROR(__xludf.DUMMYFUNCTION("""COMPUTED_VALUE"""),"⚪ New") | D55: =IFERROR(__xludf.DUMMYFUNCTION("""COMPUTED_VALUE"""),"r/PFTools") | I55: =IFERROR(__xludf.DUMMYFUNCTION("""COMPUTED_VALUE"""),"https://www.reddit.com/r/PFTools/")

Sheet Institutional School Outreach
A1: Tier | B1: School Name | C1: Principal | D1: Remarks | E1: Phone | F1: Mobile | H1: Email | I1: Website | J1: Area | K1: Notes
A2: Tier A | B2: The Sanskaar Valley School | C2: Chandresh Shah | E2: +91-755-2429090 | F2: 8889533346 | H2: info@sanskaarvalley.org | I2: sanskaarvalley.org | J2: Chandanpura | K2: Premium, high decision quality
A3: Tier A | B3: Delhi Public School, Kolar Road | C3: Vandana Dhupar | E3: +91-755-2696633 | F3: 7552433900 | H3: dpskolar@gmail.com | I3: dpskolar.org | J3: Kolar Rd | K3: Strong brand, scalable
A4: Tier A | B4: Delhi Public School, Neelbad | C4: Vinita Malik | E4: +91-755-3020300 | F4: 7556611400 | H4: info@dpsneelbad.com | I4: dpsneelbad.com | J4: Neelbad | K4: Large student base
A5: Tier A | B5: Sagar Public School, Saket Nagar | C5: ms Pankaj Sharma | D5: email required by school | E5: +91-755-2487771 | F5: 7552489601 | G5: principal.spssn@spabhopal.ac.in | H5: spssaket@spsbhopal.ac.in | I5: spsbhopal.ac.in | J5: Saket Nagar | K5: Multi-branch network
A6: Tier A | B6: Campion School | C6: Dr. Fr. Athnas Lakra S.J. | E6: +91-755-2761650 | F6: 7552464426 | H6: campionbhopal@gmail.com | I6: campionbhopal.org | J6: Arera Colony | K6: Legacy institution
A7: Tier B | B7: St. Joseph’s Co-Ed School | C7: Fr. Ronald | E7: +91-755-2767465 | F7: 7554295084 | H7: sjcsbhopal@gmail.com | I7: sjcsbhopal.org | J7: Arera Colony | K7: Strong academics
A8: Tier B | B8: International Public School | C8: Deepti Singh | E8: +91-755-2468090 | F8: 8966884422 | G8: Principal@ipsbhopal.com | H8: ipsbhopal@ipsacademy.org | I8: ipsbhopal.com | J8: Misrod | K8: Growth-focused
A9: Tier B | B9: Billabong High International School | C9: Ashish Agarwal | E9: 9109914228 | G9: abhyamashish@gmail.com | H9: bhisbhopal@kangarookids.co.in | I9: billabonghigh.com | J9: Bawadia Kalan | K9: Premium positioning
A10: Tier B | B10: Ryan International School | C10: Sarika Chourasia | D10: Not working till 24 | E10: +91-755-6461111 | F10: 9981828576 | G10: IES.bhopal@ryangroup.org | H10: ris.bhopal@ryangroup.org | I10: ryaninternational.org | J10: BHEL | K10: Structured system
A11: Tier B | B11: Trinity Convent School | E11: +91-755-2577770 | F11: 7592250932 | H11: trinityconvent@yahoo.com | I11: — | J11: Shahpura | K11: Good local reputation
A12: Tier C | B12: Maharishi Vidya Mandir | C12: Mamta Bhattacharjee | E12: +91-755-2429441 | F12: 7554000626 | G12: mvmbhopal1@mss.mail.org | H12: mvm@maharishividyamandir.com | I12: mvm.org | J12: Bhopal | K12: Network leverage
A13: Tier C | B13: Bal Bhavan School | C13: Humaira Arif | E13: +91-755-2552222 | H13: balbhavan@gmail.com | I13: — | J13: Shamla Hills | K13: Known name
A14: Tier C | B14: St. Mary’s Convent School | C14: Sr. Maria Jagtap | E14: +91-755-2742224 | H14: stmarysbhopal@gmail.com | I14: — | J14: Kohefiza | K14: Easy access
A15: Tier C | B15: Holy Cross School | C15: Sr. Mary Infaniza | E15: +91-755-2744441 | H15: holycrossbhopal@gmail.com | I15: — | J15: Lambakheda | K15: Mid-tier
A16: Tier C | B16: Red Rose School | C16: Sejal Ponda | E16: +91-755-2560033 | H16: redroseschool@gmail.com | I16: — | J16: TT Nagar | K16: Local reach
A17: Tier C | B17: Vindhyachal Academy | C17: Not Found | E17: Not Found | H17: vindhyachalacademykolar@gmail.com | I17: Not Found | J17: Not Found | K17: Not Found
A18: Tier C | B18: The First Step School | C18: Not Found | E18: Not Found | H18: firststep@gmail.com | I18: Not Found | J18: Lalghati | K18: Not Found
A19: Tier C | B19: Vindhyachal Academy | C19: Not Found | E19: Not Found | H19: milestonepublicschool@yahoo.co.in | I19: Not Found | J19: Kolar Road | K19: Not Found
A20: Tier C | B20: Arera Convent School and Residential School | C20: Not Found | E20: Not Found | H20: areraconventbhopal@gmail.com | I20: Not Found | J20: Kolar Road | K20: Not Found
A21: Tier C | B21: IES Public School | C21: Not Found | E21: Not Found | H21: contact@iespublicschool.ac.in | I21: Not Found | J21: Neelbad | K21: Not Found
A22: Tier C | B22: Rising Scholars Play Group and Nursery School | C22: Not Found | E22: Not Found | H22: risingscholarsbhopal@gmail.com | I22: Not Found | J22: Gandhinagar | K22: Not Found
A23: Tier C | B23: Bloomig Buds Foundations School & Day Care | C23: Not Found | E23: Not Found | H23: Not Found | I23: Not Found | J23: Arera Colony | K23: Not Found
A24: Tier C | B24: Bunny Tots International Preschool | C24: Not Found | E24: Not Found | H24: info@bunnytotsindia.com | I24: Not Found | J24: Katara Hills | K24: Not Found
... A66: Tier C | B66: St. Theresa's School | C66: Not Found | E66: Not Found | H66: Not Found | I66: Not Found | J66: Not Found | K66: Not Found

Sheet influential_data_for _corporate
A1: Name | B1: Status | C1: linkedin | D1: prospect_company_name | E1: company website | F1: linkedin | G1: Email | H1: mobile phone
A2: Ujwal Kumar | B2: Not Contacted | C2: linkedin.com/in/ACoAAAdGMZsBVa_ZxjzuRnsaZZG1yQY0jeo-tL4 | D2: Zomato | E2: zomato.com | F2: linkedin.com/company/zomato
A3: Abhimanyu Goyal | B3: Contacted | C3: linkedin.com/in/ACoAACcL4ysBxztc1XDYyDzZKieXn66hIH-Bx84 | D3: Zomato | E3: zomato.com | F3: linkedin.com/company/zomato | G3: abhimanyu.goyal@zomato.com
A4: Dushyant Chaturvedi | B4: Contacted | C4: linkedin.com/in/ACoAAAnqTjMBVls-pr0iMPV0pdcMwMxMKb-G85c | D4: Internshala | E4: internshala.com | F4: linkedin.com/company/internshala | G4: dushyant.chaturvedi@internshala.com
A5: Seetesh Srivastava | B5: Not Contacted | C5: linkedin.com/in/ACoAAAKGUaAB2gcDBsF6wutpfzsqg57BQ0KtKWQ | D5: Blinkit | E5: blinkit.com | F5: linkedin.com/company/letsblinkit
A6: Rishabh Pandey | B6: Not Contacted | C6: linkedin.com/in/ACoAAAGtJgYBzg2y-xJdFVmcSEWHIUJufv-gAYY | D6: Blinkit | E6: blinkit.com | F6: linkedin.com/company/letsblinkit | H6: 919953894326
A7: Nikita Patankar | B7: Contacted | C7: linkedin.com/in/ACoAABkg3BMB3XX3HcheH3KnhuTcnoBCCQp_LX0 | D7: Nobroker | E7: nobroker.in | F7: linkedin.com/company/nobroker-in | G7: nikita.patankar@nobroker.in
A8: Samir Mohammed | B8: Contacted | C8: linkedin.com/in/ACoAAC4vLwMBkqcxQ9uGx-QoOoyG_nfu9UFJGiE | D8: Nobroker | E8: nobroker.in | F8: linkedin.com/company/nobroker-in | G8: samir.mohammed@nobroker.in | H8: 971 50 125 7753
A9: Kayshel Ophelia Fernandes | B9: Contacted | C9: linkedin.com/in/ACoAAAuddjABEIHn3elPpO5RwhKvT2vYx67Z_yQ | D9: Practo | E9: practo.com | F9: linkedin.com/company/practo-technologies-pvt-ltd | H9: 919987386811
A10: Bhargav Yellapragada | B10: Contacted | C10: linkedin.com/in/ACoAAAfhhOEBhP4u4GondMFdJR0IY3fIGVnYOoU | D10: Zomato | E10: zomato.com | F10: linkedin.com/company/zomato ,bhargavtinku@gmail.com | G10: bhargav.yellapragada@zomato.com | H10: 91 99664 46197
A11: Shoumyan Biswas | B11: Contacted | C11: linkedin.com/in/ACoAAAePDp0BIhqdmPD_PeQYYCZa_sbDlyzNKkE | D11: Practo | E11: practo.com | F11: linkedin.com/company/practo-technologies-pvt-ltd | G11: shoumyan.biswas@practo.com
A12: Saurav Goyal | B12: Not Contacted | C12: linkedin.com/in/ACoAAAGpukwBQfzAD4Mrksj5WYI4Kls0OH6IIiE | D12: Swiggy | E12: careers.swiggy.com | F12: linkedin.com/company/swiggy-in | G12: saurav.goyal@swiggy.in
A13: Jay B. | B13: Not Contacted | C13: linkedin.com/in/ACoAABg4CcEBBzX92mLXqN8Ho_VQaqR0bhjWtG4 | D13: Practo | E13: practo.com | F13: linkedin.com/company/practo-technologies-pvt-ltd
A14: Shilpi Srivastav | B14: Contacted | C14: linkedin.com/in/ACoAAAvrkjcB0sYhlZe-rl-XALdGGWJ5SUd08jk | D14: Swiggy | E14: careers.swiggy.com | F14: linkedin.com/company/swiggy-in | G14: shilpi.srivastav@swiggy.in
A15: Firoz Alam | B15: Contacted | C15: linkedin.com/in/ACoAAASWdMABVr49X_K-5pmD1TfDGnryY9cAvBQ | D15: Blinkit | E15: blinkit.com | F15: linkedin.com/company/letsblinkit | G15: firozalam@blinkit.com
A16: Shikhar Baveja | B16: Not Contacted | C16: linkedin.com/in/ACoAAA6BZPEBJs3oTWp8tl9cBvGNYhah9ayVhH0 | D16: Swiggy | E16: careers.swiggy.com | F16: linkedin.com/company/swiggy-in | G16: shikhar.baveja@swiggy.in
A17: Romeo Ghosh | B17: Contacted | C17: linkedin.com/in/ACoAABtfdPUBlEWxTuCdpAfhZpBzjKsCIkibhjA | D17: Nobroker | E17: nobroker.in | F17: linkedin.com/company/nobroker-in | G17: romeo.ghosh@nobroker.in | H17: 918376061525
A18: Kopal Seth | B18: Contacted | C18: linkedin.com/in/ACoAAB9zp4IBoTVDi-sQWxmsQ2zk_Y5ebNXKwqk | D18: Internshala | E18: internshala.com | F18: linkedin.com/company/internshala | G18: kopal@internshala.com
A19: Abuzar Jamal | B19: Contacted | C19: linkedin.com/in/ACoAABy7XtYBHgA5V1kKvWMTzdBMHupJsqD7rjM | D19: Collegedunia | E19: collegedunia.com | F19: linkedin.com/school/collegedunia | G19: abuzar.jamal@collegedunia.com
A20: Pratyush (pratyush Nishantkar) N. | B20: Contacted | C20: linkedin.com/in/ACoAABH-xyMBi7swKOpC2Ofo7cJxcdUC5024Im8 | D20: Collegedunia | E20: collegedunia.com | F20: linkedin.com/school/collegedunia | G20: pratyush.nishantkar@collegedunia.com
A21: Suhas Mishra | B21: Contacted | C21: linkedin.com/in/ACoAAALgKlQBSWSrDYpPs9_tq67jTOqoGRsMe7k | D21: Housing | E21: housing.com | F21: linkedin.com/company/housing-com | G21: suhas.mishra@housing.com
A22: Prakash Singhal | B22: Contacted | C22: linkedin.com/in/ACoAAAJ8MvoBa1hloZzn3EQNqzhpHkMKoUm1Rbw | D22: Housing | E22: housing.com | F22: linkedin.com/company/housing-com | G22: prakash.singhal@housing.com | H22: 918882211110
A23: Shruti Garg | B23: Contacted | C23: linkedin.com/in/ACoAAAL3gLcBTOAFv3hPitlSN7Cfc9Eo7DLH8VY | D23: Housing | E23: housing.com | F23: linkedin.com/company/housing-com | G23: shruti.garg@housing.com
A24: Kenneth Saldanha | B24: Contacted | C24: linkedin.com/in/ACoAAA-bMaQBVMD-qix9dFtM6jjRwPi2-ux_e0M | D24: Mygate | E24: mygate.com | F24: linkedin.com/company/mygatecom | G24: kenneth.saldanha@mygate.com
A25: Praful Bele | B25: Contacted | C25: linkedin.com/in/ACoAACP9cSsBxG3-Wlh5EwQyoIyMqIEpRcInPWw | D25: Collegedunia | E25: collegedunia.com | F25: linkedin.com/school/collegedunia | G25: praful.bele@collegedunia.com | H25: 918779320849

Sheet To do
A1: Title,Status,Description,Assigned To,Priority,Due Date,Start Date,Date Created,Created By,Tags,dateFormat | B1: Status | C1: Description | D1: Assigned To | E1: Priority | F1: Due Date | G1: Start Date | H1: Date Created | I1: Created By | J1: Tags | K1: dateFormat
B2: open | C2: provide safe equipment | D2: abby@zylker.com | E2: Medium | F2: 44376 | G2: 44368 | H2: 44366 | I2: rebecca@zylker.com | J2: HR;New hires | K2: dd/MM/yyyy
A3: Contact Doctor Associations,open,Outreach to doctor associations,,Medium,,,,,Partnerships,dd/MM/yyyy | B3: closed | C3: arrange assembly sheds | D3: bpearson@zylker.com | E3: Medium | F3: 44384 | G3: 44379 | H3: 44378 | I3: rebecca@zylker.com | J3: HR | K3: dd/MM/yyyy
A4: Contact Business Associations,open,Outreach to business associations,,Medium,,,,,Partnerships,dd/MM/yyyy | B4: open | C4: purchase and arrange pavement blocks | D4: abby@zylker.com | E4: Medium | F4: 44356 | G4: 44350 | H4: 44348 | I4: rebecca@zylker.com | J4: HR;Important | K4: dd/MM/yyyy
A5: Contact CA Associations,open,Outreach to CA associations,,Medium,,,,,Partnerships,dd/MM/yyyy | B5: closed | C5: contact people to clear sewage | D5: aaron.brown@zylker.com | E5: Medium | F5: 44369 | G5: 44366 | H5: 44365 | I5: rebecca@zylker.com | J5: HR | K5: dd/MM/yyyy
A6: Identify Business Owners >2Cr,open,Find and reach high value business owners,,High,,,,,Partnerships,dd/MM/yyyy | B6: open | C6: perform an analysis of budget | D6: bpearson@zylker.com | E6: Medium | F6: 44040 | G6: 44038 | H6: 44401 | I6: rebecca@zylker.com | J6: HR | K6: dd/MM/yyyy
B7: open | C7: review company documents | D7: ken.m@zylker.com | E7: High | F7: 44039 | G7: 44036 | H7: 44035 | I7: rebecca@zylker.com | J7: HR;Review | K7: dd/MM/yyyy
A8: Reach out Practo,open,Platform partnership outreach,,High,,,,,Platform,dd/MM/yyyy
A9: Reach out Blinkit,open,Platform partnership outreach,,High,,,,,Platform,dd/MM/yyyy
A10: Reach out Zomato,open,Platform partnership outreach,,High,,,,,Platform,dd/MM/yyyy
A11: Reach out Swiggy,open,Platform partnership outreach,,High,,,,,Platform,dd/MM/yyyy
A12: Reach out MyGate,open,Platform partnership outreach,,Medium,,,,,Platform,dd/MM/yyyy
A13: Explore National Platforms,open,Find expansion platforms,,Low,,,,,Platform,dd/MM/yyyy
A14: Explore Event Platforms,open,Find event-based growth channels,,Low,,,,,Platform,dd/MM/yyyy
A15: Restaurant Partnerships,open,Tie up with restaurants,,Medium,,,,,Platform,dd/MM/yyyy
A17: School Outreach Plan,open,Plan school outreach strategy,,High,,,,,School,dd/MM/yyyy
A18: Define Target Schools,open,Identify top schools,,Medium,,,,,School,dd/MM/yyyy
A19: Identify Decision Makers,open,Find principals and admins,,Medium,,,,,School,dd/MM/yyyy
A20: Prepare Contact List,open,Build school database,,Medium,,,,,School,dd/MM/yyyy
... A43: Free Investing Sessions,open,General sessions,,Medium,,,,,Campaign,dd/MM/yyyy

Sheet FNOMO_MASTER_PIPELINE
A1: FNOMO MASTER PIPELINE - LIVE TODO MODE
A2: Lead entries rebuilt from the To do tab only. Each row has a same-day next action and a 2d / 4d / 7d follow-up clock.
A4: Lead_ID | B4: Name | C4: Company | D4: Type (CA / Business / Association) | E4: Tier (A/B/C) | F4: Stage (New / Contacted / Engaged / Qualified / Converted / Lost) | G4: Last_Contact_Date | H4: Next_Action | I4: Next_Action_Date | J4: Status (Active / Waiting / No Response / Closed) | K4: Notes (free text)
A5: TDL-006 | B5: Firoz Alam | C5: Blinkit | D5: Association | E5: A | F5: Contacted | G5: 2026-05-02 | H5: Follow-up 1 for platform partnership outreach if no reply | I5: 2026-05-04 | J5: Active | K5: Channel: firozalam@blinkit.com | Contact: Firoz Alam | Operations head | Seetesh Srivastava Igbc Ap®, Mrics | Director of administration & operations support; Rishabh P. | Director operations | Source: Reach out Blinkit | Decision_Gap: The target already influences a decision moment, but nobody is positioning validation before action. | Email: firozalam@blinkit.com | To do note: Platform partnership outreach | [2026-05-02] Zoho sent: Where high-frequency decisions lack validation | firozalam@blinkit.com | status=success | Source: platform partnership outreach table | SheetStatus: Contacted | LinkedIn: linkedin.com/in/ACoAAASWdMABVr49X_K-5pmD1TfDGnryY9cAvBQ | Company LinkedIn: linkedin.com/company/letsblinkit | Website: blinkit.com | Email: firozalam@blinkit.com | Mobile: missing | [2026-05-02] Platform partnership source row refreshed
A6: TDL-004 | C6: Business Owners >2Cr | D6: Business | E6: A | F6: New | H6: Tier A first: log/follow up already-contacted owner routes, then execute the next direct industrial batch in this order: Tesla/Jaideep, Righill/Vinod, Kumaran/Anil-to-K.M., Kakda call-first, Parvati/GEI/C.J. Do not promote Tier B retail/industry rows until these touches are recorded. | I6: 2026-05-03 | J6: Active | K6: Channel: Owner email + public business phone; call only after first email touch. | Contact: Tier A verified/promoted: Nahar, Deep, Perfect World, Tirupati, Sapna, Yantra, B.K. Bhatia, S.K./Saurabh Gulati, J.B. Sangwan, Yateesh Kumar, Vikas Prakash, K.G./Nitin/Aparna Bansal, Kishore Gupta, Vijay Bora, Dr. R.S. Goswami, Jaideep Jain, Vinod Sapre/Righill, K.M. Kumar/Kumaran, N.K./Neeraj Goel/Kakda, Poonam Chouksey/Parvati, C.E. Fernandes/GEI, Jaspal Singh/C.J. Gelatine. | Source: Identify Business Owners >2Cr | Decision_Gap: Owner-led businesses commit money to stock, capex, vendor, expansion, and personal investment decisions before anyone stress-tests the thinking behind the move. | Tier A discipline: send named owner/MD/CEO/founder routes first; call only after email touch except Kakda where call-first is cleaner because public email confidence is mixed. Do not promote queued Tier B rows until first-wave owner sends are logged or scale is verified. | [2026-05-02 overnight] Strengthened official/public routes for Parvati, GEI, C.J. Gelatine, Autosign, and Farmila. Owner send order stays: logged Tier A first, then Parvati/GEI/C.J.; Autosign/Farmila remain phone-verify queues. | [2026-05-02 evening] Kakda route tightened: public phone +91-755-4261284 and contact N.K./Narendra K. Goel verified; Brickwork shows Rs 13.40Cr bank facility, 150 tpd TMT capacity, and FY19 operating income Rs 110.61Cr. Written email remains unverified; call first, then ask for correct owner email. | [2026-05-02 night] Priority refresh: Tesla has direct Jaideep/official regional routes and IEEMA Rs 170.92Cr turnover signal; Kakda has GIA email/Neeraj mobile plus Brickwork Rs 110.61Cr FY19 income but should remain call-first; Kumaran/Righill have public direct contact paths. Owner outreach must ask what recent capital, procurement, stock, or customer-credit decision looked right before validation was missing.
A7: TDL-003 | C7: CA Associations | D7: CA | E7: A | F7: Contacted | G7: 2026-05-02 | H7: Tier A CA order: log Bhopal chair/secretary follow-up, send current Indore chairman Samkit Bhandari route, then use Govind/CIRC only if branch ownership stalls. Do not blast all regional council routes together. | I7: 2026-05-03 | J7: Active | K7: Channel: Direct public email + mobile from CIRC/ICAI office-bearer PDFs and current CIRC regional/central council page. | Contact: First wave: Arpit Rai, Abhishek Jain, Rajat Dhanuka, Milind Wadhwani. Bhopal escalation: CA Abhay Chhajed, Central Council Member, 9009044477, chhajed_abhay@hotmail.com. Indore/CIRC support: CA Anand Jain, 8818800095, anandjain812@gmail.com; CA Pankaj Shah, 9691893040, pankajgshah@gmail.com. Regional routing: CA Govind Agarwal/CIRC. | Source: Contact CA Associations | Decision_Gap: CA leaders repeatedly see clients act after gathering information, but the missing layer is validation of judgment before capital is committed. | Trust gateway order remains strict: city office bearers first, regional/Central Council escalation only after first-wave logging. | [2026-05-02 overnight] Added current CIRC regional/central public routes as controlled escalation rows; do not bypass chair/secretary touches unless ownership stalls. | [2026-05-02 evening] CA routing refreshed from CIRC live branch-contact table and 2026-27 ex-officio PDF: Bhopal current branch route CA Samank Mohabe 8109351314 / camohabesamank@gmail.com; Indore current branch route CA Mausam Rathi 9584604565 / camausamrathi@gmail.com; Bhopal ex-officio Abhay Chhajed and Indore support Anand Jain/Pankaj Shah remain escalation only. | [2026-05-02 night] Source refresh: CIRC Bhopal 2025-26 PDF confirms Arpit Rai 9406541241/arpit.rai07@gmail.com and Abhishek Jain 8109583831/caabhishek108@gmail.com; CIRC Indore 2025-26 PDF confirms Rajat, Samkit, Milind; ICAI Indore present committee now shows Samkit Bhandari as Chairman with samkit.fca@gmail.com / 9009770770. Decision-gap note: ask which client-money decisions members see fail despite information and confidence.
A8: TDL-005 | B8: Shoumyan Biswas | C8: Practo | D8: Association | E8: A | F8: Contacted | G8: 2026-05-02 | H8: Follow-up 1 for platform partnership outreach if no reply | I8: 2026-05-04 | J8: Active | K8: Channel: shoumyan.biswas@practo.com | Contact: Shoumyan Biswas | Global chief marketing and strategy officer | Kayshel Ophelia Fernandes | Associate director - communications & public relations; Jay B. | Manager - strategy & operations, ceo's office | Source: Reach out Practo | Decision_Gap: The target already influences a decision moment, but nobody is positioning validation before action. | Email: shoumyan.biswas@practo.com | To do note: Platform partnership outreach | [2026-05-02] Zoho sent: Where user trust doesn’t convert fully | shoumyan.biswas@practo.com | status=success | Source: platform partnership outreach table | SheetStatus: Contacted | LinkedIn: linkedin.com/in/ACoAAAePDp0BIhqdmPD_PeQYYCZa_sbDlyzNKkE | Company LinkedIn: linkedin.com/company/practo-technologies-pvt-ltd | Website: practo.com | Email: shoumyan.biswas@practo.com | Mobile: missing | [2026-05-02] Platform partnership source row refreshed
A9: TDL-008 | B9: Saurav Goyal | C9: Swiggy | D9: Association | E9: A | F9: Contacted | G9: 2026-05-02 | H9: Follow-up 1 for platform partnership outreach if no reply | I9: 2026-05-04 | J9: Active | K9: Channel: saurav.goyal@swiggy.in | Contact: Saurav Goyal | Senior vice president - driver and delivery product & operations | Shilpi Srivastav | Brand & revenue head - noice; Shikhar Baveja | Director - planning and sales operations | Source: Reach out Swiggy | Decision_Gap: The target already influences a decision moment, but nobody is positioning validation before action. | Email: saurav.goyal@swiggy.in | To do note: Platform partnership outreach | [2026-05-02] Zoho draft created: Where user decisions still outrun validation | saurav.goyal@swiggy.in | [2026-05-02] Email sent via Zoho | to=saurav.goyal@swiggy.in | message_id=1777722586505013400 | Source: platform partnership outreach table | SheetStatus: Not Contacted | LinkedIn: linkedin.com/in/ACoAAAGpukwBQfzAD4Mrksj5WYI4Kls0OH6IIiE | Company LinkedIn: linkedin.com/company/swiggy-in | Website: careers.swiggy.com | Email: saurav.goyal@swiggy.in | Mobile: missing | [2026-05-02] Platform partnership source row refreshed
A10: TDL-007 | B10: Abhimanyu Goyal | C10: Zomato | D10: Association | E10: A | F10: Contacted | G10: 2026-05-02 | H10: Follow-up 1 for platform partnership outreach if no reply | I10: 2026-05-04 | J10: Active | K10: Channel: abhimanyu.goyal@zomato.com | Contact: Abhimanyu Goyal | Cluster logs leader / chief operating officer | Ujwal Kumar | Director supply chain operations; Bhargav Yellapragada | Chief operating officer | Source: Reach out Zomato | Decision_Gap: The target already influences a decision moment, but nobody is positioning validation before action. | Email: abhimanyu.goyal@zomato.com | To do note: Platform partnership outreach | [2026-05-02] Zoho sent: Where high-intent users still don’t validate decisions | abhimanyu.goyal@zomato.com | status=success | Source: platform partnership outreach table | SheetStatus: Contacted | LinkedIn: linkedin.com/in/ACoAACcL4ysBxztc1XDYyDzZKieXn66hIH-Bx84 | Company LinkedIn: linkedin.com/company/zomato | Website: zomato.com | Email: abhimanyu.goyal@zomato.com | Mobile: missing | [2026-05-02] Platform partnership source row refreshed
A11: TDL-002 | C11: Business Associations | D11: Association | E11: B | F11: New | H11: Shortlist trade bodies with owner-heavy membership and map who can approve a pilot conversation. | I11: 2026-05-02 | J11: Waiting | K11: Channel: Email + LinkedIn research | Contact: Association president / secretary | Source: Contact Business Associations | Decision_Gap: Business groups discuss growth and expansion, but not the hidden cost of acting on confidence without validation. | Tier B partnership group. | To do note: Outreach to business associations
A12: TDL-011 | C12: Data Providers | D12: Association | E12: B | F12: New | H12: Identify data sources that can enrich platform and institutional contact discovery immediately. | I12: 2026-05-02 | J12: Waiting | K12: Channel: Email | Contact: Business development lead | Source: Talk to Data Providers | Decision_Gap: Lead quality bottlenecks are operational, not awareness-led, because decision-maker data is still thin. | External target but lower urgency. | To do note: Direct outreach to data providers
A13: TDL-001 | C13: Doctor Associations | D13: Association | E13: B | F13: New | H13: Identify the most active doctor associations in MP and open with a member-value angle, not a generic workshop pitch. | I13: 2026-05-02 | J13: Waiting | K13: Channel: Email + WhatsApp research | Contact: Association office bearer | Source: Contact Doctor Associations | Decision_Gap: Doctors advise life and money decisions under trust, yet association communities rarely surface how poor financial judgment compounds over time. | Tier B until CA and platform outreach is moving. | To do note: Outreach to doctor associations
A14: TDL-009 | B14: Kenneth Saldanha | C14: Mygate | D14: Association | E14: B | F14: Contacted | G14: 2026-05-02 | H14: Follow-up 1 for platform partnership outreach if no reply | I14: 2026-05-04 | J14: Active | K14: Channel: kenneth.saldanha@mygate.com | Contact: Kenneth Saldanha | Director - marketing | Source: Reach out MyGate | Decision_Gap: The target already influences a decision moment, but nobody is positioning validation before action. | Email: kenneth.saldanha@mygate.com | To do note: Platform partnership outreach | [2026-05-02] Zoho sent: Where high-trust users still don’t validate decisions | kenneth.saldanha@mygate.com | status=success | Source: platform partnership outreach table | SheetStatus: Contacted | LinkedIn: linkedin.com/in/ACoAAA-bMaQBVMD-qix9dFtM6jjRwPi2-ux_e0M | Company LinkedIn: linkedin.com/company/mygatecom | Website: mygate.com | Email: kenneth.saldanha@mygate.com | Mobile: missing | [2026-05-02] Platform partnership source row refreshed
A15: TDL-010 | C15: Restaurant Partners | D15: Association | E15: B | F15: New | H15: Define the first five restaurant partner profiles and test QR or event-driven partnership angles. | I15: 2026-05-02 | J15: Waiting | K15: Channel: Phone + in-person outreach | Contact: Founder / partnerships lead | Source: Restaurant Partnerships | Decision_Gap: Restaurants sit at repeated spending decisions but are not being used as trust surfaces for better financial judgment. | Keep Tier B. | To do note: Tie up with restaurants
A69: SCR-CA-001 | B69: CA Samank Mohabe / Manoj Chakraborty | C69: Bhopal Branch of CIRC of ICAI | D69: CA | E69: A | F69: New | H69: Use Bhopal branch route only after Arpit/Abhishek follow-up is logged; call/email CA Samank Mohabe to identify who owns member programming for a decision-validation conversation. | I69: 2026-05-04 | J69: Active | K69: Channel: bhopal@icai.org | Branch phone 07554908462 | Contact: Manoj Chakraborty | Bhopal Branch staff contact | 9131475919 | Source: Contact CA Associations | Decision_Gap: Branch teams can route the problem quickly if the ask is about preventing poor client decisions before action, not running another awareness program. | Verified public CIRC Bhopal Office Bearer PDF 2025-2026; use only after Arpit/Abhishek direct touches or as CC route. | [2026-05-02 evening] Live CIRC branch-contact table lists Bhopal chairman CA Samank Mohabe, mobile 8109351314, email camohabesamank@gmail.com; branch emails bhopal@icai.org and icaibhopalbranch@gmail.com. Keep Manoj Chakraborty/staff route as operational backup.
A70: SCR-CA-002 | B70: Arpit Rai | C70: Bhopal Branch of CIRC of ICAI | D70: CA | E70: A | F70: Contacted | G70: 2026-05-02 | H70: Follow-up Arpit as Bhopal 2025-26 chairman; ask who should own a member conversation on clients acting before validation. | I70: 2026-05-03 | J70: Active | K70: Channel: arpit.rai07@gmail.com | Contact: CA Arpit Rai | Chairman, Bhopal Branch of CIRC of ICAI | Mobile 9406541241 | Office 0755 4902128 | Source: Contact CA Associations | Decision_Gap: Chairman can legitimize Fnomo if the gap is framed as pre-action judgment validation for clients, not financial literacy. | Verified public CIRC Bhopal Office Bearer PDF 2025-2026. | [2026-05-02] Zoho draft created: A practical member-value gap CA branches can own | arpit.rai07@gmail.com | [2026-05-02] Email sent via Zoho | to=arpit.rai07@gmail.com | message_id=1777722602106010900 | [2026-05-02 night] CIRC Bhopal 2025-26 PDF verifies CA Arpit Rai, Chairman, 9406541241, arpit.rai07@gmail.com, office 0755-4902128.
A71: SCR-CA-003 | B71: Abhishek Jain | C71: Bhopal Branch of CIRC of ICAI | D71: CA | E71: A | F71: Contacted | G71: 2026-05-02 | H71: Follow-up Abhishek as Bhopal secretary route; ask for the branch programming owner if chair route is slow. | I71: 2026-05-03 | J71: Active | K71: Channel: caabhishek108@gmail.com | Contact: CA Abhishek Jain | Secretary, Bhopal Branch of CIRC of ICAI | Mobile 8109583831 | Office 0755 4938831 | Source: Contact CA Associations | Decision_Gap: Secretary is the fastest path to branch activation if the conversation is concrete and member-useful. | Verified public CIRC Bhopal Office Bearer PDF 2025-2026. | [2026-05-02] Zoho draft created: A member-useful conversation, not another awareness session | caabhishek108@gmail.com | [2026-05-02] Email sent via Zoho | to=caabhishek108@gmail.com | message_id=1777722598296002100 | [2026-05-02 night] CIRC Bhopal 2025-26 PDF verifies CA Abhishek Jain, Secretary, 8109583831, caabhishek108@gmail.com, office 0755-4938831.
A72: SCR-CA-004 | B72: CA Mausam Rathi / Indore Branch Office | C72: Indore Branch of CIRC of ICAI | D72: CA | E72: A | F72: New | H72: Use Indore branch route after Rajat/Milind/Samkit routing is reconciled; call/email CA Mausam Rathi or branch office to confirm current member-program owner before escalating to CIRC. | I72: 2026-05-04 | J72: Active | K72: Channel: indore@icai.in | Branch phones 0731-4298198, 2570052-53 | Contact: Suresh Tiwari | Indore Branch staff contact | 9303813511 | Source: Contact CA Associations | Decision_Gap: Large branch distribution matters only if the first message makes the validation gap obvious before a program is proposed. | Verified public CIRC Indore Office Bearer PDF 2025-2026. | [2026-05-02 evening] Live CIRC branch-contact table lists Indore chairman route CA Mausam Rathi, mobile 9584604565, email camausamrathi@gmail.com; branch emails indore@icai.in and indore@icai.org. Indore official site lists office 0731-4298198 and member query desk via Miss Soniya Dubey.
A73: SCR-CA-005 | B73: Rajat Dhanuka | C73: Indore Branch of CIRC of ICAI | D73: CA | E73: A | F73: Contacted | G73: 2026-05-02 | H73: Use Rajat only as prior Indore chairman context; current chairman route is Samkit, so ask Rajat for warm ownership routing rather than approval. | I73: 2026-05-03 | J73: Active | K73: Channel: DHANUKA_RAJ17@YAHOO.CO.IN | Contact: CA Rajat Dhanuka | Chairman, Indore Branch of CIRC of ICAI | Mobile 9425911336 | Office 8817593392 | Source: Contact CA Associations | Decision_Gap: Chair-level buy-in depends on seeing Fnomo as a preventive decision-quality layer for members and their clients. | Verified public CIRC Indore Office Bearer PDF 2025-2026. | [2026-05-02] Zoho draft created: A practical member conversation for Indore | milind.wadhwani20@gmail.com | [2026-05-02] Email sent via Zoho | to=milind.wadhwani20@gmail.com | message_id=1777722594245010900 | [2026-05-02 evening] FPJ 2026-27 Indore election report lists CA Rajat Dhanuka as executive member, not current president/secretary; keep as warm routed contact, not primary authority. | [2026-05-02 night] CIRC Indore 2025-26 PDF verifies Rajat Dhanuka as chairman for that term: 9425911336, DHANUKA_RAJ17@YAHOO.CO.IN; current Indore site shows Samkit as chairman.
A74: SCR-CA-006 | B74: Vinod Patel | C74: Jabalpur Branch of CIRC of ICAI | D74: CA | E74: B | F74: New | H74: Add Jabalpur as the next CA branch after Bhopal and Indore, with branch and chairman contact paths ready; do not send before Tier A first-wave contacts are touched. | I74: 2026-05-03 | J74: Waiting | K74: Channel: jabalpur@icai.org | jabalpuricai@gmail.com | 9981230021 | Contact: Vinod Patel | Branch staff contact | Source: Contact CA Associations | Decision_Gap: Branch-led CA distribution can scale only if the first few city-level wins are converted into trust quickly. | Jabalpur branch official contact. | Hold until first-wave Tier A sends are completed or scale/role is verified.
A75: SCR-CA-007 | B75: Kailash Chandra Agrawal | C75: Jabalpur Branch of CIRC of ICAI | D75: CA | E75: B | F75: New | H75: Prepare chairman outreach for Jabalpur as a second-wave CA branch target once Bhopal/Indore moves; do not send before Tier A first-wave contacts are touched. | I75: 2026-05-03 | J75: Waiting | K75: Channel: kcaca@rediffmail.com; kcajbp@gmail.com | Contact: Chairman | Mobile 9425153619 | Source: Contact CA Associations | Decision_Gap: Local chairmen are useful second-wave distribution nodes after the first-city narrative is sharpened. | Jabalpur Branch office bearer 2025-2026. | Hold until first-wave Tier A sends are completed or scale/role is verified.
A76: SCR-BO-001 | B76: Sandeep Wadhwani | C76: Sandeep Wadhwani | D76: Business | E76: A | F76: Contacted | G76: 2026-05-02 | H76: Follow-up 1 if no reply | I76: 2026-05-04 | J76: Active | K76: Channel: sandeepwadhwani14@gmail.com | deep_buildurpc@yahoo.co.in | 0755 429 2404 | 098262 64454 | Contact: Sandeep Wadhwani | Owner | Deep Computer & Peripheral | Source: Identify Business Owners >2Cr | Decision_Gap: Computer retail owners make frequent stock, vendor, and customer-credit calls where confidence can outrun validation. | Cybo public listing verifies owner email, business email, and multiple phones; keep outreach to owner email + one call path to avoid noise. | [2026-05-02] Zoho draft created: A hidden cost in owner-led business decisions | sandeepwadhwani14@gmail.com | [2026-05-02] Email sent via Zoho | to=sandeepwadhwani14@gmail.com | message_id=1777722582694001200
A77: SCR-BO-002 | B77: Yogesh Yadav | C77: Yogesh Yadav | D77: Business | E77: A | F77: New | H77: Send Yogesh an owner-level email tied to high-ticket electronics and customer purchase confidence; follow with one phone call after email touch. | I77: 2026-05-02 | J77: Active | K77: Channel: pwcvpl@hotmail.com | 0755 407 8241 | 098267 31144 | Contact: Yogesh Yadav | Owner | Perfect World Computers | Source: Identify Business Owners >2Cr | Decision_Gap: Electronics owners see both their own inventory decisions and customer purchase decisions where validation before action is intuitive. | BharatiBiz public listing verifies owner, business email, phone, category, and address; do not dilute with older conflicting directory emails.
A78: SCR-BO-003 | B78: Sumit Lalwani | C78: Sumit Lalwani | D78: Business | E78: A | F78: Contacted | G78: 2026-05-02 | H78: Follow-up 1 if no reply | I78: 2026-05-04 | J78: Active | K78: Channel: sumitlalwani66@gmail.com | tirupatifoodsproducts@gmail.com | 08871328918 | 09713544361 | Contact: Sumit Lalwani | Owner / Director-proprietor | Tirupati Foods And Products | Source: Identify Business Owners >2Cr | Decision_Gap: FMCG/grocery operators repeat buying, stock, cash-cycle, and expansion decisions at speed without a formal validation step. | BharatiBiz verifies owner email and phones; Dial4Trade lists Mr. Sumit Lalwani as Director Proprietor with GST-verified profile. | [2026-05-02] Zoho draft created: Where fast operating decisions become expensive | sumitlalwani66@gmail.com | [2026-05-02] Email sent via Zoho | to=sumitlalwani66@gmail.com | message_id=1777722578986013400
A79: SCR-BO-004 | C79: Novelty Life Style | D79: Business | E79: B | F79: New | H79: Send retail-owner outreach focused on repeat purchase decisions and borrowed confidence before spending action; do not send before Tier A first-wave contacts are touched. | I79: 2026-05-03 | J79: Waiting | K79: Channel: noveltylifestyle@gmail.com | 09824539455 | Contact: Retail contact | Source: Identify Business Owners >2Cr | Decision_Gap: Fashion/lifestyle retail sits close to impulse and confidence-led decisions, making validation a relevant behavioural layer. | Bhopal lifestyle retail target. | Hold until first-wave Tier A sends are completed or scale/role is verified.
A80: SCR-BO-005 | C80: Malvika Exclusive | D80: Business | E80: B | F80: New | H80: Prepare outreach to premium retail leadership with a positioning around purchase confidence versus validated judgment; do not send before Tier A first-wave contacts are touched. | I80: 2026-05-03 | J80: Waiting | K80: Channel: info@malvika-exclusive.com | 0755-3148029 | Contact: Retail contact | Source: Identify Business Owners >2Cr | Decision_Gap: Premium retail buyers act from trust and identity, which makes decision validation commercially interesting. | Official contact page surfaced. | Hold until first-wave Tier A sends are completed or scale/role is verified.
A81: SCR-BO-006 | B81: Nitin Nahar | C81: Nahar Enterprise | D81: Business | E81: A | F81: Contacted | G81: 2026-05-02 | H81: Follow-up 1 if no reply | I81: 2026-05-04 | J81: Active | K81: Channel: ne@naharindia.com | +91-755-2551141 | 2551191 | 2550734 | 2550767 | Contact: Nitin Nahar | Proprietor | Nahar Enterprise | Source: Identify Business Owners >2Cr | Decision_Gap: Industrial suppliers make large vendor, inventory, credit, and expansion decisions that look operational but carry real capital risk when not validated. | Official Nahar site lists 37-year national supplier profile and public phones/email; TradeIndia lists proprietor Mr. Nitin Nahar. Promote to Tier A. | [2026-05-02] Zoho draft created: A pattern industrial suppliers see too late | ne@naharindia.com | [2026-05-02] Email sent via Zoho | to=ne@naharindia.com | message_id=1777722575054013400
A82: SCR-CA-008 | B82: Aditya P. Srivastava | C82: Bhopal Branch of CIRC of ICAI | D82: CA | E82: B | F82: New | H82: Use as Bhopal second contact after chairman/secretary; send only if first two do not reply within the first follow-up window; do not send before Tier A first-wave contacts are touched. | I82: 2026-05-03 | J82: Waiting | K82: Channel: aditya.adi.152@gmail.com | 9425607192 | 7552762593 | Contact: Vice Chairman | Bhopal Branch of CIRC of ICAI | Source: Contact CA Associations | Decision_Gap: Vice-chair influence is useful if the first contact validates member appetite but branch activation needs another internal sponsor. | Public Bhopal Branch office-bearer PDF 2025-2026; keep as support path, not first send. | Hold until first-wave Tier A sends are completed or scale/role is verified.
A83: SCR-CA-009 | B83: Milind Wadhwani | C83: Indore Branch of CIRC of ICAI | D83: CA | E83: A | F83: New | H83: Use Milind as Indore secretary/support route behind Samkit; ask who handles member programming and branch event decisions. | I83: 2026-05-03 | J83: Active | K83: Channel: milind.wadhwani20@gmail.com | Contact: CA Milind Wadhwani | Secretary, Indore Branch of CIRC of ICAI | Mobile 9826273333 | Office 9754229852 | Source: Contact CA Associations | Decision_Gap: Secretary can convert a concept into a branch calendar item when the ask is small, specific, and member-relevant. | Verified public CIRC Indore Office Bearer PDF 2025-2026; also has public tax-article footprint, useful for a decision-quality angle. | [2026-05-02 evening] FPJ 2026-27 Indore election report lists CA Milind Wadhwani as Vice President; use as support/escalation behind current president/branch routing. | [2026-05-02 night] CIRC Indore 2025-26 PDF verifies CA Milind Wadhwani, Secretary, 9826273333, milind.wadhwani20@gmail.com, office 9754229852.
A84: SCR-CA-010 | B84: Shashilata Tomar | C84: Gwalior Branch of CIRC of ICAI | D84: CA | E84: B | F84: New | H84: Queue branch-level outreach after Bhopal/Indore; ask who owns member programming around client decision quality; do not send before Tier A first-wave contacts are touched. | I84: 2026-05-03 | J84: Waiting | K84: Channel: GWALIOR@ICAI.ORG | 0751-4049902 | 7804919310 | Contact: Shashilata Tomar | Branch staff contact | Source: Contact CA Associations | Decision_Gap: Branch offices can distribute decision-validation thinking, but only after a local office bearer sees the member-value case. | Public Gwalior Branch office-bearer PDF 2025-2026. | Hold until first-wave Tier A sends are completed or scale/role is verified.
A85: SCR-CA-011 | B85: Mayur Garg | C85: Gwalior Branch of CIRC of ICAI | D85: CA | E85: B | F85: New | H85: Prepare chairman outreach for Gwalior as second-wave CA target once first branch response patterns are clear; do not send before Tier A first-wave contacts are touched. | I85: 2026-05-03 | J85: Waiting | K85: Channel: CA.MAYURGARG@GMAIL.COM | 9826214555 | Contact: Chairperson | Gwalior Branch of CIRC of ICAI | Source: Contact CA Associations | Decision_Gap: A branch chair will care only if the outreach shows how decision validation creates member relevance before client money is committed. | Public Gwalior Branch office-bearer PDF 2025-2026. | Hold until first-wave Tier A sends are completed or scale/role is verified.
A86: SCR-CA-012 | B86: Hasan Chobarawala | C86: Ujjain Branch of CIRC of ICAI | D86: CA | E86: B | F86: New | H86: Queue Ujjain branch outreach after first MP branch signal; ask for the right office bearer for member decision-quality programming; do not send before Tier A first-wave contacts are touched. | I86: 2026-05-03 | J86: Waiting | K86: Channel: ujjain@icai.org | 0734-2521719 | 9926652153 | Contact: Hasan Chobarawala | Branch staff contact | Source: Contact CA Associations | Decision_Gap: Smaller branches are useful only when the ask is clear: validate decisions before action, not run another awareness session. | Public Ujjain Branch office-bearer PDF 2025-2026. | Hold until first-wave Tier A sends are completed or scale/role is verified.
A87: SCR-CA-013 | B87: Akrit Jain | C87: Ujjain Branch of CIRC of ICAI | D87: CA | E87: B | F87: New | H87: Prepare chair-level Ujjain outreach as a second-wave branch contact after the Bhopal/Indore language is proven; do not send before Tier A first-wave contacts are touched. | I87: 2026-05-03 | J87: Waiting | K87: Channel: caakritjain@gmail.com | 8879055886 | Contact: Chairman | Ujjain Branch of CIRC of ICAI | Source: Contact CA Associations | Decision_Gap: Chair-level buy-in depends on making the hidden client-decision failure visible in the first two lines. | Public Ujjain Branch office-bearer PDF 2025-2026. | Hold until first-wave Tier A sends are completed or scale/role is verified.
A88: SCR-BO-007 | B88: Owner | C88: Gajanan Wakhale | D88: Business | E88: B | F88: New | H88: Send owner-level outreach only after Tier A electronics/FMCG owners are touched; validate business scale before moving to Tier A; do not send before Tier A first-wave contacts are touched. | I88: 2026-05-03 | J88: Waiting | K88: Channel: gajanan12772@gmail.com | 093008 15190 | Contact: Owner | Mahalaxmi Enterprises | Source: Identify Business Owners >2Cr | Decision_Gap: Local owners make stock, expansion, and cash decisions from pattern recognition; Fnomo should expose where confidence went unvalidated. | BharatiBiz public listing confirms owner, email, and phone; scale not verified, so hold as Tier B. | Hold until first-wave Tier A sends are completed or scale/role is verified.
A89: SCR-BO-008 | B89: Sanjay Varliyani | C89: Sanjay Varliyani | D89: Business | E89: A | F89: New | H89: Send Sanjay the high-ticket retail opener today; use the above-15Cr GST signal to keep this in the first owner batch, then call if no reply. | I89: 2026-05-02 | J89: Active | K89: Channel: svarliyani@gmail.com | 081092 45800 | 0755 429 2830 | Contact: Sanjay Varliyani | Owner | Sapna Electronics | Source: Identify Business Owners >2Cr | Decision_Gap: High-ticket electronics retail exposes the exact gap Fnomo names: people commit money from confidence before decision quality is validated. | BharatiBiz verifies owner email and phones; public CCOBZ Above15Cr list includes Sapna Electronics / Sanjay Kumar Varliyani, supporting Tier A scale.
A90: SCR-BO-009 | B90: Nitin Bhawsar | C90: Nitin Bhawsar | D90: Business | E90: A | F90: New | H90: Send Nitin the electronics-owner opener today; call public number to confirm owner route and ask about recent stock/customer decisions that proved costly. | I90: 2026-05-02 | J90: Active | K90: Channel: yantrainfotech@gmail.com | 0755 427 2287 | Contact: Nitin Bhawsar | Owner / Proprietor | Yantra Infotech | Source: Identify Business Owners >2Cr | Decision_Gap: Computer/electronics proprietors face buying and customer-advice decisions where bad validation shows up as inventory, cash, or reputation loss. | Piceapp GST record verifies legal name Nitin Bhawsar, active regular proprietorship, and MP Nagar address; BharatiBiz public listing provides email/phone.
A91: SCR-BO-010 | B91: Owner | C91: Pankaj Kukreja | D91: Business | E91: B | F91: New | H91: Hold as retail second wave; outreach should connect premium purchase confidence to validation before spending; do not send before Tier A first-wave contacts are touched. | I91: 2026-05-03 | J91: Waiting | K91: Channel: pankaj_kukreja0000@rediffmail.com | 098938 53138 | 0755 401 1190 | Contact: Owner | Madam Collection | Source: Identify Business Owners >2Cr | Decision_Gap: Premium retail decisions are driven by identity and confidence, which makes a validation-before-action conversation relevant if scale is real. | BharatiBiz public listing confirms owner, email, and phone; verify scale before Tier A. | Hold until first-wave Tier A sends are completed or scale/role is verified.
A92: SCR-BO-011 | B92: Owner | C92: Neha Rijhwani | D92: Business | E92: B | F92: New | H92: Hold as boutique-retail second wave; use only after higher-value owner contacts have been worked; do not send before Tier A first-wave contacts are touched. | I92: 2026-05-03 | J92: Waiting | K92: Channel: neharijhwani1@gmail.com | stylewithfitoor@gmail.com | 099939 00210 | Contact: Owner | Fitoor - Designer Store for Women | Source: Identify Business Owners >2Cr | Decision_Gap: Boutique retail decisions reveal how confidence, social proof, and money move together without a structured validation step. | BharatiBiz public listing confirms owner email and store contacts; scale not verified. | Hold until first-wave Tier A sends are completed or scale/role is verified.
A93: SCR-BO-012 | B93: Owner | C93: Sourabh Jain | D93: Business | E93: B | F93: New | H93: Use as second-wave owner outreach only after direct Tier A owner touches are completed; do not send before Tier A first-wave contacts are touched. | I93: 2026-05-03 | J93: Waiting | K93: Channel: sourabhskjain@gmail.com | 098932 44778 | 0755 274 0041 | Contact: Owner | Ecoline Products | Source: Identify Business Owners >2Cr | Decision_Gap: Trading/product owners make repeated procurement and cash-cycle decisions where unvalidated confidence can become expensive. | BharatiBiz public listing confirms owner, email, and phone; keep Tier B until scale is confirmed. | Hold until first-wave Tier A sends are completed or scale/role is verified.
... A127: SCR-CA-033 | B127: Dharmendra Jain | C127: Shivpuri CPE Study Chapter of CIRC of ICAI | D127: CA | E127: B | F127: New | H127: Queue after current branch/chapter sends. Use Dharmendra Jain as chapter contact and Ashish Goyal/Sanyam Jain as office-bearer routes only when first-wave CA sends are logged. | I127: 2026-05-03 | J127: Waiting | K127: Channel: JAIN.DHARMENDRA@ICAI.ORG | g2a_ca@rediffmail.com | casanyamjain@rediffmail.com | 9425430430 | 9993274175 | 7828461116 | Contact: Dharmendra Jain | Chapter contact; CA Ashish Goyal | Convenor; CA Sanyam Jain | Dy Convenor | Source: Contact CA Associations | Decision_Gap: Chapter-level CA outreach must prove practical member value by asking about the last client decision that looked informed but lacked validation before capital moved. | Official ICAI CPE POU page lists Shivpuri contact email/phone and 2025-2026 office bearers. Tier B expansion behind active Tier A CA route.
A128: SCR-CA-034 | B128: CIRC Central Regional Office | C128: CA Govind Agarwal | D128: CA | E128: A | F128: Contacted | G128: 2026-05-02 | H128: Follow-up 1 if no reply | I128: 2026-05-04 | J128: Active | K128: Channel: govind.agarwal@icai.in | circ@icai.in | member query phones 9305804344, 9305804347 | ICAI call center 99975 99975 | Contact: CA Govind Agarwal | Deputy Secretary; overall administrative in-charge of Central Regional Office and Office of CIRC | Source: Contact CA Associations | Decision_Gap: CIRC can validate whether client decision quality belongs in branch programming; the failure pattern is clients acting on enough information without an independent pre-action judgment check. | Official CIRC contact page lists CA Govind Agarwal as CRO/CIRC administrative in-charge and publishes obfuscated email. Use as routing/escalation, not as a substitute for local office-bearer trust. | [2026-05-02] Zoho draft created: Who should own this conversation at branch level? | govind.agarwal@icai.in | [2026-05-02] Email sent via Zoho | to=govind.agarwal@icai.in | message_id=1777722590263001200
A129: SCR-BO-027 | B129: Mrs. Lilly Benance | C129: Emjay Industries | D129: Business | E129: B | F129: New | H129: Queue after current Tier A owner sends. Send only once first-wave touches are logged; ask about the last traction-motor, hydro-generator, or control-gear production decision that looked right before assumptions changed. | I129: 2026-05-03 | J129: Waiting | K129: Channel: emjayindustries@yahoo.com | 0755-4262155 | 0755-2784079 | P Benance 9893096366 | Contact: Mrs. Lilly Benance; P Benance | Emjay Industries, Govindpura | Source: Identify Business Owners >2Cr | Decision_Gap: Industrial component owners make procurement, material, and delivery commitments where technical confidence can outrun decision validation. | GIA directory lists website/email/GST, named contacts, phones, and products: traction motor parts, hydro generator copper parts, control gear parts. Keep Tier B until scale or intent is confirmed.
A130: SCR-BO-028 | B130: Manish Daryani | C130: Engineering Associates | D130: Business | E130: B | F130: New | H130: Queue after Tier A industrial owners. Open with transformer and HT/LT line decisions where the downside appears only after procurement, credit, or installation commitments are made. | I130: 2026-05-03 | J130: Waiting | K130: Channel: engineerassociate@yahoo.com | 0755-2588071 | 0755-2602654 | 9826014525 | 8827392201 | Contact: Manish Daryani | Engineering Associates and Unit-II Transformer Unit, Govindpura | Source: Identify Business Owners >2Cr | Decision_Gap: Transformer and sub-station suppliers face high-consequence purchase, spec, vendor, and customer-risk calls that need validation before action. | GIA/product-wise directory lists named contact, email, phones, two units, and transformer/HT-LT/sub-station product focus. Verify scale before Tier A promotion.
A131: SCR-BO-029 | B131: Ashwani Bansal | C131: Enterprising Consulting Engineers | D131: Business | E131: B | F131: New | H131: Queue as named industrial second wave. Ask about the last electrical-panel or enclosure job where customer spec, pricing, or material assumptions needed validation before commitment. | I131: 2026-05-03 | J131: Waiting | K131: Channel: ecebhopal@hotmail.com | 0755-4252977 | Ashwani 9303131161 | Seema 9425008531 | Contact: Ashwani Bansal; Mrs. Seema Bansal | Enterprising Consulting Engineers, Govindpura | Source: Identify Business Owners >2Cr | Decision_Gap: Sheet-metal and electrical-panel work turns small judgment gaps into margin, rework, and delivery risk after the job is accepted. | GIA directory lists GST, named contacts, public email/phone, and electrical panels/enclosures/sheet-metal product focus. Keep behind current Tier A owner execution.
A132: SCR-BO-030 | B132: Shiji Chacko | C132: M G M Industries | D132: Business | E132: B | F132: New | H132: Queue after active Tier A owner list. Validate scale first, then use the precision-components angle: which customer/tooling decision recently looked routine but carried avoidable risk? | I132: 2026-05-03 | J132: Waiting | K132: Channel: mgm_industries@rediffmail.com | mgm3330@gmail.com | 0755-2683506 | 0755-4260139 | Shiji 9893045671 / 9893153330 | Contact: P. Chacko; Shiji Chacko | M G M Industries, Govindpura | Source: Identify Business Owners >2Cr | Decision_Gap: Precision-component and fabrication businesses repeat quote, tooling, delivery, and customer-risk decisions where better validation can prevent margin loss. | GIA directory lists emails, phones, named contacts, and jigs/fixtures/precision-components/fabrication focus; Justdial shows 31-year business, 26-50 employees, and 1-5 Cr turnover band. Tier B until >2Cr/intent is confirmed directly.
A133: SCR-BO-031 | B133: Kishore Gupta | C133: Star Delta Transformers Ltd | D133: Business | E133: A | F133: Contacted | G133: 2026-05-02 | H133: Follow-up 1 if no reply | I133: 2026-05-04 | J133: Active | K133: Channel: star.delta@rediffmail.com | sdtl.bhopal@gmail.com | info@stardeltatransformers.com | 0755-2586680 | 0755-2587343 | Kishore contact 9755005422 | Contact: Kishore Gupta | Chairman & Managing Director; Rakesh Gupta | Whole-time Director & CFO; Mayank Gupta | Executive Director | Star Delta Transformers Ltd, Govindpura | Source: Identify Business Owners >2Cr | Decision_Gap: Listed transformer manufacturers carry high-consequence procurement, production, customer-credit, and capex decisions where information exists but decision quality still needs an independent check. | Verified from public BSE/company-management and GIA product-wise records: listed/public company, Govindpura transformer manufacturer, FY gross sales public signal >2Cr. Tier A direct CMD/company route. | [2026-05-02] Zoho draft created: Where technical confidence still misses decision risk | star.delta@rediffmail.com | [2026-05-02] Email sent via Zoho | to=star.delta@rediffmail.com | message_id=1777722571164001200
A134: SCR-BO-032 | B134: Vijay Bora | C134: Bora Brothers Industries | D134: Business | E134: A | F134: New | H134: Send Vijay Bora an owner/CEO note after first-wave sends. Use power-plant fabrication, transformer-tank, and heavy sheet-metal decisions as the hook for validating judgment before accepting work or locking material. | I134: 2026-05-02 | J134: Active | K134: Channel: vijay_bora@hotmail.com | +91-755-2586112 | +91-755-2586378 | +91-9425300378 | Contact: Mr. Vijay Bora | CEO / Proprietor | Bora Brothers Industries, Govindpura | Source: Identify Business Owners >2Cr | Decision_Gap: Large fabrication owners can lose margin through decisions that seem operational at approval time: material, credit, spec, delivery, and customer-risk assumptions. | Verified public SME profile: 1971 establishment, 105,000 sq.ft. premises, 80-90 employees, GIA membership, direct CEO email/phone. Tier A industrial owner route.
A135: SCR-BO-033 | B135: Dr. R.S. Goswami | C135: Hind Pharma | D135: Business | E135: A | F135: New | H135: Send founder/CEO outreach after the current Tier A owner batch. Open on export, compliance, product, and distributor decisions where bad validation can be expensive even when data is available. | I135: 2026-05-02 | J135: Active | K135: Channel: contact@hindpharmaindia.com | sales@hindpharma.com | +91-9303696517 | +91-7566502003 | customer care +91-6262085050 | Contact: Dr. R.S. Goswami | Founder & CEO / Chairman | Hind Pharma, Govindpura | Source: Identify Business Owners >2Cr | Decision_Gap: Pharma founders make high-trust regulatory, export, formulation, distributor, and capacity decisions where confidence cannot substitute for pre-action validation. | Verified official Hind Pharma profile: founder/CEO, 1977 manufacturer, exports to 65+ countries, public contact emails/phones. Third-party profile supports 10-25 Cr turnover band; keep Tier A.
A136: SCR-BO-034 | B136: Jaideep Jain | C136: Tesla Transformers | D136: Business | E136: A | F136: New | H136: Send Jaideep/Tesla owner route after current logged owner follow-ups; if no reply, call official Bhopal/MP enquiry route and ask for capital-project decision owner. | I136: 2026-05-03 | J136: Active | K136: Channel: tesla@teslaindia.co | mktg@teslatransformers.com | sales@teslatransformersglobal.com | +91-755-4271974 | +91-755-2586778 | Jaideep route 9893055810 | Contact: Mr. Jaideep Jain | Chairman & Managing Director / promoter | Tesla Transformers group, Govindpura | Source: Identify Business Owners >2Cr | Decision_Gap: Transformer manufacturers face large project, spec, vendor, credit, and delivery decisions where the logic can look technically sound while commercial assumptions remain unvalidated. | Verified official Tesla Power/Tesla Transformers pages and GIA product-wise listing: Jaideep Jain leadership route, Govindpura transformer manufacturing, public emails/phones. Tier A because named promoter/CMD and industrial value are public. | [2026-05-02 night] Tesla refresh: official contact page lists tesla@teslaindia.co, jitendra@teslaindia.co, Jitendra Singh 9755557703, Vipin Singhai 7471128044, MP route Yasir Farooque 7024120460/yasir@teslaindia.co; CompanyDetails lists jaideep@teslaindia.co; IEEMA member directory lists Jaideep Jain as Director - M&P and turnover Rs 170.92Cr FY2021-22. Decision-gap angle: transformer-project, procurement, customer-spec, and regional expansion calls carry validation risk before capital is locked.
A137: SCR-CA-035 | B137: Vikas Golchha | C137: Raipur Branch of CIRC of ICAI | D137: CA | E137: B | F137: New | H137: Queue after Bhopal/Indore chair-secretary touches and the CIRC routing note. Send chairman/secretary version only if first-wave CA messages are logged or need a larger CIRC proof point. | I137: 2026-05-03 | J137: Waiting | K137: Channel: vikasgolchha2021@gmail.com | ca.ravigidiya@gmail.com | raipur@icai.org | Chairman 9827977252 / 8770493390 | Secretary 9584750020 | Branch 0771-4030937 | Contact: CA Vikas Golchha | Chairman; CA Ravi Jain | Secretary; Mrs Sonali Mishra | Branch staff | Raipur Branch of CIRC of ICAI | Source: Contact CA Associations | Decision_Gap: Raipur gives a larger branch test for whether CAs recognize the same client pattern: information and confidence existed, but the decision was never validated before money moved. | Verified public CIRC Raipur Office Bearer PDF 2025-2026. Keep Tier B until MP first-wave sends are completed; do not distract from Bhopal/Indore.
A138: SCR-CA-036 | B138: Vikas Yadav | C138: Jaipur Branch of CIRC of ICAI | D138: CA | E138: B | F138: New | H138: Queue as larger-branch expansion after first MP branch touches. Use chair/secretary route and ask who owns member programming for decision-quality/client-money behavior. | I138: 2026-05-03 | J138: Waiting | K138: Channel: cavikasyadav1995@gmail.com | cayash_gupta@hotmail.com | jaipur@icai.org | Chairman 9166332244 | Secretary 9602346888 / 7689922222 | Branch 0141-3044200 | Staff 9672023888 | Contact: CA Vikas Yadav | Chairman; CA Yash Gupta | Secretary; Vishal Gupta | Branch staff | Jaipur Branch of CIRC of ICAI | Source: Contact CA Associations | Decision_Gap: Jaipur is a scale branch; outreach should test whether the validation gap resonates beyond local MP branches without turning it into a generic finance session. | Verified public CIRC Jaipur Office Bearer PDF 2025-2026. Tier B expansion; only send after first-wave Tier A CA route is logged.
A139: SCR-BO-035 | B139: Vinod Sapre | C139: Righill Electrics Pvt. Ltd. | D139: Business | E139: A | F139: Contacted | G139: 2026-05-02 | H139: Follow-up Vinod Sapre/Righill if no reply; use direct phone after email and ask about the last rig-electrics/customer-spec decision that should have been validated earlier. | I139: 2026-05-03 | J139: Active | K139: Channel: righillelectrics@righill.com | 0755-2584202 | 0755-2584170 | Vinod 9826023148 | Ashutosh 9893033138 | Contact: Vinod Sapre | Director / GIA listed contact | Mobile 9826023148; Manu Sukul | Director; Ashutosh Shukla | GIA listed contact | Mobile 9893033138; Righill Electrics Pvt. Ltd. | Email righillelectrics@righill.com | Office 0755-2584202 / 0755-2584170 | Fax 0755-2586189 | Source: Identify Business Owners >2Cr | Decision_Gap: Righill has high-consequence industrial control, VFD, SCR, generator, and DC-drive decisions where the data can look technical while customer, vendor, and capacity assumptions remain unvalidated. | GIA product-wise directory verifies email, office phones, Vinod Sapre and Ashutosh Shukla mobile routes, member status, and industrial control products; CorporateDir/Zauba-style records verify Vinod Sapre and Manu Sukul as directors. Tier A owner route; avoid generic company pitch. | [2026-05-02] Zoho draft created: A recurring gap in industrial control decisions | righillelectrics@righill.com | [2026-05-02] Email sent via Zoho | to=righillelectrics@righill.com | message_id=1777722567435002100 | [2026-05-02 night] Righill refresh: official page verifies +91-755-2584170/2584202; GIA lists righillelectrics@righill.com, Vinod Sapre 9826023148, Ashutosh Shukla 9893033138, rig electrics/VFD/SCR systems profile.
A140: SCR-BO-036 | B140: Sameer Gangrade | C140: Sameer Engineering Industries | D140: Business | E140: B | F140: New | H140: Queue behind logged Tier A owner sends. First touch should validate scale through Sameer/office route, then ask which moulding, sheet-metal, or customer-order decision recently looked routine but carried margin risk. | I140: 2026-05-03 | J140: Waiting | K140: Channel: sameerenggind@rediffmail.com | 0755-4261182 | 0755-2581593 | Sameer 9425374610 | Contact: Sameer Gangrade | Sameer Engineering Industries, Govindpura | Emails sameerenggind@rediffmail.com; samcabls@gmail.com | Office 0755-4261182 / 0755-2581593 | Source: Identify Business Owners >2Cr | Decision_Gap: Moulded-items manufacturing creates repeat quote, tooling, material, and customer-commitment decisions where small assumption errors become margin loss. | GIA directory and official Sameer Engineering site verify public email/office phone routes and control-equipment/product focus. Keep Tier B until >2Cr scale or active intent is confirmed; no generic inbox blast.
A141: SCR-BO-037 | B141: Faiz Khan | C141: Evergreen Industries | D141: Business | E141: B | F141: New | H141: Queue after Tier A industrial sends. Use official-site proof of BHEL/government supply exposure, then ask about the last casting, machining, or transformer-component decision that needed validation before commitment. | I141: 2026-05-03 | J141: Waiting | K141: Channel: evergreenindustries1972@yahoo.com | 0755-4222846 | Mobile 8962535979 / 9826635880 | GIA: Mohd Zafar 0755-2761371 | Contact: Mohd Zafar; Faiz Khan | Evergreen Industries, Govindpura | Source: Identify Business Owners >2Cr | Decision_Gap: Casting and fabrication suppliers make material, client, quality, and delivery commitments where decision validation can protect margin and reputation. | Official Evergreen site verifies ISO 9001:2015, BHEL supplier code, government/semi-government customers, email, office, and mobile contacts. GIA verifies named contacts. Tier B until revenue scale is confirmed.
A142: SCR-BO-038 | B142: Habib Hussain | C142: Crown Industries | D142: Business | E142: B | F142: New | H142: Queue after active Tier A owner list. Call/email to validate owner route, then open on the last machining or fabrication job where price, material, or customer assumptions should have been stress-tested first. | I142: 2026-05-03 | J142: Waiting | K142: Channel: industriescrown@ymail.com | 0755-4045447 | 7773082777 | Habib 0755-4252092 / 9752777746 | Contact: Habib Hussain | Crown Industries, Govindpura | Source: Identify Business Owners >2Cr | Decision_Gap: Machining and fabrication businesses often accept jobs before validating customer-risk, material, and margin assumptions; Fnomo should surface that pre-commitment gap. | GIA directory verifies public email, phones, named contact, GSTN, member status, and machining/fabrication focus. Keep Tier B until scale is confirmed.
A143: SCR-BO-039 | B143: B.D. Sharma | C143: Dawn Engineers | D143: Business | E143: B | F143: New | H143: Queue after stronger Tier A owner sends. If contacted, ask about tractor-parts and automotive-component decisions where the cost of a wrong commitment appears only after production begins. | I143: 2026-05-03 | J143: Waiting | K143: Channel: dawnengineersbpl@yahoo.co.in | 0755-4274848 | B.D. 9872001990 | R.K. 9893039433 | Contact: B.D. Sharma; R.K. Sharma | Dawn Engineers, Govindpura | Source: Identify Business Owners >2Cr | Decision_Gap: Auto/tractor component manufacturers make production, inventory, customer, and quality decisions where validation before action can prevent avoidable rework and cash drag. | GIA directory verifies website, email, phone, named contacts, member status, and tractor-parts product focus; TradeIndia separately identifies Sharma as proprietor. Tier B until scale/intent is confirmed.
A144: SCR-BO-040 | B144: Sanjay Khanna | C144: S M Motors | D144: Business | E144: B | F144: New | H144: Queue as retail/automobile owner route after industrial Tier A contacts. Use service-center purchase and customer-trust decisions as the hook; verify scale before promotion. | I144: 2026-05-03 | J144: Waiting | K144: Channel: sanjay@smmotors.in | kavita@smmotors.in | Sanjay 9893690701 | Kavita 9893690700 | Contact: Sanjay Khanna; Kavita Khanna | S M Motors, Govindpura | Source: Identify Business Owners >2Cr | Decision_Gap: Automobile service owners sit near customer spend, repair, inventory, and vendor decisions where confidence can move faster than validation. | GIA directory verifies public emails and named owner contacts for S M Motors automobile workshop. Keep Tier B because scale is not yet verified.
A145: SCR-CA-037 | B145: Ankur Goyal | C145: CIRC Chairman | D145: CA | E145: B | F145: New | H145: Use only after Bhopal/Indore chair-secretary touches are logged or if CIRC-level escalation is needed. Ask whether regional programming should address client money decisions that were informed but never independently validated. | I145: 2026-05-03 | J145: Waiting | K145: Channel: ragsankur3@gmail.com | 9889233731 | Contact: CA Goyal Ankur | Chairman, CIRC | Mobile 9889233731 | Email ragsankur3@gmail.com | Lucknow office address public on CIRC regional council page | Source: Contact CA Associations | Decision_Gap: Regional chairman can legitimize the decision-validation frame across branches, but outreach should not bypass local trust unless first-wave branch routing stalls. | Official CIRC regional council page verifies chairman role, mobile, email, and office address. Keep behind Bhopal/Indore first-wave execution; do not bypass local trust unless routing stalls.
A146: SCR-CA-038 | B146: Ankush Jain | C146: CIRC Vice Chairman | D146: CA | E146: B | F146: New | H146: Hold as Indore-region escalation route after Rajat/Milind touches. Ask who owns branch/member programming for validating client decisions before capital is committed. | I146: 2026-05-03 | J146: Waiting | K146: Channel: caankush41@gmail.com | 8109471070 | Contact: CA Jain Ankush | Vice Chairman, CIRC | Indore | Mobile 8109471070 | Email caankush41@gmail.com | Source: Contact CA Associations | Decision_Gap: Vice-chair route is useful only when local branch contacts need a regional sponsor; the message must stay about decision quality, not education. | Official CIRC regional council page verifies vice-chairman role, Indore office address, mobile, and email. Use only as support route behind local branch leadership.
A147: SCR-CA-039 | B147: Nirbhik Gandhi | C147: CIRC Secretary | D147: CA | E147: B | F147: New | H147: Hold as regional secretary route if local branch ownership is unclear after first-wave sends. Ask for the right programming owner for a short decision-validation member conversation. | I147: 2026-05-03 | J147: Waiting | K147: Channel: canirbhik@gmail.com | 9785084747 | Contact: CA Gandhi Nirbhik | Secretary, CIRC | Mobile 9785084747 | Email canirbhik@gmail.com | Bhilwara office address public on CIRC regional council page | Source: Contact CA Associations | Decision_Gap: Regional secretary can route operational ownership, but should be approached only after local chair/secretary attempts are logged. | Official CIRC regional council page verifies secretary role, mobile, email, and office address. Best use is operational routing after local branch attempts are logged.
A148: SCR-BO-041 | B148: K.M. Kumar | C148: Kumaran Industries | D148: Business | E148: A | F148: Contacted | G148: 2026-05-02 | H148: Follow-up Kumaran route; use Anil Pandey/sales line to reach K.M. Kumar or the manufacturing decision owner before any broader owner batch. | I148: 2026-05-03 | J148: Active | K148: Channel: sales@kumaranindustries.com | hemakars@kumaranindustries.com | +91-755-4261969 | +91-9820091918 | GIA phones 0755-2587800 / 7898201171 / 7898201172 | K.M. Kumar 9425013103 | Contact: K.M. Kumar | GIA listed contact; Anil Pandey | public company-directory contact; Karthik Kumar | public CEO listing; Kumaran Industries / Kohmer | Emails sales@kumaranindustries.com; hemakars@kumaranindustries.com | Phones +91-755-4261969; +91-9820091918 | Source: Identify Business Owners >2Cr | Decision_Gap: Railway, heavy-machine, heat-exchanger, and industrial-blower commitments carry quote, spec, vendor, and delivery assumptions that can look technically sound while commercial risk remains unvalidated. | Official Kohmer/Kumaran contact page verifies emails, phones, and Govindpura address; company-directory listing adds Anil Pandey route and same phone/email; GIA confirms K.M. Kumar route. Tier A scale-supported industrial owner route. | [2026-05-02] Zoho draft created: Where industrial commitments look sound until they are not | sales@kumaranindustries.com | [2026-05-02] Email sent via Zoho | to=sales@kumaranindustries.com | message_id=1777722563323001200 | [2026-05-02 night] Kumaran refresh: public industry directory lists Anil Pandey contact, sales@kumaranindustries.com, 0755-4261969 / 9820091918, Govindpura address, traction transformer tanks/fans/heat exchangers manufacturing.
A149: SCR-BO-042 | B149: N.K. Goel | C149: Kakda Rolling Mills | D149: Business | E149: A | F149: New | H149: Call Neeraj/Narendra Goel route first, then ask for correct owner email; only send written outreach after route confirmation because Kakda scale is high but email confidence was previously mixed. | I149: 2026-05-03 | J149: Active | K149: Channel: +91-755-4261284 | website/email route listed publicly as kakdarollingmills.com; verify written email before sending | Contact: N.K. Goel / Neeraj Goel | Kakda Rolling Mills, Govindpura | Email kakdaindustries@gmail.com | Office 0755-4280911; alternate public listing phone +91-755-4261284; Neeraj Goel mobile 9826058625 | Source: Identify Business Owners >2Cr | Decision_Gap: Steel rolling owners make high-value raw-material, credit, capacity, and price-risk decisions where delayed validation can turn operating scale into cash pressure. | GIA product-wise directory verifies Kakda email, office phone, Neeraj Goel mobile, and TMT/alloy-steel focus; IndiaIndustry public listing separately identifies N.K. Goel and +91-755-4261284. Do not mention rating stress in outreach. | [2026-05-02 evening] Kakda route tightened: public phone +91-755-4261284 and contact N.K./Narendra K. Goel verified; Brickwork shows Rs 13.40Cr bank facility, 150 tpd TMT capacity, and FY19 operating income Rs 110.61Cr. Written email remains unverified; call first, then ask for correct owner email. | [2026-05-02 night] Kakda refresh: GIA product directory lists kakdaindustries@gmail.com, 0755-4280911, Neeraj Goel 9826058625; Unit-II lists goelbaaba@yahoo.co.in, Meenu Goel 9425008604. Brickwork verifies conversion to partnership by Narendra K. Goel and sons, 150 tpd TMT capacity, Rs 13.40Cr bank facility, and Rs 110.61Cr FY19 operating income. Decision-gap angle: working-capital, raw-material, dealer-credit, and procurement calls need validation before commitment.
A150: SCR-CA-040 | B150: Anurag Pandey | C150: Lucknow Branch of CIRC of ICAI | D150: CA | E150: B | F150: New | H150: Queue as large-branch expansion after Bhopal/Indore/CIRC first-wave touches are logged. Use Anurag Pandey and Rishabh Mishra first; ask who owns member programming around client decisions that looked informed but were not validated. | I150: 2026-05-03 | J150: Waiting | K150: Channel: PCSANDASSOCIATES@GMAIL.COM | ca.rishabhmishra@gmail.com | lucknow@icai.org | Chairman 9415075740 | Secretary 9935459122 | Branch 0522-4069931 | Contact: CA Anurag Pandey | Chairman | Mobile 9415075740 | Email PCSANDASSOCIATES@GMAIL.COM; CA Rishabh Mishra | Secretary | Mobile 9935459122 | Email ca.rishabhmishra@gmail.com; Lucknow Branch | Phone 0522-4069931 | Email lucknow@icai.org | Source: Contact CA Associations | Decision_Gap: A large branch can test whether CAs recognize the repeated client pattern: enough information, strong confidence, but no independent validation before capital moved. | Official CIRC Lucknow Office Bearer PDF 2025-2026 verifies chairman, secretary, direct mobiles/emails, branch phone, branch email, and website. Keep Tier B until MP first-wave CA route is worked.
A151: SCR-CA-041 | B151: Niraj Kumar Singh | C151: Varanasi Branch of CIRC of ICAI | D151: CA | E151: B | F151: New | H151: Queue as second large-branch test after Bhopal/Indore and one regional route are logged. Use chairman + secretary route and keep the ask to one practical member conversation on decision validation before client money moves. | I151: 2026-05-03 | J151: Waiting | K151: Channel: singhniraj3037@gmail.com | cavikasdwivedee@gmail.com | varanasi@icai.in | Chairman 9454053317 / 8299256912 | Secretary 9044174249 / 7376551117 | Staff 9919672555 | Branch 0542-2585192 | Contact: CA Niraj Kumar Singh | Chairman | Mobiles 9454053317 / 8299256912 | Email singhniraj3037@gmail.com; CA Vikas Dwivedee | Secretary | Mobiles 9044174249 / 7376551117 | Email cavikasdwivedee@gmail.com; Gyan Prakash Tripathi | Branch staff | Mobile 9919672555; Varanasi Branch | Phone 0542-2585192 | Email varanasi@icai.in | Source: Contact CA Associations | Decision_Gap: Varanasi gives another active CIRC branch route to validate whether client-decision failures resonate beyond MP without turning Fnomo into generic education. | Official CIRC Varanasi Office Bearer PDF 2025-2026 verifies chairman, secretary, staff route, direct emails/mobiles, branch email, branch phone, and website. Keep queued behind Tier A local CA execution.
A152: SCR-DR-001 | B152: Dr. Ajay Goenka | C152: Chirayu Medical College | D152: Business | E152: B | F152: Contacted | G152: 2026-05-01 | H152: Follow up on the sent outreach and reopen the decision-validation angle with one concrete question tied to their last wrong financial or commercial decision. | I152: 2026-05-03 | J152: Active | K152: Specialty: Medicine | Email: info@cmchbhopal.com | [2026-05-01] Outreach sent via email. Verified in docs/bhopal_send_log.txt. No reply logged yet. | [2026-05-01] Zoho sent: You read data for a living — what about your portfolio? | info@cmchbhopal.com | status=success
A153: SCR-DR-002 | B153: Dr. Skand Kumar Trivedi | C153: Bansal Hospital | D153: Business | E153: B | F153: Contacted | G153: 2026-05-01 | H153: Follow up on the sent outreach and reopen the decision-validation angle with one concrete question tied to their last wrong financial or commercial decision. | I153: 2026-05-03 | J153: Active | K153: Specialty: Cardiology | Email: skand.trivedi@bansalhospital.com | [2026-05-01] Outreach sent via email. Verified in docs/bhopal_send_log.txt. No reply logged yet. | [2026-05-01] Zoho sent: You read data for a living — what about your portfolio? | skand.trivedi@bansalhospital.com | status=success
A154: SCR-DR-003 | B154: Dr. Gopal Batni | C154: Apollo Sage Hospital | D154: Business | E154: B | F154: Contacted | G154: 2026-05-01 | H154: Follow up on the sent outreach and reopen the decision-validation angle with one concrete question tied to their last wrong financial or commercial decision. | I154: 2026-05-03 | J154: Active | K154: Specialty: Internal Med | Email: gopal.batni@apollosage.in | [2026-05-01] Outreach sent via email. Verified in docs/bhopal_send_log.txt. No reply logged yet. | [2026-05-01] Zoho sent: You read data for a living — what about your portfolio? | gopal.batni@apollosage.in | status=success
A155: SCR-DR-004 | B155: Dr. Shyam Agrawal | C155: Navodaya Oncology | D155: Business | E155: B | F155: Contacted | G155: 2026-05-01 | H155: Follow up on the sent outreach and reopen the decision-validation angle with one concrete question tied to their last wrong financial or commercial decision. | I155: 2026-05-03 | J155: Active | K155: Specialty: Oncology | Email: contact@navodaya.com | [2026-05-01] Outreach sent via email. Verified in docs/bhopal_send_log.txt. No reply logged yet. | [2026-05-01] Zoho sent: You read data for a living — what about your portfolio? | contact@navodaya.com | status=hasretry
A156: SCR-DR-005 | B156: Dr. Kavita Singh | C156: GMC / Private Clinic | D156: Business | E156: B | F156: Contacted | G156: 2026-05-01 | H156: Follow up on the previous outreach and ask about the last financial decision that felt informed but was never independently validated. | I156: 2026-05-03 | J156: Active | K156: Specialty: Gynaecology | Email: kavita.singh@gmc.edu.in | [2026-05-01] Outreach sent via email. Verified in docs/bhopal_send_log.txt. No reply logged yet.
A157: SCR-DR-006 | B157: Dr. Aaditya Sirohi | C157: AIIMS Bhopal | D157: Business | E157: B | F157: Contacted | G157: 2026-05-01 | H157: Follow up on the sent outreach and reopen the decision-validation angle with one concrete question tied to their last wrong financial or commercial decision. | I157: 2026-05-03 | J157: Active | K157: Specialty: CTVS Surgery | Email: aaditya.ctvs@aiimsbhopal.edu.in | [2026-05-01] Outreach sent via email. Verified in docs/bhopal_send_log.txt. No reply logged yet. | [2026-05-01] Zoho sent: Evidence-based investing — does this exist? | aaditya.ctvs@aiimsbhopal.edu.in | status=success
A158: SCR-DR-007 | B158: Dr. Rohit Joshi | C158: Bansal Hospital | D158: Business | E158: B | F158: Contacted | G158: 2026-05-01 | H158: Follow up on the sent outreach and reopen the decision-validation angle with one concrete question tied to their last wrong financial or commercial decision. | I158: 2026-05-03 | J158: Active | K158: Specialty: Child Neuro | Email: rohit.joshi@bansalhospital.com | [2026-05-01] Outreach sent via email. Verified in docs/bhopal_send_log.txt. No reply logged yet. | [2026-05-01] Zoho sent: You read data for a living — what about your portfolio? | rohit.joshi@bansalhospital.com | status=success
A159: SCR-DR-008 | B159: Dr. Deepti Gupta | C159: Bansal Hospital | D159: Business | E159: B | F159: Contacted | G159: 2026-05-01 | H159: Follow up on the sent outreach and reopen the decision-validation angle with one concrete question tied to their last wrong financial or commercial decision. | I159: 2026-05-03 | J159: Active | K159: Specialty: Gynaecology | Email: deepti.gupta@bansalhospital.com | [2026-05-01] Outreach sent via email. Verified in docs/bhopal_send_log.txt. No reply logged yet. | [2026-05-01] Zoho sent: You read data for a living — what about your portfolio? | deepti.gupta@bansalhospital.com | status=success
A160: SCR-DR-009 | B160: Dr. Sunil Malik | C160: Arera Heart Clinic | D160: Business | E160: B | F160: Contacted | G160: 2026-05-01 | H160: Follow up on the sent outreach and reopen the decision-validation angle with one concrete question tied to their last wrong financial or commercial decision. | I160: 2026-05-03 | J160: Active | K160: Specialty: Cardiology | Email: sunil.malik@gmail.com | [2026-05-01] Outreach sent via email. Verified in docs/bhopal_send_log.txt. No reply logged yet. | [2026-05-01] Zoho sent: You read data for a living — what about your portfolio? | sunil.malik@gmail.com | status=success
A161: SCR-DR-010 | B161: Dr. Amitabh Sonakiya | C161: MP Nagar Clinic | D161: Business | E161: B | F161: Contacted | G161: 2026-05-01 | H161: Follow up on the previous outreach and ask about the last financial decision that felt informed but was never independently validated. | I161: 2026-05-03 | J161: Active | K161: Specialty: Orthopaedics | Email: amitabh.ortho@yahoo.com | [2026-05-01] Outreach sent via email. Verified in docs/bhopal_send_log.txt. No reply logged yet.
A162: SCR-DR-011 | B162: Dr. Shiv Shanker | C162: Chirayu Medical College | D162: Business | E162: B | F162: Contacted | G162: 2026-05-01 | H162: Follow up on the sent outreach and reopen the decision-validation angle with one concrete question tied to their last wrong financial or commercial decision. | I162: 2026-05-03 | J162: Active | K162: Specialty: Medicine | Email: dean@cmchbhopal.com | [2026-05-01] Outreach sent via email. Verified in docs/bhopal_send_log.txt. No reply logged yet. | [2026-05-01] Zoho sent: You read data for a living — what about your portfolio? | dean@cmchbhopal.com | status=success
A163: SCR-DR-012 | B163: Dr. Nitesh Arora | C163: Chirayu Hospital | D163: Business | E163: B | F163: Contacted | G163: 2026-05-01 | H163: Follow up on the previous outreach and ask about the last financial decision that felt informed but was never independently validated. | I163: 2026-05-03 | J163: Active | K163: Specialty: Cardiology | Email: nitesh.cardio@cmchbhopal.com | [2026-05-01] Outreach sent via email. Verified in docs/bhopal_send_log.txt. No reply logged yet.
... A214: SCR-EM-014 | B214: Corporate Slot 5 | C214: Corporate Slot 5 | D214: Business | E214: B | F214: Contacted | G214: 2026-04-30 | H214: Follow up on the sent outreach and reopen the decision-validation angle with one concrete question tied to their audience, members, or last decision bottleneck. | I214: 2026-05-02 | J214: Active | K214: Email: tbd@corporate.com | [2026-04-30] Zoho sent: What if Corporate Slot 5's Leadership Development Initiative Isn't Reaching Its Full Potential? | status=success | Source: Sent folder 8585832000000002022
A215: SCR-BO-043 | B215: Poonam Chouksey | C215: Parvati Sweetners and Power Limited | D215: Business | E215: A | F215: New | H215: Send Poonam Chouksey a listed-manufacturer MD note after the current owner sends are logged; ask about the last commodity, capex, or working-capital decision that looked right before downside appeared. | I215: 2026-05-03 | J215: Active | K215: Channel: info@parvatisweetners.com; info@parvatisweetners.co.in | Phone 0755-4009254 | Contact: Poonam Chouksey | Chairperson & Managing Director / CEO; Anupam Chouksey | Executive Director; Shweta Chouksey | CFO; Khadija Husain | Company Secretary | Source: Official Parvati corporate information, Moneycontrol management profile, and StockAnalysis company profile. | Decision_Gap: Sugar/bioethanol businesses carry procurement, commodity, capex, and cash-cycle decisions where confidence can outrun validation before money moves. | Tier A because listed manufacturing scale, public MD/CEO route, and material capital decisions are explicit. Use after today's Tier A owner sends are logged.
A216: SCR-BO-044 | B216: C. E. Fernandes | C216: GEI Industrial Systems Limited | D216: Business | E216: A | F216: New | H216: Send C.E. Fernandes an industrial-founder note after logged owner sends; anchor on bid, vendor, project, and capex decisions that need validation before commitment. | I216: 2026-05-03 | J216: Active | K216: Channel: pscmd@geiind.com; cs@geiind.com; cmdgei@yahoo.co.in | Phones +91-7554922011, +91-7554926350, +91-7554923011; registered-office 0755-2586691 | Contact: C E Fernandes | Chairman & Managing Director; Bernard John | Joint Managing Director route | Source: Official GEI site, Moneycontrol management/contact profile, and GIA Govindpura listing. | Decision_Gap: Engineering/project businesses make expensive bid, capacity, vendor, and project-risk calls where a pre-action validation layer is commercially legible. | Tier A because public listed/industrial profile and leadership route are explicit.
A217: SCR-BO-045 | B217: Jaspal Singh | C217: C.J. Gelatine Products Limited | D217: Business | E217: A | F217: New | H217: Send Jaspal Singh a chair/MD note after the current Tier A sends are logged; frame around procurement, plant-utilization, export, and quality decisions where a wrong call is expensive before it is visible. | I217: 2026-05-03 | J217: Active | K217: Channel: contact@cjgelatineproducts.com; cjsecretarial@gmail.com | Factory phone 91-7480-423301 | Company-secretary/investor phone 07480-423302 | Contact: Jaspal Singh | Chairman and Managing Director; Harman Singh | Executive Director / Company Secretary route | Source: Official C.J. Gelatine investor-relations page and public board profile. | Decision_Gap: Specialty manufacturing creates procurement, plant-utilization, quality, and market-timing decisions where judgment needs stress-testing before capital is committed. | Tier A because public listed manufacturer with named chair/MD and company-secretary routes.
A218: SCR-BO-046 | B218: Rakesh Agrawal | C218: Autosign Industries | D218: Business | E218: B | F218: New | H218: Keep as queued direct-owner route; call Rakesh Agrawal only after Tier A listed/industrial sends are logged. Verify scale/fit, then ask about the last tender or project commitment that should have been stress-tested earlier. | I218: 2026-05-04 | J218: Waiting | K218: Channel: rakesh@autosignindustries.com; kamal@autosignindustries.com; info@autosignindustries.com | Office 0755-4243311 | Rakesh mobile +91-8602252541 | Kamal mobile +91-9425043311 | Contact: Rakesh Agrawal | Managing Director; Kamal Kishor Agrawal | Chairman | Source: Official Autosign contact page. | Decision_Gap: Road-safety and industrial supply decisions involve tenders, inventory, and project timing where owner confidence can outrun validation. | Tier B until revenue/intent is confirmed; do not add to first-wave owner send.
A219: SCR-BO-047 | B219: Govind Singh Dangi | C219: Farmila Ventures Private Limited | D219: Business | E219: B | F219: New | H219: Queue as agri-machinery owner route; verify scale and active owner availability by phone before promotion, then open on dealer-credit, farmer-equipment, and service-capacity decisions. | I219: 2026-05-04 | J219: Waiting | K219: Channel: gsdangi@gmail.com; pushpendrasingh25@gmail.com; farmilaventures@gmail.com | Phones 9009990650, 9630055837 | Contact: Govind Singh Dangi | Managing Director / Director; Pushpendra Singh | Managing Director / Director | Source: Official Farmila managing-director page plus public company profiles confirming active director roles. | Decision_Gap: Agri-equipment businesses sit between dealer judgment and farmer capital decisions, making validation before purchase/action a practical angle. | Tier B pending scale validation; keep behind Tier A listed/industrial owner routes.
A220: SCR-CA-042 | B220: Abhay Chhajed | C220: CIRC / Bhopal Ex-Officio Route | D220: CA | E220: A | F220: New | H220: Use as Bhopal ex-officio escalation after Arpit/Abhishek first follow-up is logged; ask whether branch/CIRC programming can own a member conversation on client decisions that looked informed but were never validated. | I220: 2026-05-04 | J220: Active | K220: Channel: chhajed_abhay@hotmail.com | Mobile 9009044477 | Contact: CA Abhay Kumar Chhajed | Central Council Member; Bhopal ex-officio route | Source: Current CIRC regional/central council page and CIRC ex-officio listing. | Decision_Gap: Bhopal ex-officio authority can unblock branch ownership if the ask stays on client decision-quality before capital moves, not generic awareness. | Tier A escalation because Bhopal route, direct public mobile/email, and Central Council role are explicit. | [2026-05-02 evening] Official CIRC ex-officio 2026-27 PDF confirms Bhopal ex-officio CA Abhay Chhajed-CCM; keep behind Bhopal chair/secretary follow-up.
A221: SCR-CA-043 | B221: Anand Jain | C221: CIRC / Indore Regional Council Route | D221: CA | E221: B | F221: New | H221: Hold as Indore regional support after Rajat/Milind touches and first follow-up are logged; ask who owns member programming for validating client decisions before money moves. | I221: 2026-05-04 | J221: Waiting | K221: Channel: anandjain812@gmail.com | Mobile 8818800095 | Contact: CA Anand Jain | Regional Council Member, Indore | Source: Current CIRC regional/central council page and Indore ICAI torch-bearers page. | Decision_Gap: Regional Indore support is useful if branch ownership stalls; the conversation must stay about decision validation as member value. | Tier B support route behind local chair/secretary execution. | [2026-05-02 evening] Official CIRC ex-officio 2026-27 PDF confirms Indore support includes CA Anand Jain-RCM and member CICASA; keep behind local Indore route.
A222: SCR-CA-044 | B222: Pankaj Shah | C222: CIRC / Indore Central Council Route | D222: CA | E222: B | F222: New | H222: Hold as Central Council escalation behind Indore chair/secretary and Anand Jain; use only if local ownership stalls or a higher-authority routing note is needed. | I222: 2026-05-04 | J222: Waiting | K222: Channel: pankajgshah@gmail.com | Mobile 9691893040 | Contact: CA Pankaj Shah | Central Council Member, Indore | Source: Current CIRC regional/central council page and public ICAI committee profile. | Decision_Gap: Central Council route can validate regional relevance, but only after local branch contact proves the client-decision gap is concrete. | Tier B escalation route; do not bypass local trust sequence. | [2026-05-02 evening] Official CIRC ex-officio 2026-27 PDF confirms Indore support includes CA Pankaj Shah-CCM; use only after local ownership stalls.
A223: WA-CA-001 | B223: Rajesh Jain | C223: Jain & Associates | D223: CA | E223: A | F223: Contacted | G223: 2026-05-02 | H223: Follow-up 1 via WhatsApp if no reply | I223: 2026-05-04 | J223: Active | K223: Channel: WhatsApp 91-9820123456 | Email: rajesh.jain@jainassociates.in | Title: Chartered Accountant | City: Mumbai | Source: User screenshot WhatsApp batch | Decision_Gap: Lead has been touched through WhatsApp; next conversation must reconstruct last wrong financial or business decision before positioning Fnomo. | [2026-05-02] WhatsApp contacted via user screenshot batch
A224: WA-CA-002 | B224: Priya Mehta | C224: Mehta Tax Consultants | D224: CA | E224: A | F224: Contacted | G224: 2026-05-02 | H224: Follow-up 1 via WhatsApp if no reply | I224: 2026-05-04 | J224: Active | K224: Channel: WhatsApp 91-9810234567 | Email: priya.mehta@mehtatax.com | Title: Senior CA | City: Delhi | Source: User screenshot WhatsApp batch | Decision_Gap: Lead has been touched through WhatsApp; next conversation must reconstruct last wrong financial or business decision before positioning Fnomo. | [2026-05-02] WhatsApp contacted via user screenshot batch
A225: WA-CA-003 | B225: Suresh Kumar | C225: SKR Partners | D225: CA | E225: A | F225: Contacted | G225: 2026-05-02 | H225: Follow-up 1 via WhatsApp if no reply | I225: 2026-05-04 | J225: Active | K225: Channel: WhatsApp 91-9845678901 | Email: suresh@skrpartners.co.in | Title: Practicing CA | City: Bangalore | Source: User screenshot WhatsApp batch | Decision_Gap: Lead has been touched through WhatsApp; next conversation must reconstruct last wrong financial or business decision before positioning Fnomo. | [2026-05-02] WhatsApp contacted via user screenshot batch
A226: WA-CA-004 | B226: Ankita Shah | C226: Shah Financial Services | D226: CA | E226: A | F226: Contacted | G226: 2026-05-02 | H226: Follow-up 1 via WhatsApp if no reply | I226: 2026-05-04 | J226: Active | K226: Channel: WhatsApp 91-9824567890 | Email: ankita.shah@shahfinancial.in | Title: CA - FCA | City: Ahmedabad | Source: User screenshot WhatsApp batch | Decision_Gap: Lead has been touched through WhatsApp; next conversation must reconstruct last wrong financial or business decision before positioning Fnomo. | [2026-05-02] WhatsApp contacted via user screenshot batch
A227: WA-CA-005 | B227: Vivek Nair | C227: Nair & Co. Chartered Accountants | D227: CA | E227: A | F227: Contacted | G227: 2026-05-02 | H227: Follow-up 1 via WhatsApp if no reply | I227: 2026-05-04 | J227: Active | K227: Channel: WhatsApp 91-9841234567 | Email: vivek@nairandco.in | Title: Senior Partner | City: Chennai | Source: User screenshot WhatsApp batch | Decision_Gap: Lead has been touched through WhatsApp; next conversation must reconstruct last wrong financial or business decision before positioning Fnomo. | [2026-05-02] WhatsApp contacted via user screenshot batch
A228: WA-CA-006 | B228: Deepa Verma | C228: Verma Tax Advisory | D228: CA | E228: A | F228: Contacted | G228: 2026-05-02 | H228: Follow-up 1 via WhatsApp if no reply | I228: 2026-05-04 | J228: Active | K228: Channel: WhatsApp 91-9823456789 | Email: deepa.verma@vermatax.in | Title: CA - DISA | City: Pune | Source: User screenshot WhatsApp batch | Decision_Gap: Lead has been touched through WhatsApp; next conversation must reconstruct last wrong financial or business decision before positioning Fnomo. | [2026-05-02] WhatsApp contacted via user screenshot batch
A229: WA-CA-007 | B229: Arun Gupta | C229: Gupta & Associates | D229: Business | E229: B | F229: Contacted | G229: 2026-05-02 | H229: Follow-up 1 via WhatsApp if no reply | I229: 2026-05-04 | J229: Active | K229: Channel: WhatsApp 91-9848901234 | Email: arun.gupta@guptaassoc.in | Title: Managing Partner | City: Hyderabad | Source: User screenshot WhatsApp batch | Decision_Gap: Lead has been touched through WhatsApp; next conversation must reconstruct last wrong financial or business decision before positioning Fnomo. | [2026-05-02] WhatsApp contacted via user screenshot batch
A230: WA-CA-008 | B230: Meera Krishnan | C230: MK Financial Advisors | D230: CA | E230: A | F230: Contacted | G230: 2026-05-02 | H230: Follow-up 1 via WhatsApp if no reply | I230: 2026-05-04 | J230: Active | K230: Channel: WhatsApp 91-9846789012 | Email: meera@mkfinancial.in | Title: Chartered Accountant | City: Kochi | Source: User screenshot WhatsApp batch | Decision_Gap: Lead has been touched through WhatsApp; next conversation must reconstruct last wrong financial or business decision before positioning Fnomo. | [2026-05-02] WhatsApp contacted via user screenshot batch
A231: WA-CA-009 | B231: Ravi Shankar | C231: RS Chartered Accountants | D231: CA | E231: A | F231: Contacted | G231: 2026-05-02 | H231: Follow-up 1 via WhatsApp if no reply | I231: 2026-05-04 | J231: Active | K231: Channel: WhatsApp 91-9829012345 | Email: ravi.shankar@rscharteredCA.in | Title: CA Partner | City: Jaipur | Source: User screenshot WhatsApp batch | Decision_Gap: Lead has been touched through WhatsApp; next conversation must reconstruct last wrong financial or business decision before positioning Fnomo. | [2026-05-02] WhatsApp contacted via user screenshot batch
A232: WA-CA-010 | B232: Nisha Patel | C232: NP Tax Solutions | D232: CA | E232: A | F232: Contacted | G232: 2026-05-02 | H232: Follow-up 1 via WhatsApp if no reply | I232: 2026-05-04 | J232: Active | K232: Channel: WhatsApp 91-9825678901 | Email: nisha.patel@nptaxsolutions.com | Title: Senior CA | City: Surat | Source: User screenshot WhatsApp batch | Decision_Gap: Lead has been touched through WhatsApp; next conversation must reconstruct last wrong financial or business decision before positioning Fnomo. | [2026-05-02] WhatsApp contacted via user screenshot batch
A233: WA-BIZ-001 | B233: Ramesh Agarwal | C233: Agarwal Traders Pvt Ltd | D233: Business | E233: B | F233: Contacted | G233: 2026-05-02 | H233: Follow-up 1 via WhatsApp if no reply | I233: 2026-05-04 | J233: Active | K233: Channel: WhatsApp 91-9826789012 | Email: ramesh@agarwaltraders.in | Title: Director | City: Indore | Source: User screenshot WhatsApp batch | Decision_Gap: Lead has been touched through WhatsApp; next conversation must reconstruct last wrong financial or business decision before positioning Fnomo. | [2026-05-02] WhatsApp contacted via user screenshot batch
A234: WA-BIZ-002 | B234: Hiren Shah | C234: Shah Electronics Pvt Ltd | D234: Business | E234: B | F234: Contacted | G234: 2026-05-02 | H234: Follow-up 1 via WhatsApp if no reply | I234: 2026-05-04 | J234: Active | K234: Channel: WhatsApp 91-9824123456 | Email: hiren.shah@shahelectronics.in | Title: Managing Director | City: Rajkot | Source: User screenshot WhatsApp batch | Decision_Gap: Lead has been touched through WhatsApp; next conversation must reconstruct last wrong financial or business decision before positioning Fnomo. | [2026-05-02] WhatsApp contacted via user screenshot batch
... A242: WA-BIZ-010 | B242: Geeta Pandey | C242: Pandey Food Processing | D242: Business | E242: B | F242: Contacted | G242: 2026-05-02 | H242: Follow-up 1 via WhatsApp if no reply | I242: 2026-05-04 | J242: Active | K242: Channel: WhatsApp 91-9812345678 | Email: geeta.pandey@pandeyfoods.in | Title: Director | City: Lucknow | Source: User screenshot WhatsApp batch | Decision_Gap: Lead has been touched through WhatsApp; next conversation must reconstruct last wrong financial or business decision before positioning Fnomo. | [2026-05-02] WhatsApp contacted via user screenshot batch
A243: PLAT-001 | B243: Ujwal Kumar | C243: Zomato | D243: Association | E243: B | F243: New | H243: Send first platform partnership outreach | I243: 2026-05-03 | J243: Active | K243: Source: platform partnership outreach table | SheetStatus: Not Contacted | LinkedIn: linkedin.com/in/ACoAAAdGMZsBVa_ZxjzuRnsaZZG1yQY0jeo-tL4 | Company LinkedIn: linkedin.com/company/zomato | Website: zomato.com | Email: missing | Mobile: missing | [2026-05-02] Platform partnership source row refreshed
A244: PLAT-002 | B244: Seetesh Srivastava | C244: Blinkit | D244: Association | E244: B | F244: New | H244: Send first platform partnership outreach | I244: 2026-05-03 | J244: Active | K244: Source: platform partnership outreach table | SheetStatus: Not Contacted | LinkedIn: linkedin.com/in/ACoAAAKGUaAB2gcDBsF6wutpfzsqg57BQ0KtKWQ | Company LinkedIn: linkedin.com/company/letsblinkit | Website: blinkit.com | Email: missing | Mobile: missing | [2026-05-02] Platform partnership source row refreshed
...

Sheet FNOMO_TASK_MAP
A1: TASK TO PIPELINE MAP
A2: Raw meeting mandate translated into pipeline-ready action items.
A4: Task_Name | B4: Category | C4: Parent_Task | D4: Mapped_Lead_Name | E4: Entry_Type | F4: Owner | G4: Next_Action | H4: Next_Action_Date | I4: Notes
A5: Contact Doctor Associations | B5: Partnerships | C5: Partnerships | D5: Doctor Associations | E5: Action | F5: Codex | G5: Build a 15-target list of city, state, and specialty doctor associations before first outreach. | H5: 2026-05-02 | I5: Associations host decision moments but are not yet framed as channels for financial decision validation.
A6: Contact Business Associations | B6: Partnerships | C6: Partnerships | D6: Business Associations | E6: Action | F6: Codex | G6: Shortlist chambers and local trade groups whose members routinely advise or influence capital decisions. | H6: 2026-05-02 | I6: Business associations see the cost of poor decisions but do not yet recognize validation as a member need.
A7: Contact CA Associations | B7: Partnerships | C7: Partnerships | D7: CA Associations | E7: Action | F7: Codex | G7: Identify Bhopal and MP CA bodies plus the senior office bearers who can approve a pilot conversation. | H7: 2026-05-02 | I7: CAs influence financial choices daily, but their communities still treat wrong investment calls as knowledge gaps instead of validation gaps.
A8: Identify Business Owners >2Cr | B8: Partnerships | C8: Partnerships | D8: Identify Business Owners >2Cr | E8: Action | F8: Codex | G8: Create a first 20-account list of profitable owner-led businesses with visible expansion or treasury decisions. | H8: 2026-05-02 | I8: High-liquidity owners make costly capital choices without a validation layer before action.
A9: Reach out Practo | B9: Platform | C9: Platform Tie-ups | D9: Practo | E9: Action | F9: Codex | G9: Use named Practo operators to frame Fnomo as a decision-quality layer for patient and health-spend choices. | H9: 2026-05-02 | I9: Practo reduces discovery friction, but patients still make poor downstream decisions without validation.
A10: Reach out Blinkit | B10: Platform | C10: Platform Tie-ups | D10: Blinkit | E10: Action | F10: Codex | G10: Open with an operations-led angle on high-frequency purchase decisions and employee financial wellness. | H10: 2026-05-02 | I10: Fast commerce excels at speed, but speed amplifies bad decisions when judgment is unvalidated.
A11: Reach out Zomato | B11: Platform | C11: Platform Tie-ups | D11: Zomato | E11: Action | F11: Codex | G11: Start with the supply-chain or ops leader who feels the cost of impulsive consumer choices most directly. | H11: 2026-05-02 | I11: Marketplace behavior is rich with rapid decisions, but nobody owns validation before action.
A12: Reach out Swiggy | B12: Platform | C12: Platform Tie-ups | D12: Swiggy | E12: Action | F12: Codex | G12: Frame a pilot around employee or customer decision moments rather than generic brand partnership language. | H12: 2026-05-02 | I12: Swiggy sits near daily spending decisions yet lacks a validation narrative before spending action.
A13: Reach out MyGate | B13: Platform | C13: Platform Tie-ups | D13: MyGate | E13: Action | F13: Codex | G13: Identify the business or partnerships lead and position Fnomo around household money and trust decisions. | H13: 2026-05-02 | I13: MyGate touches communities at the moment of local trust decisions but does not yet convert that into validation-led engagement.
A14: Explore National Platforms | B14: Platform | C14: Platform Tie-ups | D14: Explore National Platforms | E14: Action | F14: Codex | G14: Rank ten scalable platforms by access to high-consequence decision moments before new outreach begins. | H14: 2026-05-02 | I14: Scale channels are available, but channel selection is not yet tied to where decisions actually happen.
A15: Explore Event Platforms | B15: Platform | C15: Platform Tie-ups | D15: Explore Event Platforms | E15: Action | F15: Codex | G15: List webinar, ticketing, and community platforms that already aggregate decision-curious audiences. | H15: 2026-05-02 | I15: Fnomo needs borrowed attention from moments of active evaluation, not broad awareness alone.
... A40: Free Investing Sessions | B40: Campaign | C40: Campaign | D40: Free Investing Sessions | E40: Action | F40: Codex | G40: Reframe free sessions as decision-diagnosis sessions so they build seriousness instead of casual attendance. | H40: 2026-05-02 | I40: Free sessions attract attention, but not necessarily conviction, unless the decision pain is explicit.

Sheet FNOMO_EXECUTION_LOG
A1: FNOMO EXECUTION LOG - TODO MODE
A2: DATE: 02/05/2026
A4: Actions Taken | B4: Results
A5: Read the live To do tab and discarded the template-noise columns. | B5: 11 leads created.
A6: Split every live row into lead or action based on the execution rule plus mandatory overrides. | B6: 25 tasks created.
A7: Rebuilt the lead pipeline with Kush as owner and a fixed follow-up clock. | B7: 8 outreach messages generated.
A8: Generated ready-to-send Tier A outreach and school messages. | B8: No broken leads in the current pass.
A10: Current Progress Refresh | B10: Dashboard and progress sheet now reflect FNOMO_MASTER_PIPELINE.
A11: Pipeline status | B11: 185 total leads; 99 contacted; 86 new; 21 Tier A still new.
A12: WhatsApp lead batch | B12: 20 WA rows mirrored from WHATSAPP_CA_LEADS; follow-up due 2026-05-04.

Sheet FNOMO_EXECUTION_TASKS
A1: FNOMO EXECUTION TASKS
A2: Internal actions extracted from the To do tab and sorted by execution urgency.
A4: Task_ID | B4: Task | C4: Owner | D4: Priority | E4: Next_Action | F4: Deadline | G4: Status | H4: Related_Segment | I4: Notes
A5: TDA-010 | B5: Email Outreach | C5: Indu | D5: A | E5: Send email outreach today to The Sanskaar Valley School, Delhi Public School, Kolar Road, Delhi Public School, Neelbad. | F5: 2026-05-02 | G5: Execute Today | H5: School | I5: Source: To do tab row 24.
A6: TDA-011 | B6: WhatsApp Outreach | C6: Indu | D6: A | E6: Prepare WhatsApp follow-ups for The Sanskaar Valley School, Delhi Public School, Kolar Road, Delhi Public School, Neelbad after email delivery. | F6: 2026-05-02 | G6: Execute Today | H6: School | I6: Source: To do tab row 25.
A7: TDA-015 | B7: Create Demo Video | C7: Kush | D7: B | E7: Storyboard one decision-failure example that can support partner outreach later. | F7: 2026-05-04 | G7: Within 48h | H7: Execution | I7: Source: To do tab row 31.
A8: TDA-007 | B8: Create Outreach Script | C8: Kush | D8: B | E8: Finalize one email and one WhatsApp script for schools using decision-gap framing. | F8: 2026-05-04 | G8: Within 48h | H8: School | I8: Source: To do tab row 21.
A9: TDA-004 | B9: Define Target Schools | C9: Kush | D9: B | E9: Confirm the first school shortlist from the institutional tab and freeze Tier A pilot names. | F9: 2026-05-04 | G9: Within 48h | H9: School | I9: Source: To do tab row 18.
A10: TDA-005 | B10: Identify Decision Makers | C10: Kush | D10: B | E10: Fill principal, admin, or trustee names for every priority school row. | F10: 2026-05-04 | G10: Within 48h | H10: School | I10: Source: To do tab row 19.
A11: TDA-009 | B11: Identify Pilot Schools | C11: Kush | D11: B | E11: Select the first three schools for immediate outreach and note why each one was chosen. | F11: 2026-05-04 | G11: Within 48h | H11: School | I11: Source: To do tab row 23.
A12: TDA-013 | B12: Platform Placement | C12: Kush | D12: B | E12: Define where Fnomo should appear inside partner flows only after first partner responses. | F12: 2026-05-04 | G12: Within 48h | H12: Execution | I12: Source: To do tab row 28.
A13: TDA-006 | B13: Prepare Contact List | C13: Kush | D13: B | E13: Create one send-ready school contact list with email, phone, and owner. | F13: 2026-05-04 | G13: Within 48h | H13: School | I13: Source: To do tab row 20.
A14: TDA-003 | B14: School Outreach Plan | C14: Kush | D14: B | E14: Lock the school outreach sequence and define the send order before any bulk messaging. | F14: 2026-05-04 | G14: Within 48h | H14: School | I14: Source: To do tab row 17.
A15: TDA-017 | B15: Setup Telegram System | C15: Kush | D15: B | E15: Map the community outreach logging flow before live sends. | F15: 2026-05-04 | G15: Within 48h | H15: Execution | I15: Source: To do tab row 33.
... A29: TDA-023 | B29: Women Investing Webinars | C29: Kush | D29: C | E29: Ignore for now. | F29: 2026-05-09 | G29: Ignore For Now | H29: Campaign | I29: Source: To do tab row 41.

Sheet FNOMO_OUTREACH_READY
A1: FNOMO OUTREACH READY
A2: Tier A messages ready to send plus school email and WhatsApp outreach.
A4: Lead_Name | B4: Channel | C4: Owner | D4: Next_Action_Date | E4: Followup_1_Date | F4: Followup_2_Date | G4: Cold_Date | H4: Subject | I4: Message
A5: Blinkit | B5: firozalam@blinkit.com; rish_invincible@yahoo.com; activatedspidey00@gmail.com | C5: Kush | D5: 2026-05-02 | E5: 2026-05-04 | F5: 2026-05-06 | G5: 2026-05-09 | H5: Fast decisions are not the same as good decisions | I5: Hi Firoz, Blinkit lives in moments where people move fast and decide even faster. What stands out to me is that convenience reduces friction, but it does not improve judgment. In many cases it amplifies poor decision habits. Fnomo exists in that space before action, where the decision itself needs validation. I’d like to explore whether there is a meaningful fit here rather than force a generic partnership pitch. Would a short conversation be worth it? Kush
A6: Business Owners >2Cr | B6: ne@naharindia.com; sandeepwadhwani14@gmail.com; pwcvpl@hotmail.com; sumitlalwani66@gmail.com; svarliyani@gmail.com; yantrainfotech@gmail.com; kgbansal2@gmail.com; salesenquiry.ee@gmail.com; star.delta@rediffmail.com; sdtl.bhopal@gmail.com; vijay_bora@hotmail.com; contact@hindpharmaindia.com; sales@hindpharma.com; tesla@teslaindia.co; mktg@teslatransformers.com; info@parvatisweetners.com; info@parvatisweetners.co.in; pscmd@geiind.com; cs@geiind.com; contact@cjgelatineproducts.com; cjsecretarial@gmail.com | C6: Kush | D6: 2026-05-02 | E6: 2026-05-04 | F6: 2026-05-06 | G6: 2026-05-09 | H6: What was the last expensive decision that looked right at the time? | I6: Hi [Name], I am reaching out because owner-led businesses often lose money on decisions that did not look reckless at the time. They looked reasonable: a stock call, a vendor commitment, an expansion move, or a personal capital decision made with confidence. What was the last expensive decision you were confident about, but later wished you had stress-tested before acting? Fnomo is built around that gap: validating the decision before money moves. Worth a short conversation? Kush Operator note: send first-wave owner emails first. If logged today, use named industrial Tier A routes next: B.K., S.K., Electro Auto, T S Industrys, Cee Dee, Enterprising Engineers. Do not add generic inboxes to the same send. Priority addendum: Enterprising Engineers now has direct MD/CEO/partner routes; new GIA industrial contacts stay queued until Tier A owner sends are logged. Latest enrichment addendum: added Star Delta, Bora Brothers, Hind Pharma, and Tesla as public direct leadership routes. Send only after the earlier Tier A owner batch is logged, unless capacity allows a second owner batch today. Latest enrichment addendum: Righill is now a Tier A director route; Sameer, Evergreen, Crown, Dawn, and S M Motors are queued public routes. Do not add queued Tier B contacts to the first send wave until logged owner sends or scale validation justify it. Latest enrichment addendum: Kumaran and Kakda are now scale-supported Tier A routes. Use only after the current owner batch is logged; verify Kakda written email before any email send and keep the first touch on working-capital/procurement decision quality. Latest enrichment addendum: direct public contact fields are now explicit in master rows for Righill, Sameer, Kumaran, and Kakda. Use Righill/Kumaran/Kakda only after current Tier A sends are logged; Sameer stays queued Tier B pending scale validation. Overnight addendum: Parvati/GEI/C.J. Gelatine are now Tier A official leadership routes for the next controlled owner batch. Autosign/Farmila remain queued until scale is confirmed. Do not expand first-wave recipients until current owner sends are logged. Overnight addendum: Parvati, GEI, and C.J. Gelatine now have strengthened public listed-company routes in the master pipeline. Use them as the next controlled Tier A batch only after the existing owner sends are logged. Autosign and Farmila have direct public owner/mobile routes but stay queued for scale/intent verification. | Night enrichment addendum: use Tesla/Jaideep, Righill/Vinod, Kumaran/Anil-to-K.M., and Kakda call-first as the next Tier A owner-quality routes. Do not add lower-confidence Tier B retail contacts until logged owner follow-ups are complete.
A7: CA Associations | B7: arpit.rai07@gmail.com; caabhishek108@gmail.com; DHANUKA_RAJ17@YAHOO.CO.IN; milind.wadhwani20@gmail.com; bhopal@icai.org; icaibhopalbranch@gmail.com; camohabesamank@gmail.com; indore@icai.in; indore@icai.org; camausamrathi@gmail.com; SAMKIT.FCA@GMAIL.COM; govind.agarwal@icai.in; circ@icai.in; chhajed_abhay@hotmail.com; anandjain812@gmail.com; pankajgshah@gmail.com | C7: Kush | D7: 2026-05-02 | E7: 2026-05-04 | F7: 2026-05-06 | G7: 2026-05-09 | H7: A question about client decisions that go wrong | I7: Hello [Association Leader], CAs often see the same pattern before damage shows up: a client had information, had confidence, and still made the wrong money decision because the thinking itself was never validated. What was the last client decision your members saw go wrong even though the client believed they had done enough homework? That is the gap Fnomo is built around: decision validation before capital is committed. I would like to explore whether this can create practical member value for your branch. Kush Operator note: send chair/secretary first; use CPE chapter routes only after first-wave touches or Follow-up 1. Keep the ask around client decisions that looked informed but were not validated. Priority addendum: use CA Govind Agarwal only as a regional routing path after Bhopal/Indore chair-secretary touches. CIRC regional council addendum: CA Ankur Goyal, CA Ankush Jain, and CA Nirbhik Gandhi are verified regional escalation routes. Use only after Bhopal/Indore chair-secretary touches or if local ownership is unclear. Latest enrichment addendum: Lucknow and Varanasi CIRC branches are verified 2025-2026 large-branch expansion routes. Keep them queued behind Bhopal/Indore chair-secretary touches and CIRC regional routing. Latest enrichment addendum: CIRC regional, Lucknow, and Varanasi rows now include direct public mobiles/emails. Keep Bhopal/Indore chair-secretary first; use regional/large-branch routes only after first-wave touches are logged or routing stalls. Overnight addendum: Raipur/Jaipur CIRC chair-secretary contacts are now queued expansion routes. Keep Bhopal/Indore and CIRC regional follow-up first; use larger branches only after first-wave action is logged or routing stalls. Overnight addendum: Abhay Chhajed, Anand Jain, and Pankaj Shah have been added as CIRC escalation/support rows. Use Abhay only after Bhopal chair/secretary follow-up is logged; keep Anand/Pankaj behind Indore local trust unless routing stalls. Evening routing note: Bhopal/Indore now have live branch-contact routes from CIRC. Use Samank Mohabe and Mausam Rathi to verify ownership only after the already-contacted chair/secretary follow-ups are logged; Samkit Bhandari is promoted as Indore 2026-27 president route, while Abhay/Anand/Pankaj remain escalation paths. | Night enrichment addendum: Bhopal chair/secretary contacts are reconfirmed from CIRC 2025-26; Samkit Bhandari is the current Indore chairman route. Sequence: Bhopal follow-up, Samkit, then Govind/CIRC escalation only if ownership stalls.
A8: Practo | B8: shoumyan.biswas@practo.com; shoumyan_78@yahoo.com | C8: Kush | D8: 2026-05-02 | E8: 2026-05-04 | F8: 2026-05-06 | G8: 2026-05-09 | H8: Trust alone does not protect decision quality | I8: Hi Shoumyan, Healthcare platforms have solved discovery and trust distribution well. What still remains exposed is the quality of the decisions people make after discovery, especially when confidence outruns validation. That is where Fnomo is positioned: before action, at the point where judgment should be stress-tested. I think there is a non-obvious partnership angle here if you’re open to exploring it briefly. Kush
A9: Swiggy | B9: saurav.goyal@swiggy.in; shilpi.srivastav@swiggy.in; shikhar.baveja@swiggy.in | C9: Kush | D9: 2026-05-02 | E9: 2026-05-04 | F9: 2026-05-06 | G9: 2026-05-09 | H9: Speed changes behavior, but not always for the better | I9: Hi Saurav, Platforms that win on speed also shape behavior. The part most teams miss is that faster action often means weaker reflection before a decision is made. Fnomo is built around that gap: validating the quality of a decision before it turns into action. I’d value a short discussion on whether that logic can become a meaningful collaboration surface for Swiggy. Kush
A10: Zomato | B10: abhimanyu.goyal@zomato.com; ujwal146@yahoo.com | C10: Kush | D10: 2026-05-02 | E10: 2026-05-04 | F10: 2026-05-06 | G10: 2026-05-09 | H10: A speed business still pays for unvalidated decisions | I10: Hi Abhimanyu, Businesses built around speed usually see the cost of bad decisions earlier than most. The problem is not lack of data. It is that action often happens before the thinking gets properly stress-tested. Fnomo is built around that exact gap: validating decision quality before action. I think there is a sharp partnership conversation here around high-frequency money and judgment decisions. Open to a short call this week? Kush
A11: Tier A Schools - Email Outreach | B11: info@sanskaarvalley.org; dpskolar@gmail.com; info@dpsneelbad.com | C11: Indu | D11: 2026-05-02 | E11: 2026-05-04 | F11: 2026-05-06 | G11: 2026-05-09 | H11: School outreach pilot | I11: Subject: The real student investing problem is not lack of information Hello [Principal Name], Most young people do not make poor financial decisions because nobody explained finance to them. They make them because confidence arrives before judgment is validated. That is the gap Fnomo is built around. We are exploring a sharp, institution-facing pilot on better decision quality for students and families, and your school is one of the few where this conversation feels worth having. Would you be open to a short discussion this week? Kush
A12: Tier A Schools - WhatsApp Outreach | B12: 8889533346; 7552433900; 7556611400 | C12: Indu | D12: 2026-05-02 | E12: 2026-05-04 | F12: 2026-05-06 | G12: 2026-05-09 | H12: School outreach follow-up | I12: Hello [Principal Name], this is Kush from Fnomo. Reaching out because the real issue in young investing is rarely lack of information. It is that decisions feel right before they are properly validated. We are shaping a focused school pilot around that exact gap. If relevant, I’d value 10 minutes to share the thought.

Sheet FNOMO_EXECUTION_HISTORY
A1: FNOMO EXECUTION HISTORY
A2: Cumulative log of executed Fnomo work. Update this every time Kush reports a send, contact, reply, or completion.
A4: Date | B4: Action_Type | C4: Lead_or_Task | D4: Owner | E4: Channel | F4: Outcome | G4: Next_Move | H4: Source
A5: 2026-05-02 | B5: System Rebuild | C5: FNOMO_MASTER_PIPELINE | D5: Codex | E5: Workbook | F5: Rebuilt lead pipeline from To do tab | G5: Use this as the live execution sheet | H5: Codex execution
A6: 2026-05-02 | B6: Task Structuring | C6: FNOMO_EXECUTION_TASKS | D6: Codex | E6: Workbook | F6: Built internal execution queue from To do tab | G6: Track completions and deadlines daily | H6: Codex execution
A7: 2026-05-02 | B7: Outreach Drafting | C7: FNOMO_OUTREACH_READY | D7: Codex | E7: Workbook | F7: Prepared 8 ready-to-send messages | G7: Mark sent messages back into history once executed | H7: Codex execution
A8: 2026-05-02 | B8: Operating Model | C8: Fnomo execution workflow | D8: Codex | E8: GitHub | F8: Locked To do as execution mandate and other sheets as enrichment | G8: Use morning and evening automations to maintain rhythm | H8: docs/ops/fnomo_execution_operating_model.md
A9: 2026-05-02 | B9: Lead Enrichment | C9: CA Associations + Business Owners >2Cr | D9: Codex | E9: Workbook + web | F9: Added 13 public contact rows for overnight priority research inside the existing master pipeline | G9: Use these for tomorrow outreach and second-wave enrichment | H9: Overnight scrape pass
A10: 2026-05-02 | B10: Lead Enrichment | C10: Overnight priority enrichment 2026-05-02 | D10: Codex | E10: Workbook + web | F10: Added 12 verified public contact rows and upgraded Deep/Perfect World owner contacts | G10: Execute Tier A CA and owner contacts first; keep unverified-scale retail as Tier B | H10: Overnight priority enrichment automation
A11: 2026-05-02 | B11: Priority Enrichment | C11: Business Owners >2Cr | D11: Codex | E11: Workbook | F11: Promoted/confirmed Tier A owner routes and added verified public contact/source detail | G11: Execute Nahar, Deep, Perfect World, Tirupati, Sapna, Yantra today; call after email touch | H11: Fnomo Overnight Priority Enrichment
A12: 2026-05-02 | B12: Priority Enrichment | C12: CA Associations | D12: Codex | E12: Workbook | F12: Updated first-wave Bhopal/Indore chair-secretary route from public CIRC office-bearer PDFs | G12: Send chair/secretary emails today; keep branch inboxes as backup route | H12: Fnomo Overnight Priority Enrichment
A13: 2026-05-02 | B13: Outreach Copy Cleanup | C13: FNOMO_OUTREACH_READY | D13: Codex | E13: Workbook | F13: Rewrote aggregate Tier A owner and CA messages around last wrong decision / validation gap | G13: Use these as templates; personalize per named contact before sending | H13: Fnomo Overnight Priority Enrichment
A14: 2026-05-02 | B14: Priority Enrichment | C14: CA Associations second-wave routes | D14: Codex | E14: Workbook + web | F14: Added Bhopal/Indore support office-bearer rows with public emails, mobiles, roles, and non-generic decision-gap notes. | G14: Execute chair/secretary Tier A first; use vice-chair/treasurer/CICASA routes only after first-wave touches or Follow-up 1. | H14: Fnomo Overnight Priority Enrichment
A15: 2026-05-02 | B15: Priority Enrichment | C15: Business Owners >2Cr second-wave owner routes | D15: Codex | E15: Workbook + web | F15: Added named Bhopal owner/retail routes for Parshvnath, Gupta, Kumar, and A Z with public emails/phones and tier discipline. | G15: Work existing Tier A owner rows first; promote second-wave only when scale or intent is confirmed. | H15: Fnomo Overnight Priority Enrichment
... A47: 2026-05-02 | B47: Notion Backend Sync | C47: FNOMO_MASTER_PIPELINE | D47: Codex | E47: Notion Internal Integration | F47: Created Notion mirror databases and synced 194 leads plus 42 execution history events | G47: Use stored Notion database IDs for repeat lead and history sync | H47: Codex execution

Sheet WHATSAPP_CA_LEADS
A1: Lead_ID | B1: Name | C1: Title | D1: Company | E1: City | F1: WhatsApp | G1: Email | H1: Segment | I1: Tier | J1: Stage | K1: Last_Contact_Date | L1: Next_Action | M1: Next_Action_Date | N1: Status | O1: Source | P1: Notes
A2: WA-CA-001 | B2: Rajesh Jain | C2: Chartered Accountant | D2: Jain & Associates | E2: Mumbai | F2: 91-9820123456 | G2: rajesh.jain@jainassociates.in | H2: CA | I2: A | J2: Contacted | K2: 2026-05-02 | L2: Follow-up 1 via WhatsApp if no reply | M2: 2026-05-04 | N2: Active | O2: User screenshot WhatsApp batch | P2: Separate lead-bank update; pipeline row mirrors contact status.
A3: WA-CA-002 | B3: Priya Mehta | C3: Senior CA | D3: Mehta Tax Consultants | E3: Delhi | F3: 91-9810234567 | G3: priya.mehta@mehtatax.com | H3: CA | I3: A | J3: Contacted | K3: 2026-05-02 | L3: Follow-up 1 via WhatsApp if no reply | M3: 2026-05-04 | N3: Active | O3: User screenshot WhatsApp batch | P3: Separate lead-bank update; pipeline row mirrors contact status.
A4: WA-CA-003 | B4: Suresh Kumar | C4: Practicing CA | D4: SKR Partners | E4: Bangalore | F4: 91-9845678901 | G4: suresh@skrpartners.co.in | H4: CA | I4: A | J4: Contacted | K4: 2026-05-02 | L4: Follow-up 1 via WhatsApp if no reply | M4: 2026-05-04 | N4: Active | O4: User screenshot WhatsApp batch | P4: Separate lead-bank update; pipeline row mirrors contact status.
A5: WA-CA-004 | B5: Ankita Shah | C5: CA - FCA | D5: Shah Financial Services | E5: Ahmedabad | F5: 91-9824567890 | G5: ankita.shah@shahfinancial.in | H5: CA | I5: A | J5: Contacted | K5: 2026-05-02 | L5: Follow-up 1 via WhatsApp if no reply | M5: 2026-05-04 | N5: Active | O5: User screenshot WhatsApp batch | P5: Separate lead-bank update; pipeline row mirrors contact status.
A6: WA-CA-005 | B6: Vivek Nair | C6: Senior Partner | D6: Nair & Co. Chartered Accountants | E6: Chennai | F6: 91-9841234567 | G6: vivek@nairandco.in | H6: CA | I6: A | J6: Contacted | K6: 2026-05-02 | L6: Follow-up 1 via WhatsApp if no reply | M6: 2026-05-04 | N6: Active | O6: User screenshot WhatsApp batch | P6: Separate lead-bank update; pipeline row mirrors contact status.
A7: WA-CA-006 | B7: Deepa Verma | C7: CA - DISA | D7: Verma Tax Advisory | E7: Pune | F7: 91-9823456789 | G7: deepa.verma@vermatax.in | H7: CA | I7: A | J7: Contacted | K7: 2026-05-02 | L7: Follow-up 1 via WhatsApp if no reply | M7: 2026-05-04 | N7: Active | O7: User screenshot WhatsApp batch | P7: Separate lead-bank update; pipeline row mirrors contact status.
A8: WA-CA-007 | B8: Arun Gupta | C8: Managing Partner | D8: Gupta & Associates | E8: Hyderabad | F8: 91-9848901234 | G8: arun.gupta@guptaassoc.in | H8: CA | I8: A | J8: Contacted | K8: 2026-05-02 | L8: Follow-up 1 via WhatsApp if no reply | M8: 2026-05-04 | N8: Active | O8: User screenshot WhatsApp batch | P8: Separate lead-bank update; pipeline row mirrors contact status.
A9: WA-CA-008 | B9: Meera Krishnan | C9: Chartered Accountant | D9: MK Financial Advisors | E9: Kochi | F9: 91-9846789012 | G9: meera@mkfinancial.in | H9: CA | I9: A | J9: Contacted | K9: 2026-05-02 | L9: Follow-up 1 via WhatsApp if no reply | M9: 2026-05-04 | N9: Active | O9: User screenshot WhatsApp batch | P9: Separate lead-bank update; pipeline row mirrors contact status.
A10: WA-CA-009 | B10: Ravi Shankar | C10: CA Partner | D10: RS Chartered Accountants | E10: Jaipur | F10: 91-9829012345 | G10: ravi.shankar@rscharteredCA.in | H10: CA | I10: A | J10: Contacted | K10: 2026-05-02 | L10: Follow-up 1 via WhatsApp if no reply | M10: 2026-05-04 | N10: Active | O10: User screenshot WhatsApp batch | P10: Separate lead-bank update; pipeline row mirrors contact status.
A11: WA-CA-010 | B11: Nisha Patel | C11: Senior CA | D11: NP Tax Solutions | E11: Surat | F11: 91-9825678901 | G11: nisha.patel@nptaxsolutions.com | H11: CA | I11: A | J11: Contacted | K11: 2026-05-02 | L11: Follow-up 1 via WhatsApp if no reply | M11: 2026-05-04 | N11: Active | O11: User screenshot WhatsApp batch | P11: Separate lead-bank update; pipeline row mirrors contact status.
A12: WA-BIZ-001 | B12: Ramesh Agarwal | C12: Director | D12: Agarwal Traders Pvt Ltd | E12: Indore | F12: 91-9826789012 | G12: ramesh@agarwaltraders.in | H12: Business | I12: B | J12: Contacted | K12: 2026-05-02 | L12: Follow-up 1 via WhatsApp if no reply | M12: 2026-05-04 | N12: Active | O12: User screenshot WhatsApp batch | P12: Separate lead-bank update; pipeline row mirrors contact status.
... A21: WA-BIZ-010 | B21: Geeta Pandey | C21: Director | D21: Pandey Food Processing | E21: Lucknow | F21: 91-9812345678 | G21: geeta.pandey@pandeyfoods.in | H21: Business | I21: B | J21: Contacted | K21: 2026-05-02 | L21: Follow-up 1 via WhatsApp if no reply | M21: 2026-05-04 | N21: Active | O21: User screenshot WhatsApp batch | P21: Separate lead-bank update; pipeline row mirrors contact status.
